Workbook

Sheet DOMO
A1: ID | B1: Origem | C1: Tipologia | D1: Area | E1: Data_Manifestacao | F1: Agente | G1: Status_Solicitação | H1: Status_Acao | I1: Cliente | J1: UC | K1: Obra_Const_Man | L1: Regional | M1: Localidade | N1: Poder | O1: Prefeitura | P1: Manifestação | Q1: Data_Envio_Area | R1: Descricao_da_acao | S1: Data_Resp_Area | T1: Resposta_Area | U1: Expectativa_Cliente | V1: Data_Prev_Acao | W1: Data_Conclusao | X1: Resp_Tratativa | Y1: Registrado_por | Z1: Participantes_Municipio | AA1: Participantes_Energisa_txt | AB1: Critico | AC1: Acao | AD1: Modificado | AE1: Modificado por.title | AF1: Criado | AG1: Criado por.title | AH1: Peso_I_INST | AI1: Peso_I_INST_2 | AJ1: Peso_Geral | AK1: Processo | AL1: Previsao | AM1: Sub_Areas | AN1: Supervisão | AO1: dias das soliictações | AP1: aging | AQ1: Expectativa | AR1: Risco | AS1: Integrar | AT1: SLA | AU1: Area 2
A2: 1008 | B2: Visita Domo de Ferro | C2: Obra | D2: DCMD | E2: 46246 | F2: Monike Chaves | G2: Em Andamento | H2: Em Andamento | K2: 0402600304 | L2: SUL | M2: Coronel Sapucaia | N2: Prefeitura | O2: Coronel Sapucaia | P2: Obra parada precisa remover a estrutura para seguir com a parte interna, prefeitura quer intervir na rede, foi orientando quanto ao risco a segurança, e continuidade do fornecimento. Escola será entregue no dia 02/09/2026 e precisamos que a obra seja atendida antes dessa data. | Q2: 46265 | R2: 0402600304 PROGRAMAR OBRA | S2: 46280 | T2: Reprogramada para 18/09 - devido a contingência | U2: 46273 | V2: 46283 | X2: Amanda Aparecida Teixeira dos Santos | Y2: Amanda Santos | Z2: Thiago Secretario De Administração Prefeitura De Cel Sapucaia | AB2: Sim | AC2: Visita Domo de Ferro | AD2: 46280 | AE2: Amanda Aparecida Teixeira dos Santos | AF2: 46280 | AG2: Amanda Aparecida Teixeira dos Santos | AH2: 100 | AI2: 100 | AJ2: 100 | AN2: =VLOOKUP(M2,[1]municipios!$B:$D,3,0) -> PONTA PORA | AO2: =TODAY()-E2 -> 42 | AP2: =IF(AO2<=5,"0–5 dias",IF(AO2<=15,"6–15 dias",IF(AO2<=16,"16–30 dias",IF(AO2<=30,"30–50 dias",">50 dias")))) -> >50 dias | AQ2: =IF(U2="","Dentro",(IF(IF(W2="",TODAY(),W2)<=U2,"Dentro","Fora"))) -> Fora | AR2: =IF(U2="","Não risco",IF((TODAY()-U2)<=7,"Risco","Não risco")) -> Não risco | AS2: =IF(SEARCH("integrar",P2)>0,"Sim","Não") -> #VALUE! | AT2: =IF(S2="",TODAY()-Q2,S2-Q2) -> 15 | AU2: =VLOOKUP(X2,'pontos focais'!C:D,2,0) -> DCMD Programação de Obra | AV2: =U2-Q2 -> 8
A3: 1009 | B3: Visita Domo de Ferro | C3: Obra | D3: DCMD | E3: 46247 | F3: Monike Chaves | G3: Em Andamento | H3: Em Andamento | K3: 0202601135 | L3: SUL | M3: Maracaju | N3: Prefeitura | O3: Maracaju | P3: Por favor agilizar atendimento da Obra 0202601135. Loteamento Fortaleza III - objeto das matrículas de no 26830 e 26.833 do Cartório de Registro de Imóveis de Maracaju/MS, em atendimento aos 109 lotes, conforme consta no Projeto Elétrico e croqui da locação dos postes para a extensão da rede. | Q3: 46247 | R3: Por favor agilizar atendimento da Obra 0202601135. Loteamento Fortaleza III - objeto das matrículas de no 26830 e 26.833 do Cartório de Registro de Imóveis de Maracaju/MS, em atendimento aos 109 lotes, conforme consta no Projeto Elétrico e croqui da locação dos postes para a extensão da rede. | S3: 46269 | U3: 46259 | V3: 46283 | X3: Amanda Aparecida Teixeira dos Santos | Y3: Amanda Santos | Z3: Prefeito Calderan Gerente de Obras Ariana | AA3: Monike Chaves | AB3: Sim | AC3: Visita Domo de Ferro | AD3: 46269 | AE3: Amanda Aparecida Teixeira dos Santos | AF3: 46269 | AG3: Amanda Aparecida Teixeira dos Santos | AH3: 100 | AI3: 100 | AJ3: 100 | AN3: =VLOOKUP(M3,[1]municipios!$B:$D,3,0) -> RIO BRILHANTE | AO3: =TODAY()-E3 -> 41 | AP3: =IF(AO3<=5,"0–5 dias",IF(AO3<=15,"6–15 dias",IF(AO3<=16,"16–30 dias",IF(AO3<=30,"30–50 dias",">50 dias")))) -> >50 dias | AQ3: =IF(U3="","Dentro",(IF(IF(W3="",TODAY(),W3)<=U3,"Dentro","Fora"))) -> Fora | AR3: =IF(U3="","Não risco",IF((TODAY()-U3)<=7,"Risco","Não risco")) -> Não risco | AS3: =IF(SEARCH("integrar",P3)>0,"Sim","Não") -> #VALUE! | AT3: =IF(S3="",TODAY()-Q3,S3-Q3) -> 22 | AU3: =VLOOKUP(X3,'pontos focais'!C:D,2,0) -> DCMD Programação de Obra | AV3: =U3-Q3 -> 12
A4: 1012 | B4: Visita Domo de Ferro | C4: Obra | D4: DCMD | E4: 46237 | F4: Monike Chaves | G4: Em Andamento | H4: Em Andamento | K4: 0402600456 | L4: SUL | M4: Aral Moreira | N4: Prefeitura | O4: Aral Moreira | P4: PREZADOS 1053824, NÃO FOI ATENDIDO A REDE DO LOTEAMENTO, ANEXO NO PROJETO TEM OS DOCUMENTOS NECESSARIOS PARA ATENDIMENTO, BEM COMO LEI DE CRIAÇÃO. A ENTREGA DAS CASAS SERIAM NO MÊS DE AGOSTO. | Q4: 46262 | R4: Obra 0402600456 - programação de obra | S4: 46269 | T4: PROGRAMADA PARA 18/09 | U4: 46295 | V4: 46283 | X4: Amanda Aparecida Teixeira dos Santos | Y4: Amanda Santos | Z4: PREFEITA ELAINE | AB4: Sim | AC4: Visita Domo de Ferro | AD4: 46269 | AE4: Amanda Aparecida Teixeira dos Santos | AF4: 46269 | AG4: Amanda Aparecida Teixeira dos Santos | AH4: 100 | AI4: 100 | AJ4: 100 | AN4: =VLOOKUP(M4,[1]municipios!$B:$D,3,0) -> PONTA PORA | AO4: =TODAY()-E4 -> 51 | AP4: =IF(AO4<=5,"0–5 dias",IF(AO4<=15,"6–15 dias",IF(AO4<=16,"16–30 dias",IF(AO4<=30,"30–50 dias",">50 dias")))) -> >50 dias | AQ4: =IF(U4="","Dentro",(IF(IF(W4="",TODAY(),W4)<=U4,"Dentro","Fora"))) -> Dentro | AR4: =IF(U4="","Não risco",IF((TODAY()-U4)<=7,"Risco","Não risco")) -> Risco | AS4: =IF(SEARCH("integrar",P4)>0,"Sim","Não") -> #VALUE! | AT4: =IF(S4="",TODAY()-Q4,S4-Q4) -> 7 | AU4: =VLOOKUP(X4,'pontos focais'!C:D,2,0) -> DCMD Programação de Obra | AV4: =U4-Q4 -> 33
A5: 1016 | B5: Visita Domo de Ferro | C5: Atendimento Comercial | D5: DESC | E5: 46247 | F5: Marcelly Arce Avalo Franca | G5: Em Andamento | H5: Em Andamento | K5: 0452600171 | L5: CENTRO | M5: Paraíso das Águas | N5: Diretoria | O5: Paraíso das Águas | P5: OBRA: 0452600171 - ESCOPO: 40 METROS DE EXTENSÃO DE REDE + PONTO DE ENTREGA. PRAZO: 120 DIAS EXPECTATIVA DO CLIENTE: 11/09 CLIENTE SOLICITA PRIORIDADE, ATUALMENTE OPERANDO COM GERADOR. | Q5: 46275 | R5: gerar os de ligação e programar pra 11/09 | S5: 46275 | T5: OS DE LIGAÇÃO GERADAS PEDIDO PROGRAMAÇÃO PARA 11/09, AGUARDANDO CONFIRMAÇÃO | U5: 46276 | V5: 46276 | X5: Marcelly Arce Avalo Franca | Y5: Marcelly Franca | AA5: Thamara Araujo Canteiro Collombelli | AB5: Sim | AC5: Visita Domo de Ferro | AD5: 46275 | AE5: Marcelly Arce Avalo Franca | AF5: 46275 | AG5: Marcelly Arce Avalo Franca | AH5: 100 | AI5: 100 | AJ5: 100 | AN5: =VLOOKUP(M5,[1]municipios!$B:$D,3,0) -> COSTA RICA | AO5: =TODAY()-E5 -> 41 | AP5: =IF(AO5<=5,"0–5 dias",IF(AO5<=15,"6–15 dias",IF(AO5<=16,"16–30 dias",IF(AO5<=30,"30–50 dias",">50 dias")))) -> >50 dias | AQ5: =IF(U5="","Dentro",(IF(IF(W5="",TODAY(),W5)<=U5,"Dentro","Fora"))) -> Fora | AR5: =IF(U5="","Não risco",IF((TODAY()-U5)<=7,"Risco","Não risco")) -> Não risco | AS5: =IF(SEARCH("integrar",P5)>0,"Sim","Não") -> #VALUE! | AT5: =IF(S5="",TODAY()-Q5,S5-Q5) -> 0 | AU5: =VLOOKUP(X5,'pontos focais'!C:D,2,0) -> DESC Agentes de Relacionamento | AV5: =U5-Q5 -> 1
A6: 1016 | B6: Visita Domo de Ferro | C6: Obra | D6: DCMD | E6: 46247 | F6: Marcelly Arce Avalo Franca | G6: Em Andamento | H6: Finalizada | K6: 0452600171 | L6: CENTRO | M6: Paraíso das Águas | N6: Diretoria | O6: Paraíso das Águas | P6: OBRA: 0452600171 - ESCOPO: 40 METROS DE EXTENSÃO DE REDE + PONTO DE ENTREGA. PRAZO: 120 DIAS EXPECTATIVA DO CLIENTE: 11/09 CLIENTE SOLICITA PRIORIDADE, ATUALMENTE OPERANDO COM GERADOR. | Q6: 46248 | R6: Verificar cronograma e executar com o prioridade a obra. | S6: 46280 | U6: 46276 | V6: 46274 | X6: Amanda Aparecida Teixeira dos Santos | Y6: Amanda Santos | AA6: Thamara Araujo Canteiro Collombelli | AB6: Sim | AC6: Visita Domo de Ferro | AD6: 46280 | AE6: Amanda Aparecida Teixeira dos Santos | AF6: 46280 | AG6: Amanda Aparecida Teixeira dos Santos | AH6: 100 | AI6: 100 | AJ6: 100 | AN6: =VLOOKUP(M6,[1]municipios!$B:$D,3,0) -> COSTA RICA | AO6: =TODAY()-E6 -> 41 | AP6: =IF(AO6<=5,"0–5 dias",IF(AO6<=15,"6–15 dias",IF(AO6<=16,"16–30 dias",IF(AO6<=30,"30–50 dias",">50 dias")))) -> >50 dias | AQ6: =IF(U6="","Dentro",(IF(IF(W6="",TODAY(),W6)<=U6,"Dentro","Fora"))) -> Fora | AR6: =IF(U6="","Não risco",IF((TODAY()-U6)<=7,"Risco","Não risco")) -> Não risco | AS6: =IF(SEARCH("integrar",P6)>0,"Sim","Não") -> #VALUE! | AT6: =IF(S6="",TODAY()-Q6,S6-Q6) -> 32 | AU6: =VLOOKUP(X6,'pontos focais'!C:D,2,0) -> DCMD Programação de Obra | AV6: =U6-Q6 -> 28
A7: 1022 | B7: Visita Domo de Ferro | C7: Qualidade | D7: DEOP | E7: 46083 | F7: Julio Cesar dos Santos Antonelo | G7: Em Andamento | H7: Não Iniciada | J7: 30723 | L7: NORTE | M7: Corumbá | N7: Diretoria | O7: Corumbá | P7: Em 02/03/2026 - realizada reunião presencial na Energisa com os diretores da SANESUL para tratar da qualidade de fornecimento das unidades de Corumbá. Conforme documento anexo, cliente reclama de constantes oscilações no fornecimento de energia elétrica nas unidades de Corumbá. | Q7: 46226 | R7: 07/08/2026: Instalar medição nas 2 UC's prioritárias até dia 14/08/2026 14/08/2026: Instalar medição nas 2 UC's prioritárias até dia 18/08/2026. Necessário envolver o time da Gleistuany (GEST) | S7: 46269 | X7: Luan Henrique Soares Diniz Afonso | Y7: Gabriella Domingo | Z7: RENATO MARCILIO DA SILVA | AA7: Julio Cesar dos Santos Antonelo | AB7: Sim | AC7: Visita Domo de Ferro | AD7: 46269 | AE7: Gabriella Amorim Domingo | AF7: 46269 | AG7: Gabriella Amorim Domingo | AH7: 100 | AI7: 100 | AJ7: 100 | AN7: =VLOOKUP(M7,[1]municipios!$B:$D,3,0) -> CORUMBA | AO7: =TODAY()-E7 -> 205 | AP7: =IF(AO7<=5,"0–5 dias",IF(AO7<=15,"6–15 dias",IF(AO7<=16,"16–30 dias",IF(AO7<=30,"30–50 dias",">50 dias")))) -> >50 dias | AQ7: =IF(U7="","Dentro",(IF(IF(W7="",TODAY(),W7)<=U7,"Dentro","Fora"))) -> Dentro | AR7: =IF(U7="","Não risco",IF((TODAY()-U7)<=7,"Risco","Não risco")) -> Não risco | AS7: =IF(SEARCH("integrar",P7)>0,"Sim","Não") -> #VALUE! | AT7: =IF(S7="",TODAY()-Q7,S7-Q7) -> 43 | AU7: =VLOOKUP(X7,'pontos focais'!C:D,2,0) -> DEOP Qualidade | AV7: =U7-Q7 -> -46226
A8: 1027 | B8: Visita Domo de Ferro | C8: Obra | D8: DCMD | E8: 46265 | F8: Monike Chaves | G8: Em Andamento | H8: Em Andamento | K8: 0402600390 | L8: SUL | M8: Antônio João | N8: Prefeitura | O8: Antônio João | P8: Prefeito de Antonio João pedindo prioridade no atendimento dessa obra, pois a obra interna oi paralisada. | Q8: 46252 | S8: 46280 | T8: Reprogramada para 24/09 - devido a contingencia | U8: 46265 | V8: 46289 | X8: Amanda Aparecida Teixeira dos Santos | Y8: Amanda Santos | Z8: Prefeito Marcelo | AB8: Sim | AC8: Visita Domo de Ferro | AD8: 46280 | AE8: Amanda Aparecida Teixeira dos Santos | AF8: 46280 | AG8: Amanda Aparecida Teixeira dos Santos | AH8: 100 | AI8: 100 | AJ8: 100 | AN8: =VLOOKUP(M8,[1]municipios!$B:$D,3,0) -> PONTA PORA | AO8: =TODAY()-E8 -> 23 | AP8: =IF(AO8<=5,"0–5 dias",IF(AO8<=15,"6–15 dias",IF(AO8<=16,"16–30 dias",IF(AO8<=30,"30–50 dias",">50 dias")))) -> 30–50 dias | AQ8: =IF(U8="","Dentro",(IF(IF(W8="",TODAY(),W8)<=U8,"Dentro","Fora"))) -> Fora | AR8: =IF(U8="","Não risco",IF((TODAY()-U8)<=7,"Risco","Não risco")) -> Não risco | AS8: =IF(SEARCH("integrar",P8)>0,"Sim","Não") -> #VALUE! | AT8: =IF(S8="",TODAY()-Q8,S8-Q8) -> 28 | AU8: =VLOOKUP(X8,'pontos focais'!C:D,2,0) -> DCMD Programação de Obra | AV8: =U8-Q8 -> 13
A9: 1032 | B9: Visita Domo de Ferro | C9: Obra | D9: DCMD | E9: 46211 | F9: Monike Chaves | G9: Finalizada | H9: Finalizada | K9: 0502600521 | L9: SUL | M9: Tacuru | N9: Prefeitura | O9: Tacuru | P9: Por favor verificar possibilidade de agilizar atendimento da Obra 0502600521. | Q9: 46252 | R9: Por favor verificar possibilidade de agilizar atendimento da Obra 0502600521. | S9: 46267 | T9: OBRA CONCLUIDA 21/08 | U9: 46337 | W9: 46255 | X9: Amanda Aparecida Teixeira dos Santos | Y9: Amanda Santos | Z9: Prefeito Rogério | AA9: Jonas Ortiz Rudis | AB9: Sim | AC9: Visita Domo de Ferro | AD9: 46267 | AE9: Amanda Aparecida Teixeira dos Santos | AF9: 46267 | AG9: Amanda Aparecida Teixeira dos Santos | AH9: 100 | AI9: 100 | AJ9: 100 | AN9: =VLOOKUP(M9,[1]municipios!$B:$D,3,0) -> NAVIRAI | AO9: =TODAY()-E9 -> 77 | AP9: =IF(AO9<=5,"0–5 dias",IF(AO9<=15,"6–15 dias",IF(AO9<=16,"16–30 dias",IF(AO9<=30,"30–50 dias",">50 dias")))) -> >50 dias | AQ9: =IF(U9="","Dentro",(IF(IF(W9="",TODAY(),W9)<=U9,"Dentro","Fora"))) -> Dentro | AR9: =IF(U9="","Não risco",IF((TODAY()-U9)<=7,"Risco","Não risco")) -> Risco | AS9: =IF(SEARCH("integrar",P9)>0,"Sim","Não") -> #VALUE! | AT9: =IF(S9="",TODAY()-Q9,S9-Q9) -> 15 | AU9: =VLOOKUP(X9,'pontos focais'!C:D,2,0) -> DCMD Programação de Obra | AV9: =U9-Q9 -> 85
A10: 1036 | B10: Visita Domo de Ferro | C10: Manutenção | D10: DCMD | E10: 46252 | F10: Giovani Moura Sousa | G10: Em Andamento | H10: Não Iniciada | L10: CENTRO | M10: Campo Grande | N10: Câmara | O10: Campo Grande | P10: Solicita substituião do poste quebrado a Rua Grace Kelly, 306 | Q10: 46253 | R10: Programar levantamento para substituição de poste quebrado. Rua Grace Kelly, nº 306 - Bairro Jardim Colibri - Campo Grande/MS. | X10: Evair Rogerio da Conceicao | Z10: Vereador Beto Avelar | AA10: Giovani Moura Sousa | AB10: Sim | AC10: Visita Domo de Ferro | AD10: 46253 | AE10: Wander Idalino Machado | AF10: 46253 | AG10: Wander Idalino Machado | AH10: 25 | AI10: 25 | AJ10: 12.5 | AK10: Manutenção e Poda | AM10: DCMD - PODA E MANUTENÇÃO | AN10: =VLOOKUP(M10,[1]municipios!$B:$D,3,0) -> CAMPO GRANDE | AO10: =TODAY()-E10 -> 36 | AP10: =IF(AO10<=5,"0–5 dias",IF(AO10<=15,"6–15 dias",IF(AO10<=16,"16–30 dias",IF(AO10<=30,"30–50 dias",">50 dias")))) -> >50 dias | AQ10: =IF(U10="","Dentro",(IF(IF(W10="",TODAY(),W10)<=U10,"Dentro","Fora"))) -> Dentro | AR10: =IF(U10="","Não risco",IF((TODAY()-U10)<=7,"Risco","Não risco")) -> Não risco | AS10: =IF(SEARCH("integrar",P10)>0,"Sim","Não") -> #VALUE! | AT10: =IF(S10="",TODAY()-Q10,S10-Q10) -> 35 | AU10: =VLOOKUP(X10,'pontos focais'!C:D,2,0) -> DCMD Manutenção | AV10: =U10-Q10 -> -46253
A11: 1043 | B11: Visita Domo de Ferro | C11: Obra | D11: DCMD | E11: 46253 | F11: Dian Cleiton de Brito | G11: Finalizada | H11: Finalizada | K11: 0302600251 | L11: SUL | M11: Bataguassu | N11: Assembleia Legislativa | O11: Bataguassu | P11: Deputado e Prefeita solicitam a relocação com urgÊncia considerando a paralização das obras de pavimentação. Expect 31/08/26; | Q11: 46255 | R11: Por favor, disponibilizar orçamento ao cliente. | S11: 46273 | T11: Obra gerada o boleto na UC conforme solicitado e liberada. | U11: 46265 | W11: 46199 | X11: Bruna Victoria Rodrigues Ricardes | Y11: Bruna Ricardes | Z11: Caravina - Deputado Wanderleia - Prefeita Carol - Secretaria de Adm | AA11: Dian Cleiton de Brito | AB11: Sim | AC11: Visita Domo de Ferro | AD11: 46273 | AE11: Bruna Victoria Rodrigues Ricardes | AF11: 46273 | AG11: Bruna Victoria Rodrigues Ricardes | AH11: 100 | AI11: 100 | AJ11: 100 | AN11: =VLOOKUP(M11,[1]municipios!$B:$D,3,0) -> NOVA ANDRADINA | AO11: =TODAY()-E11 -> 35 | AP11: =IF(AO11<=5,"0–5 dias",IF(AO11<=15,"6–15 dias",IF(AO11<=16,"16–30 dias",IF(AO11<=30,"30–50 dias",">50 dias")))) -> >50 dias | AQ11: =IF(U11="","Dentro",(IF(IF(W11="",TODAY(),W11)<=U11,"Dentro","Fora"))) -> Dentro | AR11: =IF(U11="","Não risco",IF((TODAY()-U11)<=7,"Risco","Não risco")) -> Não risco | AS11: =IF(SEARCH("integrar",P11)>0,"Sim","Não") -> #VALUE! | AT11: =IF(S11="",TODAY()-Q11,S11-Q11) -> 18 | AU11: =VLOOKUP(X11,'pontos focais'!C:D,2,0) -> DCMD Orçamento e Projetos | AV11: =U11-Q11 -> 10
A12: 1045 | B12: Visita Domo de Ferro | C12: Obra | D12: DCMD | E12: 46254 | F12: Dian Cleiton de Brito | G12: Em Andamento | H12: Em Andamento | K12: 050-26-00571 | L12: SUL | M12: Itaquiraí | N12: Governo do Estado | O12: Itaquiraí | P12: Governador solicitou agilizar obra de atendimento ao Cliente. Expec: 20/09/26; NELSON TUTIDA CPF: 245.245.499-00 IE: 28.790.825-9 FAZ MEIO SECULO, ZONA RURAL, ITAQUIRAÍ - MS PROJETO 23623/26 UC: 3877911 CUSD 13524 OBRA: 050-26-00571 | Q12: 46253 | R12: Liberar programação da Obra 0502600571 | S12: 46280 | U12: 46284 | V12: 46283 | X12: Amanda Aparecida Teixeira dos Santos | Y12: Amanda Santos | Z12: Eduardo Riedel - Governador Paulo Roberto - DPRE | AA12: Dian Cleiton de Brito | AB12: Sim | AC12: Visita Domo de Ferro | AD12: 46280 | AE12: Amanda Aparecida Teixeira dos Santos | AF12: 46280 | AG12: Amanda Aparecida Teixeira dos Santos | AH12: 100 | AI12: 100 | AJ12: 100 | AN12: =VLOOKUP(M12,[1]municipios!$B:$D,3,0) -> NAVIRAI | AO12: =TODAY()-E12 -> 34 | AP12: =IF(AO12<=5,"0–5 dias",IF(AO12<=15,"6–15 dias",IF(AO12<=16,"16–30 dias",IF(AO12<=30,"30–50 dias",">50 dias")))) -> >50 dias | AQ12: =IF(U12="","Dentro",(IF(IF(W12="",TODAY(),W12)<=U12,"Dentro","Fora"))) -> Fora | AR12: =IF(U12="","Não risco",IF((TODAY()-U12)<=7,"Risco","Não risco")) -> Risco | AS12: =IF(SEARCH("integrar",P12)>0,"Sim","Não") -> #VALUE! | AT12: =IF(S12="",TODAY()-Q12,S12-Q12) -> 27 | AU12: =VLOOKUP(X12,'pontos focais'!C:D,2,0) -> DCMD Programação de Obra | AV12: =U12-Q12 -> 31
A13: 1057 | B13: Visita Domo de Ferro | C13: Obra | D13: DCMD | E13: 46255 | F13: Dian Cleiton de Brito | G13: Em Andamento | H13: Em Andamento | K13: 0252600281 | L13: NORTE | M13: Miranda | N13: Diretoria | O13: Miranda | P13: Presidente solicitou para agilizar obra de extensão de rede para atendimento de Eletroposto. Expectativa: 20/09/26 | Q13: 46258 | R13: Obra 0252600281 - por favor agilizar programação. | S13: 46269 | T13: Obra programada para finalizar 20/09 | U13: 46285 | V13: 46285 | X13: Amanda Aparecida Teixeira dos Santos | Y13: Amanda Santos | Z13: Paulo Roberto | AA13: Dian Cleiton de Brito | AB13: Sim | AC13: Visita Domo de Ferro | AD13: 46269 | AE13: Amanda Aparecida Teixeira dos Santos | AF13: 46269 | AG13: Amanda Aparecida Teixeira dos Santos | AH13: 100 | AI13: 100 | AJ13: 100 | AN13: =VLOOKUP(M13,[1]municipios!$B:$D,3,0) -> AQUIDAUANA | AO13: =TODAY()-E13 -> 33 | AP13: =IF(AO13<=5,"0–5 dias",IF(AO13<=15,"6–15 dias",IF(AO13<=16,"16–30 dias",IF(AO13<=30,"30–50 dias",">50 dias")))) -> >50 dias | AQ13: =IF(U13="","Dentro",(IF(IF(W13="",TODAY(),W13)<=U13,"Dentro","Fora"))) -> Fora | AR13: =IF(U13="","Não risco",IF((TODAY()-U13)<=7,"Risco","Não risco")) -> Risco | AS13: =IF(SEARCH("integrar",P13)>0,"Sim","Não") -> #VALUE! | AT13: =IF(S13="",TODAY()-Q13,S13-Q13) -> 11 | AU13: =VLOOKUP(X13,'pontos focais'!C:D,2,0) -> DCMD Programação de Obra | AV13: =U13-Q13 -> 27
A14: 1060 | B14: Visita Domo de Ferro | C14: Obra | D14: DCMD | E14: 46258 | F14: Aline da Silva Mesquita | G14: Em Andamento | H14: Em Andamento | K14: 0102601321 | L14: CENTRO | M14: Ribas do Rio Pardo | N14: Prefeitura | O14: Ribas do Rio Pardo | P14: Prefeito de Ribas me pediu para agilizar essas obras a seguir pra esta semana urgente. | Q14: 46258 | R14: agilizar obra, pra esta semana urgente. | S14: 46280 | T14: Programada para 14/10 | U14: 46265 | V14: 46309 | X14: Amanda Aparecida Teixeira dos Santos | Y14: Amanda Santos | AB14: Sim | AC14: Visita Domo de Ferro | AD14: 46280 | AE14: Amanda Aparecida Teixeira dos Santos | AF14: 46280 | AG14: Amanda Aparecida Teixeira dos Santos | AH14: 100 | AI14: 100 | AJ14: 100 | AN14: =VLOOKUP(M14,[1]municipios!$B:$D,3,0) -> CAMPO GRANDE INTERIOR | AO14: =TODAY()-E14 -> 30 | AP14: =IF(AO14<=5,"0–5 dias",IF(AO14<=15,"6–15 dias",IF(AO14<=16,"16–30 dias",IF(AO14<=30,"30–50 dias",">50 dias")))) -> 30–50 dias | AQ14: =IF(U14="","Dentro",(IF(IF(W14="",TODAY(),W14)<=U14,"Dentro","Fora"))) -> Fora | AR14: =IF(U14="","Não risco",IF((TODAY()-U14)<=7,"Risco","Não risco")) -> Não risco | AS14: =IF(SEARCH("integrar",P14)>0,"Sim","Não") -> #VALUE! | AT14: =IF(S14="",TODAY()-Q14,S14-Q14) -> 22 | AU14: =VLOOKUP(X14,'pontos focais'!C:D,2,0) -> DCMD Programação de Obra | AV14: =U14-Q14 -> 7
A15: 1061 | B15: Visita Domo de Ferro | C15: Obra | D15: DCMD | E15: 46258 | F15: Aline da Silva Mesquita | G15: Finalizada | H15: Finalizada | K15: 0102601427 | L15: CENTRO | M15: Ribas do Rio Pardo | N15: Prefeitura | O15: Ribas do Rio Pardo | P15: Prefeito de Ribas me pediu para agilizar essas obras a seguir pra esta semana urgente | Q15: 46258 | R15: agilizar obra pra esta semana urgente. | S15: 46269 | T15: Obra concluída 28/08 | U15: 46265 | W15: 46262 | X15: Amanda Aparecida Teixeira dos Santos | Y15: Amanda Santos | AB15: Sim | AC15: Visita Domo de Ferro | AD15: 46269 | AE15: Amanda Aparecida Teixeira dos Santos | AF15: 46269 | AG15: Amanda Aparecida Teixeira dos Santos | AH15: 100 | AI15: 100 | AJ15: 100 | AN15: =VLOOKUP(M15,[1]municipios!$B:$D,3,0) -> CAMPO GRANDE INTERIOR | AO15: =TODAY()-E15 -> 30 | AP15: =IF(AO15<=5,"0–5 dias",IF(AO15<=15,"6–15 dias",IF(AO15<=16,"16–30 dias",IF(AO15<=30,"30–50 dias",">50 dias")))) -> 30–50 dias | AQ15: =IF(U15="","Dentro",(IF(IF(W15="",TODAY(),W15)<=U15,"Dentro","Fora"))) -> Dentro | AR15: =IF(U15="","Não risco",IF((TODAY()-U15)<=7,"Risco","Não risco")) -> Não risco | AS15: =IF(SEARCH("integrar",P15)>0,"Sim","Não") -> #VALUE! | AT15: =IF(S15="",TODAY()-Q15,S15-Q15) -> 11 | AU15: =VLOOKUP(X15,'pontos focais'!C:D,2,0) -> DCMD Programação de Obra | AV15: =U15-Q15 -> 7
A16: 1062 | B16: Visita Domo de Ferro | C16: Obra | D16: DCMD | E16: 46258 | F16: Aline da Silva Mesquita | G16: Em Andamento | H16: Não Iniciada | K16: 0102601240 | L16: CENTRO | M16: Ribas do Rio Pardo | N16: Prefeitura | O16: Ribas do Rio Pardo | P16: Prefeito de Ribas me pediu para agilizar essas obras a seguir pra esta semana urgente | Q16: 46275 | R16: Obra 0102601240. Devolver ao SPRO, projeto não condiz com a situação em campo. No projeto pede a desativação de uma rede mas ela não é existente em campo. | S16: 46276 | U16: 46442 | X16: Evelyn Carlos Benites | Y16: Rafaela Almeida | AB16: Sim | AC16: Visita Domo de Ferro | AD16: 46276 | AE16: Rafaela Mattos de Almeida | AF16: 46276 | AG16: Rafaela Mattos de Almeida | AH16: 100 | AI16: 100 | AJ16: 100 | AN16: =VLOOKUP(M16,[1]municipios!$B:$D,3,0) -> CAMPO GRANDE INTERIOR | AO16: =TODAY()-E16 -> 30 | AP16: =IF(AO16<=5,"0–5 dias",IF(AO16<=15,"6–15 dias",IF(AO16<=16,"16–30 dias",IF(AO16<=30,"30–50 dias",">50 dias")))) -> 30–50 dias | AQ16: =IF(U16="","Dentro",(IF(IF(W16="",TODAY(),W16)<=U16,"Dentro","Fora"))) -> Dentro | AR16: =IF(U16="","Não risco",IF((TODAY()-U16)<=7,"Risco","Não risco")) -> Risco | AS16: =IF(SEARCH("integrar",P16)>0,"Sim","Não") -> #VALUE! | AT16: =IF(S16="",TODAY()-Q16,S16-Q16) -> 1 | AU16: =VLOOKUP(X16,'pontos focais'!C:D,2,0) -> DCMD Orçamento e Projetos | AV16: =U16-Q16 -> 167
A17: 1064 | B17: Visita Domo de Ferro | C17: Informação | D17: DESC | E17: 46258 | F17: Aline da Silva Mesquita | G17: Em Andamento | H17: Não Iniciada | K17: 0702600176 | L17: NORTE | M17: Coxim | N17: Prefeitura | O17: Coxim | P17: Availdo vai entrar em contato. Obra liberada, pedir prioridade via central, SOLICITADA PELA ALINE MESQUITA | Q17: 46258 | R17: Availdo vai entrar em contato, para maior entendimento, trata-se de duas obras 0702600176 e 0702600108. Aline Mesquita descreveu: Porem segue algumas observações; a Obra ainda não esta em execução mesmo ter saído sem custo, provavelmente o que esta pendente é o contrato de demanda com os grandes clientes. o posto de transformação também esta pendente a solicitação de comissionamento. | S17: 46273 | V17: 46261 | X17: Availdo Taveira de Oliveira | Y17: Gabriella Domingo | AA17: Availdo Taveira de Oliveira | AB17: Sim | AC17: Prefeitura | AD17: 46273 | AE17: Gabriella Amorim Domingo | AF17: 46273 | AG17: Gabriella Amorim Domingo | AH17: 100 | AI17: 100 | AJ17: 100 | AN17: =VLOOKUP(M17,[1]municipios!$B:$D,3,0) -> COXIM | AO17: =TODAY()-E17 -> 30 | AP17: =IF(AO17<=5,"0–5 dias",IF(AO17<=15,"6–15 dias",IF(AO17<=16,"16–30 dias",IF(AO17<=30,"30–50 dias",">50 dias")))) -> 30–50 dias | AQ17: =IF(U17="","Dentro",(IF(IF(W17="",TODAY(),W17)<=U17,"Dentro","Fora"))) -> Dentro | AR17: =IF(U17="","Não risco",IF((TODAY()-U17)<=7,"Risco","Não risco")) -> Não risco | AS17: =IF(SEARCH("integrar",P17)>0,"Sim","Não") -> #VALUE! | AT17: =IF(S17="",TODAY()-Q17,S17-Q17) -> 15 | AU17: =VLOOKUP(X17,'pontos focais'!C:D,2,0) -> DESC Agentes de Relacionamento | AV17: =U17-Q17 -> -46258
A18: 1064 | B18: Visita Domo de Ferro | C18: Obra | D18: DCMD | E18: 46258 | F18: Aline da Silva Mesquita | G18: Em Andamento | H18: Em Andamento | K18: 0702600176 | L18: NORTE | M18: Coxim | N18: Prefeitura | O18: Coxim | P18: Availdo vai entrar em contato. Obra liberada, pedir prioridade via central, SOLICITADA PELA ALINE MESQUITA | Q18: 46258 | R18: Obra liberada, liberar programação, obra necessaria ser atendida com urgencia. Demanda DPRE São duas obras 0702600176 e 0702600108 | S18: 46280 | T18: Reprogramada para 26/09 - devido a contingencia | U18: 46295 | V18: 46291 | X18: Amanda Aparecida Teixeira dos Santos | Y18: Amanda Santos | AA18: Availdo Taveira de Oliveira | AB18: Sim | AC18: Prefeitura | AD18: 46280 | AE18: Amanda Aparecida Teixeira dos Santos | AF18: 46280 | AG18: Amanda Aparecida Teixeira dos Santos | AH18: 100 | AI18: 100 | AJ18: 100 | AN18: =VLOOKUP(M18,[1]municipios!$B:$D,3,0) -> COXIM | AO18: =TODAY()-E18 -> 30 | AP18: =IF(AO18<=5,"0–5 dias",IF(AO18<=15,"6–15 dias",IF(AO18<=16,"16–30 dias",IF(AO18<=30,"30–50 dias",">50 dias")))) -> 30–50 dias | AQ18: =IF(U18="","Dentro",(IF(IF(W18="",TODAY(),W18)<=U18,"Dentro","Fora"))) -> Dentro | AR18: =IF(U18="","Não risco",IF((TODAY()-U18)<=7,"Risco","Não risco")) -> Risco | AS18: =IF(SEARCH("integrar",P18)>0,"Sim","Não") -> #VALUE! | AT18: =IF(S18="",TODAY()-Q18,S18-Q18) -> 22 | AU18: =VLOOKUP(X18,'pontos focais'!C:D,2,0) -> DCMD Programação de Obra | AV18: =U18-Q18 -> 37
A19: 1066 | B19: Visita Domo de Ferro | C19: Obra | D19: DCMD | E19: 46254 | F19: Aline da Silva Mesquita | G19: Em Andamento | H19: Finalizada | L19: CENTRO | M19: Ribas do Rio Pardo | N19: Diretoria | O19: Ribas do Rio Pardo | P19: Trata-se do novo prédio da Policia militar. Obra por parte do cliente concluída e comissionada. | Q19: 46259 | R19: Agilizar o orçamento para seguirmos com a elaboração dos contratos | S19: 46273 | U19: 46265 | X19: Bruna Victoria Rodrigues Ricardes | Y19: Bruna Ricardes | Z19: Denise Simoes | AB19: Sim | AC19: Visita Domo de Ferro | AD19: 46273 | AE19: Bruna Victoria Rodrigues Ricardes | AF19: 46273 | AG19: Bruna Victoria Rodrigues Ricardes | AH19: 100 | AI19: 100 | AJ19: 100 | AN19: =VLOOKUP(M19,[1]municipios!$B:$D,3,0) -> CAMPO GRANDE INTERIOR | AO19: =TODAY()-E19 -> 34 | AP19: =IF(AO19<=5,"0–5 dias",IF(AO19<=15,"6–15 dias",IF(AO19<=16,"16–30 dias",IF(AO19<=30,"30–50 dias",">50 dias")))) -> >50 dias | AQ19: =IF(U19="","Dentro",(IF(IF(W19="",TODAY(),W19)<=U19,"Dentro","Fora"))) -> Fora | AR19: =IF(U19="","Não risco",IF((TODAY()-U19)<=7,"Risco","Não risco")) -> Não risco | AS19: =IF(SEARCH("integrar",P19)>0,"Sim","Não") -> #VALUE! | AT19: =IF(S19="",TODAY()-Q19,S19-Q19) -> 14 | AU19: =VLOOKUP(X19,'pontos focais'!C:D,2,0) -> DCMD Orçamento e Projetos | AV19: =U19-Q19 -> 6
A20: 1066 | B20: Visita Domo de Ferro | C20: Obra | D20: DESC | E20: 46254 | F20: Aline da Silva Mesquita | G20: Em Andamento | H20: Não Iniciada | I20: SECRETARIA DE ESTADO DE JUSTIÇA E SEGURANÇA PÚBLICA | K20: 010260168 | L20: CENTRO | M20: Ribas do Rio Pardo | N20: Diretoria | O20: Ribas do Rio Pardo | P20: Trata-se do novo prédio da Policia militar. Obra por parte do cliente concluída e comissionada. | Q20: 46275 | R20: Obra 010260168 - Projeto anexado. Por favor seguir com a elaboração dos contratos. Orçamento enviado para o cliente. | X20: Marcelly Arce Avalo Franca | Z20: Denise Simoes | AB20: Sim | AC20: Visita Domo de Ferro | AD20: 46276 | AE20: Wander Idalino Machado | AF20: 46276 | AG20: Wander Idalino Machado | AH20: 100 | AI20: 100 | AJ20: 50 | AK20: Relacionamento com cliente | AM20: CGCP | AN20: =VLOOKUP(M20,[1]municipios!$B:$D,3,0) -> CAMPO GRANDE INTERIOR | AO20: =TODAY()-E20 -> 34 | AP20: =IF(AO20<=5,"0–5 dias",IF(AO20<=15,"6–15 dias",IF(AO20<=16,"16–30 dias",IF(AO20<=30,"30–50 dias",">50 dias")))) -> >50 dias | AQ20: =IF(U20="","Dentro",(IF(IF(W20="",TODAY(),W20)<=U20,"Dentro","Fora"))) -> Dentro | AR20: =IF(U20="","Não risco",IF((TODAY()-U20)<=7,"Risco","Não risco")) -> Não risco | AS20: =IF(SEARCH("integrar",P20)>0,"Sim","Não") -> #VALUE! | AT20: =IF(S20="",TODAY()-Q20,S20-Q20) -> 13 | AU20: =VLOOKUP(X20,'pontos focais'!C:D,2,0) -> DESC Agentes de Relacionamento | AV20: =U20-Q20 -> -46275
A21: 1067 | B21: Visita Domo de Ferro | C21: Poda | D21: DCMD | E21: 46265 | F21: Giovani Moura Sousa | G21: Finalizada | H21: Finalizada | J21: 1.368.792.051-47 | L21: SUL | M21: Dourados | N21: Câmara | O21: Dourados | P21: PODA E SUPRESSAO DA ARVORE UC136879205147 RUA DAS FIGUEIRAS 810 - JARDIM COLIBRI, COM AUTORIZAÇÃO DO IMAM, CONFORME ANEXO. NECESSARIO COM URGENCIA ARVORE ESTA CAINDO E NO LOCAL NAO PODE FICAR SEM ENERGIA DEVIDO A SER UM CLIENTE VIP ENFERMO COM USO DE EQUIPAMENTO ESSENCIAL. | Q21: 46259 | R21: PODA E SUPRESSAO DA ARVORE UC136879205147 RUA DAS FIGUEIRAS 810 - JARDIM COLIBRI, COM AUTORIZAÇÃO DO IMAM, CONFORME ANEXO. NECESSARIO COM URGENCIA ARVORE ESTA CAINDO E NO LOCAL NAO PODE FICAR SEM ENERGIA DEVIDO A SER UM CLIENTE VIP ENFERMO COM USO DE EQUIPAMENTO ESSENCIAL. | S21: 46265 | T21: Supressão realizada. | X21: Evair Rogerio da Conceicao | Y21: Evair Conceicao | AB21: Sim | AC21: Visita Domo de Ferro | AD21: 46265 | AE21: Evair Rogerio da Conceicao | AF21: 46265 | AG21: Evair Rogerio da Conceicao | AH21: 25 | AI21: 25 | AJ21: 25 | AN21: =VLOOKUP(M21,[1]municipios!$B:$D,3,0) -> DOURADOS | AO21: =TODAY()-E21 -> 23 | AP21: =IF(AO21<=5,"0–5 dias",IF(AO21<=15,"6–15 dias",IF(AO21<=16,"16–30 dias",IF(AO21<=30,"30–50 dias",">50 dias")))) -> 30–50 dias | AQ21: =IF(U21="","Dentro",(IF(IF(W21="",TODAY(),W21)<=U21,"Dentro","Fora"))) -> Dentro | AR21: =IF(U21="","Não risco",IF((TODAY()-U21)<=7,"Risco","Não risco")) -> Não risco | AS21: =IF(SEARCH("integrar",P21)>0,"Sim","Não") -> #VALUE! | AT21: =IF(S21="",TODAY()-Q21,S21-Q21) -> 6 | AU21: =VLOOKUP(X21,'pontos focais'!C:D,2,0) -> DCMD Manutenção | AV21: =U21-Q21 -> -46259
A22: 1073 | B22: Visita Domo de Ferro | C22: Obra | D22: DCMD | E22: 46262 | F22: Dian Cleiton de Brito | G22: Finalizada | H22: Finalizada | K22: 0402600390 | L22: SUL | M22: Antônio João | N22: Assembleia Legislativa | O22: Antônio João | P22: SOLICITA AGILIZAR A REALIZAÇAO DA OBRA EXPECTATIVA 15/09. Demanda gerada em duplicidade - Obra 0402600390 - Todas as tratativas que o caso requer ocorrerá através do ID 1027. | Q22: 46262 | R22: Obra 0402600390 - Programação. | S22: 46280 | T22: Duplicado com ID 1027 | U22: 46280 | V22: 46279 | X22: Amanda Aparecida Teixeira dos Santos | Y22: Amanda Santos | Z22: PAULO ROBERTO BETO PEREIRA | AA22: Dian Cleiton de Brito | AB22: Sim | AC22: Visita Domo de Ferro | AD22: 46280 | AE22: Amanda Aparecida Teixeira dos Santos | AF22: 46280 | AG22: Amanda Aparecida Teixeira dos Santos | AH22: 100 | AI22: 100 | AJ22: 100 | AN22: =VLOOKUP(M22,[1]municipios!$B:$D,3,0) -> PONTA PORA | AO22: =TODAY()-E22 -> 26 | AP22: =IF(AO22<=5,"0–5 dias",IF(AO22<=15,"6–15 dias",IF(AO22<=16,"16–30 dias",IF(AO22<=30,"30–50 dias",">50 dias")))) -> 30–50 dias | AQ22: =IF(U22="","Dentro",(IF(IF(W22="",TODAY(),W22)<=U22,"Dentro","Fora"))) -> Fora | AR22: =IF(U22="","Não risco",IF((TODAY()-U22)<=7,"Risco","Não risco")) -> Não risco | AS22: =IF(SEARCH("integrar",P22)>0,"Sim","Não") -> #VALUE! | AT22: =IF(S22="",TODAY()-Q22,S22-Q22) -> 18 | AU22: =VLOOKUP(X22,'pontos focais'!C:D,2,0) -> DCMD Programação de Obra | AV22: =U22-Q22 -> 18
A23: 1074 | B23: Visita Domo de Ferro | C23: Obra | D23: DCMD | E23: 46295 | F23: Monike Chaves | G23: Em Andamento | H23: Em Andamento | K23: 0202600798 | L23: SUL | M23: Caarapó | N23: Prefeitura | O23: Caarapó | P23: Prefeita solicitou adiantamento da obra, em decorrecnia de obra no local. | Q23: 46265 | R23: Obra 0202600798 - programação. | S23: 46280 | T23: Mantém para 28/09 | V23: 46293 | X23: Amanda Aparecida Teixeira dos Santos | Y23: Amanda Santos | Z23: Prefeita Lurdes | AA23: Aline da Silva Mesquita | AB23: Sim | AC23: Prefeitura | AD23: 46280 | AE23: Amanda Aparecida Teixeira dos Santos | AF23: 46280 | AG23: Amanda Aparecida Teixeira dos Santos | AH23: 100 | AI23: 100 | AJ23: 100 | AN23: =VLOOKUP(M23,[1]municipios!$B:$D,3,0) -> DOURADOS | AO23: =TODAY()-E23 -> -7 | AP23: =IF(AO23<=5,"0–5 dias",IF(AO23<=15,"6–15 dias",IF(AO23<=16,"16–30 dias",IF(AO23<=30,"30–50 dias",">50 dias")))) -> 0–5 dias | AQ23: =IF(U23="","Dentro",(IF(IF(W23="",TODAY(),W23)<=U23,"Dentro","Fora"))) -> Dentro | AR23: =IF(U23="","Não risco",IF((TODAY()-U23)<=7,"Risco","Não risco")) -> Não risco | AS23: =IF(SEARCH("integrar",P23)>0,"Sim","Não") -> #VALUE! | AT23: =IF(S23="",TODAY()-Q23,S23-Q23) -> 15 | AU23: =VLOOKUP(X23,'pontos focais'!C:D,2,0) -> DCMD Programação de Obra | AV23: =U23-Q23 -> -46265
A24: 1080 | B24: Visita Domo de Ferro | C24: Obra | D24: DCMD | E24: 46267 | F24: Dian Cleiton de Brito | G24: Em Andamento | H24: Não Iniciada | I24: JOSE RODRIGUES PEREIRA | K24: 0102201031 | L24: CENTRO | M24: Bandeirantes | N24: Assembleia Legislativa | O24: Bandeirantes | P24: Proprietário da Faz Elizabeth solicita a execução da obra em execução em sua proriedade a 4 anos. precisa da execução imediata para inicio do plantio. Necessidade 15/09/26. | Q24: 46282 | R24: Obra 0102201031 Fiscalização Reprovada. Por favor avaliar o andamento pois a obra contempla a instalação de 01 religador 34.5 KV. Tratativa deve ser feita pelo SPCO, o Religador chegará em 28/09/2026. | X24: Amanda Aparecida Teixeira dos Santos | Z24: Junior Mocci Renato Câmara | AA24: Dian Cleiton de Brito | AB24: Sim | AC24: Visita Domo de Ferro | AD24: 46282 | AE24: Wander Idalino Machado | AF24: 46282 | AG24: Wander Idalino Machado | AH24: 100 | AI24: 100 | AJ24: 50 | AK24: Programação de Obras e Gestão de Materiais | AM24: DCMD - PROGRAMAÇÃO DE OBRA | AN24: =VLOOKUP(M24,[1]municipios!$B:$D,3,0) -> CAMPO GRANDE INTERIOR | AO24: =TODAY()-E24 -> 21 | AP24: =IF(AO24<=5,"0–5 dias",IF(AO24<=15,"6–15 dias",IF(AO24<=16,"16–30 dias",IF(AO24<=30,"30–50 dias",">50 dias")))) -> 30–50 dias | AQ24: =IF(U24="","Dentro",(IF(IF(W24="",TODAY(),W24)<=U24,"Dentro","Fora"))) -> Dentro | AR24: =IF(U24="","Não risco",IF((TODAY()-U24)<=7,"Risco","Não risco")) -> Não risco | AS24: =IF(SEARCH("integrar",P24)>0,"Sim","Não") -> #VALUE! | AT24: =IF(S24="",TODAY()-Q24,S24-Q24) -> 6 | AU24: =VLOOKUP(X24,'pontos focais'!C:D,2,0) -> DCMD Programação de Obra | AV24: =U24-Q24 -> -46282
A25: 1087 | B25: Visita Domo de Ferro | C25: Qualidade | D25: DEOP | E25: 46268 | F25: Dian Cleiton de Brito | G25: Em Andamento | H25: Não Iniciada | I25: RAFAEL PIZZI | J25: 2986442/2944064 | L25: CENTRO | M25: Aparecida do Taboado | N25: Prefeitura | O25: Aparecida do Taboado | P25: RECLAMAÇÃO SOBRECARGAS E ABERTURA DO TRANSFORMADOR. UC 2986442 - 200 A UC 2944064 - 200 A ligadas no mesmo transformador. ENTF 000505 | Q25: 46269 | R25: Por favor realizar os estudos para avaliação e as possíveis intervenções. Unidades consumidoras 2986442 e 2944064. Transformador ENTF 000505. | X25: Luan Henrique Soares Diniz Afonso | Z25: José Natan - Prefeito | AA25: Dian Cleiton de Brito | AB25: Sim | AC25: Visita Domo de Ferro | AD25: 46269 | AE25: Wander Idalino Machado | AF25: 46269 | AG25: Wander Idalino Machado | AH25: 100 | AI25: 100 | AJ25: 50 | AK25: Qualidade do produto | AM25: DEOP - QUALIDADE | AN25: =VLOOKUP(M25,[1]municipios!$B:$D,3,0) -> PARANAIBA | AO25: =TODAY()-E25 -> 20 | AP25: =IF(AO25<=5,"0–5 dias",IF(AO25<=15,"6–15 dias",IF(AO25<=16,"16–30 dias",IF(AO25<=30,"30–50 dias",">50 dias")))) -> 30–50 dias | AQ25: =IF(U25="","Dentro",(IF(IF(W25="",TODAY(),W25)<=U25,"Dentro","Fora"))) -> Dentro | AR25: =IF(U25="","Não risco",IF((TODAY()-U25)<=7,"Risco","Não risco")) -> Não risco | AS25: =IF(SEARCH("integrar",P25)>0,"Sim","Não") -> #VALUE! | AT25: =IF(S25="",TODAY()-Q25,S25-Q25) -> 19 | AU25: =VLOOKUP(X25,'pontos focais'!C:D,2,0) -> DEOP Qualidade | AV25: =U25-Q25 -> -46269
A26: 1090 | B26: Visita Domo de Ferro | C26: Obra | D26: DCMD | E26: 46268 | F26: Dian Cleiton de Brito | G26: Em Andamento | H26: Em Andamento | K26: 0402600380 | L26: SUL | M26: Laguna Carapã | N26: Prefeitura | O26: Laguna Carapã | P26: Prefeito solicita a relocação em caráter emergencial, pois tem risco de perder recurso para construção de imoveis na área em questão. Obra 0402600380 Expectatica: 30:09:26 | Q26: 46269 | R26: Obra 0402600380 - Programação. | S26: 46280 | V26: 46294 | X26: Amanda Aparecida Teixeira dos Santos | Y26: Amanda Santos | Z26: Itamar - Prefeito | AA26: Dian Cleiton de Brito | AB26: Sim | AC26: Visita Domo de Ferro | AD26: 46280 | AE26: Amanda Aparecida Teixeira dos Santos | AF26: 46280 | AG26: Amanda Aparecida Teixeira dos Santos | AH26: 100 | AI26: 100 | AJ26: 100 | AN26: =VLOOKUP(M26,[1]municipios!$B:$D,3,0) -> PONTA PORA | AO26: =TODAY()-E26 -> 20 | AP26: =IF(AO26<=5,"0–5 dias",IF(AO26<=15,"6–15 dias",IF(AO26<=16,"16–30 dias",IF(AO26<=30,"30–50 dias",">50 dias")))) -> 30–50 dias | AQ26: =IF(U26="","Dentro",(IF(IF(W26="",TODAY(),W26)<=U26,"Dentro","Fora"))) -> Dentro | AR26: =IF(U26="","Não risco",IF((TODAY()-U26)<=7,"Risco","Não risco")) -> Não risco | AS26: =IF(SEARCH("integrar",P26)>0,"Sim","Não") -> #VALUE! | AT26: =IF(S26="",TODAY()-Q26,S26-Q26) -> 11 | AU26: =VLOOKUP(X26,'pontos focais'!C:D,2,0) -> DCMD Programação de Obra | AV26: =U26-Q26 -> -46269
A27: 1093 | B27: Visita Domo de Ferro | C27: Informação | D27: Central do Cliente | E27: 46266 | F27: Giovani Moura Sousa | G27: Finalizada | H27: Finalizada | L27: SUL | M27: Amambai | N27: Câmara | O27: Amambai | P27: Interruções de nergia no centro da cidade de Amabai | Q27: 46269 | R27: Para direcionamento de ação ao DEOP é necessário fornecer mais informações, tais como, número de controle interno, número da unidade consumidora, dentre outros. | S27: 46269 | T27: Para direcionamento de ação ao DEOP é necessário fornecer mais informações, tais como, número de controle interno, número da unidade consumidora, dentre outros. | W27: 46269 | X27: Wander Idalino Machado | Y27: Wander Machado | Z27: Vereadora Suzana | AA27: Giovani Moura Sousa | AB27: Sim | AC27: Visita Domo de Ferro | AD27: 46269 | AE27: Wander Idalino Machado | AF27: 46269 | AG27: Wander Idalino Machado | AH27: 25 | AI27: 25 | AJ27: 25 | AN27: =VLOOKUP(M27,[1]municipios!$B:$D,3,0) -> PONTA PORA | AO27: =TODAY()-E27 -> 22 | AP27: =IF(AO27<=5,"0–5 dias",IF(AO27<=15,"6–15 dias",IF(AO27<=16,"16–30 dias",IF(AO27<=30,"30–50 dias",">50 dias")))) -> 30–50 dias | AQ27: =IF(U27="","Dentro",(IF(IF(W27="",TODAY(),W27)<=U27,"Dentro","Fora"))) -> Dentro | AR27: =IF(U27="","Não risco",IF((TODAY()-U27)<=7,"Risco","Não risco")) -> Não risco | AS27: =IF(SEARCH("integrar",P27)>0,"Sim","Não") -> #VALUE! | AT27: =IF(S27="",TODAY()-Q27,S27-Q27) -> 0 | AU27: =VLOOKUP(X27,'pontos focais'!C:D,2,0) -> Central do Cliente | AV27: =U27-Q27 -> -46269
A28: 1095 | B28: Visita Domo de Ferro | C28: Informação | D28: Central do Cliente | E28: 46266 | F28: Giovani Moura Sousa | G28: Finalizada | H28: Finalizada | L28: SUL | M28: Amambai | N28: Câmara | O28: Amambai | P28: Interrupções de energia no centro da cidade de Amambai | Q28: 46269 | R28: Para direcionamento de ação ao DEOP é necessário fornecer mais informações, tais como, número de controle interno, número da unidade consumidora, dentre outros. | S28: 46269 | T28: Para direcionamento de ação ao DEOP é necessário fornecer mais informações, tais como, número de controle interno, número da unidade consumidora, dentre outros. | W28: 46269 | X28: Wander Idalino Machado | Y28: Wander Machado | Z28: Vereador darci José da Silva | AA28: Giovani Moura Sousa | AB28: Sim | AC28: Visita Domo de Ferro | AD28: 46269 | AE28: Wander Idalino Machado | AF28: 46269 | AG28: Wander Idalino Machado | AH28: 25 | AI28: 25 | AJ28: 25 | AN28: =VLOOKUP(M28,[1]municipios!$B:$D,3,0) -> PONTA PORA | AO28: =TODAY()-E28 -> 22 | AP28: =IF(AO28<=5,"0–5 dias",IF(AO28<=15,"6–15 dias",IF(AO28<=16,"16–30 dias",IF(AO28<=30,"30–50 dias",">50 dias")))) -> 30–50 dias | AQ28: =IF(U28="","Dentro",(IF(IF(W28="",TODAY(),W28)<=U28,"Dentro","Fora"))) -> Dentro | AR28: =IF(U28="","Não risco",IF((TODAY()-U28)<=7,"Risco","Não risco")) -> Não risco | AS28: =IF(SEARCH("integrar",P28)>0,"Sim","Não") -> #VALUE! | AT28: =IF(S28="",TODAY()-Q28,S28-Q28) -> 0 | AU28: =VLOOKUP(X28,'pontos focais'!C:D,2,0) -> Central do Cliente | AV28: =U28-Q28 -> -46269
A29: 1097 | B29: Visita Domo de Ferro | C29: Informação | D29: Central do Cliente | E29: 46269 | F29: Dian Cleiton de Brito | G29: Finalizada | H29: Finalizada | J29: 1.292.193.051-59 | L29: CENTRO | M29: Campo Grande | N29: Assembleia Legislativa | O29: Campo Grande | P29: Deputado relata que existe problema na injeção de creditos em sua unidade consumidora. Reclama do elevado consumo de sua residência. Expec: 04/09/26. Subsídios encaminhados via Teams aos cuidados do gestor de relacionamento Dian Cleiton em 04/09/2026. | Q29: 46269 | R29: Informação sobre faturamento GD - Unidade Consumidora 2406080. | S29: 46269 | T29: Controle Interno 2406080 - GD Troca de Medidor Para Aferição - Data 30/04/2025.OS 404908453 - Medidor Retirado W0002050271 Canal 03: 21178 Canal 103: 16581 Medidor Aprovado pelo INMETRO - Laudo 2859/2025 Em análise foi identificado que, na data de 29/05/2025 após ensaios realizados pelo INMETRO foi identificado que não havia inconsistências com o medidor W0002050271 retirado da unidade consumidora 2406080 através da ordem de serviço 404908453. Esclarecemos que, na ocasião o medidor W0002050271 apresentava as leituras (03 consumo medido 21178 e 103 energia injetada 16581), contabilizando 560 KWh de consumo residual e 143 KWh de energia ativa injetada residual. Após a substituição dos medidores as leituras foram coletadas mensalmente com visitas regulares realizadas por nossos leituristas e confirmação das grandezas faturáveis (consumo e injetado). Em consulta ao histórico de leitura e faturamento da unidade identificamos que, até a referência 05/2024 a unidade consumidora apresentava uma média de consumo inferior a média de energia injetada, dessa maneira, ao longo dos meses anteriores a energia injetada era superior ao consumo medido, logo, ocorria a compensação de todo consumo medido restando saldo excedente acumulado para compensação nos faturamentos subsequentes. Esclarecemos que, a partir da referência 11/2024 a unidade em questão passou a apresentar uma média de consumo superior ao injetado, no entanto, devido a existência de saldo acumulado de meses anteriores durante o processo de faturamento a compensação estava ocorrendo até o limite do custo de disponibilidade conforme dispõe a resolução vigente. Cumpre informar, que até a referência 07/2026 a unidade consumidora dispunha de 680 KWh em saldo acumulado de meses anteriores, portanto, a diferença entre o consumo medido e o injetado na respectiva referência foi compensado considerando o saldo informado resultando em uma diferença de 174 KWh, ocasionando na fatura de R$ 328,70. Para o faturamento da referência 08/2026, foi identificado que, na data de 18/08/2026 em visita realizada ao imóvel foram coletadas as leituras (03 consumo medido 13.562 e 103 energia injetada 11.436), contabilizando 1.405 KWh de consumo e 627 KWh de injetado. Logo, devido ao esgotamento do saldo excedente acumulado em meses anteriores, houve a compensação de toda a energia injetada no respectivo faturamento (627 KWh), restando uma diferença de 778 KWh (consumo medido), resultando na fatura emitida no valor de R$ 1.112,83. Diante dos dados de medição (leituras), informo que o consumo medido e o injetado na referência 08/2026 estão de acordo com os registros contabilizados pelo equipamento de medição instalado na unidade reclamada. Portanto, a fatura emitida no valor de R$ 1.112,83 está correta não havendo înconsistências com o respectivo faturamento. | W29: 46269 | X29: Wander Idalino Machado | Y29: Wander Machado | Z29: Geraldo Resende - Deputado Anne Jackeline - Secretária | AA29: Dian Cleiton de Brito | AB29: Sim | AC29: Visita Domo de Ferro | AD29: 46269 | AE29: Wander Idalino Machado | AF29: 46269 | AG29: Wander Idalino Machado | AH29: 100 | AI29: 100 | AJ29: 100 | AN29: =VLOOKUP(M29,[1]municipios!$B:$D,3,0) -> CAMPO GRANDE | AO29: =TODAY()-E29 -> 19 | AP29: =IF(AO29<=5,"0–5 dias",IF(AO29<=15,"6–15 dias",IF(AO29<=16,"16–30 dias",IF(AO29<=30,"30–50 dias",">50 dias")))) -> 30–50 dias | AQ29: =IF(U29="","Dentro",(IF(IF(W29="",TODAY(),W29)<=U29,"Dentro","Fora"))) -> Dentro | AR29: =IF(U29="","Não risco",IF((TODAY()-U29)<=7,"Risco","Não risco")) -> Não risco | AS29: =IF(SEARCH("integrar",P29)>0,"Sim","Não") -> #VALUE! | AT29: =IF(S29="",TODAY()-Q29,S29-Q29) -> 0 | AU29: =VLOOKUP(X29,'pontos focais'!C:D,2,0) -> Central do Cliente | AV29: =U29-Q29 -> -46269
A30: 1098 | B30: Visita Domo de Ferro | C30: Obra | D30: DCMD | E30: 46269 | F30: Dian Cleiton de Brito | G30: Finalizada | H30: Finalizada | K30: 0302600330 | L30: SUL | M30: Ivinhema | N30: Assembleia Legislativa | O30: Ivinhema | P30: DEPUTADO SOLICITA AGILIZAR OBRA DE MELHORIA PARA ATENDIMENTO A AUMENTO DE CARGA. EXPECTATIVA 05/10/26. Orçamento não foi aprovado pelo cliente, dessa maneira, no há possibilidade de agilizar atendimento da obra (agente institucional) orientado via Teams. | Q30: 46269 | R30: Obra 0302600330 - agilizar programação. | S30: 46280 | T30: ORÇAMENTO AINDA NAO APROVADO PELO CLIENTE | U30: 46300 | X30: Amanda Aparecida Teixeira dos Santos | Y30: Amanda Santos | Z30: Zé Teixeira - DEPUTADO Paulo Roberto - DPRE | AA30: Dian Cleiton de Brito | AB30: Sim | AC30: Visita Domo de Ferro | AD30: 46280 | AE30: Amanda Aparecida Teixeira dos Santos | AF30: 46280 | AG30: Amanda Aparecida Teixeira dos Santos | AH30: 100 | AI30: 100 | AJ30: 100 | AN30: =VLOOKUP(M30,[1]municipios!$B:$D,3,0) -> NOVA ANDRADINA | AO30: =TODAY()-E30 -> 19 | AP30: =IF(AO30<=5,"0–5 dias",IF(AO30<=15,"6–15 dias",IF(AO30<=16,"16–30 dias",IF(AO30<=30,"30–50 dias",">50 dias")))) -> 30–50 dias | AQ30: =IF(U30="","Dentro",(IF(IF(W30="",TODAY(),W30)<=U30,"Dentro","Fora"))) -> Dentro | AR30: =IF(U30="","Não risco",IF((TODAY()-U30)<=7,"Risco","Não risco")) -> Risco | AS30: =IF(SEARCH("integrar",P30)>0,"Sim","Não") -> #VALUE! | AT30: =IF(S30="",TODAY()-Q30,S30-Q30) -> 11 | AU30: =VLOOKUP(X30,'pontos focais'!C:D,2,0) -> DCMD Programação de Obra | AV30: =U30-Q30 -> 31
A31: 1105 | B31: Visita Domo de Ferro | C31: Obra | D31: DCMD | E31: 46161.042 | F31: Dian Cleiton de Brito | G31: Em Andamento | H31: Em Andamento | K31: 0302500469 | L31: SUL | M31: Bataguassu | N31: Diretoria | O31: Bataguassu | P31: Solicita realizar a ligação com urgência do loteamento | Q31: 46274 | R31: Obra 0302500469 - Favor incluir na programação. | S31: 46282 | V31: 46307 | X31: Amanda Aparecida Teixeira dos Santos | Y31: Amanda Santos | Z31: Paulo Roberto do Santos | AA31: Dian Cleiton de Brito | AB31: Sim | AC31: Visita Domo de Ferro | AD31: 46282 | AE31: Amanda Aparecida Teixeira dos Santos | AF31: 46282 | AG31: Amanda Aparecida Teixeira dos Santos | AH31: 100 | AI31: 100 | AJ31: 100 | AN31: =VLOOKUP(M31,[1]municipios!$B:$D,3,0) -> NOVA ANDRADINA | AO31: =TODAY()-E31 -> 126.95833 | AP31: =IF(AO31<=5,"0–5 dias",IF(AO31<=15,"6–15 dias",IF(AO31<=16,"16–30 dias",IF(AO31<=30,"30–50 dias",">50 dias")))) -> >50 dias | AQ31: =IF(U31="","Dentro",(IF(IF(W31="",TODAY(),W31)<=U31,"Dentro","Fora"))) -> Dentro | AR31: =IF(U31="","Não risco",IF((TODAY()-U31)<=7,"Risco","Não risco")) -> Não risco | AS31: =IF(SEARCH("integrar",P31)>0,"Sim","Não") -> #VALUE! | AT31: =IF(S31="",TODAY()-Q31,S31-Q31) -> 8 | AU31: =VLOOKUP(X31,'pontos focais'!C:D,2,0) -> DCMD Programação de Obra | AV31: =U31-Q31 -> -46274
A32: 1110 | B32: Visita Domo de Ferro | C32: Obra | D32: DCMD | E32: 46274 | F32: Dian Cleiton de Brito | G32: Em Andamento | H32: Não Iniciada | I32: HAMMES COMÉRCIO DE CEREAIS LTDA. ME | K32: 0202600853 | L32: SUL | M32: Rio Brilhante | N32: Assembleia Legislativa | O32: Rio Brilhante | P32: Solicita agilizar a realização da obra 0202600853 EXPECTATIVA: 20/09/26 | Q32: 46275 | R32: Obra 0202600853 favor incluir na programação. | U32: 46285 | X32: Amanda Aparecida Teixeira dos Santos | Z32: Zé Teixeira Paulo Roberto | AA32: Dian Cleiton de Brito | AB32: Sim | AC32: Visita Domo de Ferro | AD32: 46276 | AE32: Wander Idalino Machado | AF32: 46276 | AG32: Wander Idalino Machado | AH32: 100 | AI32: 100 | AJ32: 50 | AK32: Programação de Obras e Gestão de Materiais | AM32: DCMD - PROGRAMAÇÃO DE OBRA | AN32: =VLOOKUP(M32,[1]municipios!$B:$D,3,0) -> RIO BRILHANTE | AO32: =TODAY()-E32 -> 14 | AP32: =IF(AO32<=5,"0–5 dias",IF(AO32<=15,"6–15 dias",IF(AO32<=16,"16–30 dias",IF(AO32<=30,"30–50 dias",">50 dias")))) -> 6–15 dias | AQ32: =IF(U32="","Dentro",(IF(IF(W32="",TODAY(),W32)<=U32,"Dentro","Fora"))) -> Fora | AR32: =IF(U32="","Não risco",IF((TODAY()-U32)<=7,"Risco","Não risco")) -> Risco | AS32: =IF(SEARCH("integrar",P32)>0,"Sim","Não") -> #VALUE! | AT32: =IF(S32="",TODAY()-Q32,S32-Q32) -> 13 | AU32: =VLOOKUP(X32,'pontos focais'!C:D,2,0) -> DCMD Programação de Obra | AV32: =U32-Q32 -> 10
A33: 1119 | B33: Visita Domo de Ferro | C33: Obra | D33: DCMD | E33: 46280 | F33: Dian Cleiton de Brito | G33: Em Andamento | H33: Não Iniciada | I33: IRANI ENERHARD | K33: 0202600755 | L33: SUL | M33: Dourados | N33: Assembleia Legislativa | O33: Dourados | P33: Deputado Solicita agilizar obra de execução de instalação de ponto de entrega. Expectativa 05/10/2026; | Q33: 46279 | R33: Obra 0202600755 - Por favor incluir na programação. | U33: 46300 | X33: Amanda Aparecida Teixeira dos Santos | Z33: Zé Teixeira Paulo Roberto | AA33: Dian Cleiton de Brito | AB33: Sim | AC33: Visita Domo de Ferro | AD33: 46280 | AE33: Wander Idalino Machado | AF33: 46280 | AG33: Wander Idalino Machado | AH33: 100 | AI33: 100 | AJ33: 50 | AK33: Programação de Obras e Gestão de Materiais | AM33: DCMD - PROGRAMAÇÃO DE OBRA | AN33: =VLOOKUP(M33,[1]municipios!$B:$D,3,0) -> DOURADOS | AO33: =TODAY()-E33 -> 8 | AP33: =IF(AO33<=5,"0–5 dias",IF(AO33<=15,"6–15 dias",IF(AO33<=16,"16–30 dias",IF(AO33<=30,"30–50 dias",">50 dias")))) -> 6–15 dias | AQ33: =IF(U33="","Dentro",(IF(IF(W33="",TODAY(),W33)<=U33,"Dentro","Fora"))) -> Dentro | AR33: =IF(U33="","Não risco",IF((TODAY()-U33)<=7,"Risco","Não risco")) -> Risco | AS33: =IF(SEARCH("integrar",P33)>0,"Sim","Não") -> #VALUE! | AT33: =IF(S33="",TODAY()-Q33,S33-Q33) -> 9 | AU33: =VLOOKUP(X33,'pontos focais'!C:D,2,0) -> DCMD Programação de Obra | AV33: =U33-Q33 -> 21
A34: 1120 | B34: Visita Domo de Ferro | C34: Atendimento Comercial | D34: DESC | E34: 46281 | F34: Dian Cleiton de Brito | G34: Em Andamento | H34: Não Iniciada | I34: PONTE PRETA PARTICIPAÇÕES SOCIETÁRIAS LTDA | J34: 2952299 | L34: CENTRO | M34: Campo Grande | N34: Governo do Estado | O34: Campo Grande | P34: SOLICITA AGILIZAR OS 558638822, considerando que a regularização foi executada. Expec 16/09/26 | Q34: 46281 | R34: Por favor agilizar atendimento da OS 563985314 - Vistoria Para Padronização. | U34: 46281 | X34: Jorge Luis Martinelli | Z34: Jaime Verruck Paulo Roberto dos Santos | AA34: Dian Cleiton de Brito | AB34: Sim | AC34: Visita Domo de Ferro | AD34: 46281 | AE34: Wander Idalino Machado | AF34: 46281 | AG34: Wander Idalino Machado | AH34: 100 | AI34: 100 | AJ34: 50 | AK34: Ligação Nova GA | AM34: DECP - LIGAÇÃO GA | AN34: =VLOOKUP(M34,[1]municipios!$B:$D,3,0) -> CAMPO GRANDE | AO34: =TODAY()-E34 -> 7 | AP34: =IF(AO34<=5,"0–5 dias",IF(AO34<=15,"6–15 dias",IF(AO34<=16,"16–30 dias",IF(AO34<=30,"30–50 dias",">50 dias")))) -> 6–15 dias | AQ34: =IF(U34="","Dentro",(IF(IF(W34="",TODAY(),W34)<=U34,"Dentro","Fora"))) -> Fora | AR34: =IF(U34="","Não risco",IF((TODAY()-U34)<=7,"Risco","Não risco")) -> Risco | AS34: =IF(SEARCH("integrar",P34)>0,"Sim","Não") -> #VALUE! | AT34: =IF(S34="",TODAY()-Q34,S34-Q34) -> 7 | AU34: =VLOOKUP(X34,'pontos focais'!C:D,2,0) -> DECP - Ligação GA | AV34: =U34-Q34 -> 0
A35: 120 | B35: Visita Domo de Ferro | C35: Obra | D35: DCMD | E35: 46150 | F35: Dian Cleiton de Brito | G35: Finalizada | H35: Finalizada | K35: 0302500469 | L35: SUL | M35: Bataguassu | N35: Diretoria | O35: Bataguassu | P35: Solicita agilizar obra de ponto de entrega e loteamento - obra 0302500469 Expectativa - 10/06/26. PE 7175625 OBRAS ASSOCIADAS AO PE FINALIDAS. | Q35: 46237 | R35: Solicita agilizar obra de ponto de entrega e loteamento - obra 0302500469 Expectativa - 10/06/26. PE 7175625. Nova expectativa do cliente 31/07/2026. | S35: 46247 | U35: 46234 | X35: Amanda Aparecida Teixeira dos Santos | Y35: Gabriella Domingo | Z35: Paulo Roberto dos Santos | AA35: Dian Cleiton de Brito | AB35: Sim | AC35: Visita Domo de Ferro | AD35: 46268 | AE35: Moacir Costa Neto | AF35: 46247 | AG35: Gabriella Amorim Domingo | AH35: 100 | AI35: 100 | AJ35: 75 | AN35: =VLOOKUP(M35,[1]municipios!$B:$D,3,0) -> NOVA ANDRADINA | AO35: =TODAY()-E35 -> 138 | AP35: =IF(AO35<=5,"0–5 dias",IF(AO35<=15,"6–15 dias",IF(AO35<=16,"16–30 dias",IF(AO35<=30,"30–50 dias",">50 dias")))) -> >50 dias | AQ35: =IF(U35="","Dentro",(IF(IF(W35="",TODAY(),W35)<=U35,"Dentro","Fora"))) -> Fora | AR35: =IF(U35="","Não risco",IF((TODAY()-U35)<=7,"Risco","Não risco")) -> Não risco | AS35: =IF(SEARCH("integrar",P35)>0,"Sim","Não") -> #VALUE! | AT35: =IF(S35="",TODAY()-Q35,S35-Q35) -> 10 | AU35: =VLOOKUP(X35,'pontos focais'!C:D,2,0) -> DCMD Programação de Obra | AV35: =U35-Q35 -> -3
A36: 120 | B36: Visita Domo de Ferro | C36: Obra | D36: DESC | E36: 46150 | F36: Dian Cleiton de Brito | G36: Finalizada | H36: Finalizada | L36: SUL | M36: Bataguassu | N36: Diretoria | O36: Bataguassu | P36: Solicita agilizar obra de ponto de entrega e loteamento - obra 0302500469 Expectativa - 10/06/26. PE 7175625 OBRAS ASSOCIADAS AO PE FINALIDAS. | Q36: 46195 | R36: Dian, gentileza reavaliar a expectativa do cliente. Solicita agilizar obra de ponto de entrega e loteamento - obra 0302500469 Expectativa - 10/06/26. PE 7175625 | S36: 46259 | T36: Obras relacionadas ao PE concluídas. | W36: 46259 | X36: Dian Cleiton de Brito | Y36: Wander Machado | Z36: Paulo Roberto dos Santos | AA36: Dian Cleiton de Brito | AB36: Sim | AC36: Visita Domo de Ferro | AD36: 46268 | AE36: Moacir Costa Neto | AF36: 46259 | AG36: Wander Idalino Machado | AH36: 100 | AI36: 100 | AJ36: 100 | AN36: =VLOOKUP(M36,[1]municipios!$B:$D,3,0) -> NOVA ANDRADINA | AO36: =TODAY()-E36 -> 138 | AP36: =IF(AO36<=5,"0–5 dias",IF(AO36<=15,"6–15 dias",IF(AO36<=16,"16–30 dias",IF(AO36<=30,"30–50 dias",">50 dias")))) -> >50 dias | AQ36: =IF(U36="","Dentro",(IF(IF(W36="",TODAY(),W36)<=U36,"Dentro","Fora"))) -> Dentro | AR36: =IF(U36="","Não risco",IF((TODAY()-U36)<=7,"Risco","Não risco")) -> Não risco | AS36: =IF(SEARCH("integrar",P36)>0,"Sim","Não") -> #VALUE! | AT36: =IF(S36="",TODAY()-Q36,S36-Q36) -> 64 | AU36: =VLOOKUP(X36,'pontos focais'!C:D,2,0) -> Institucional | AV36: =U36-Q36 -> -46195
A37: 670 | B37: Visita Domo de Ferro | C37: Poda | D37: DCMD | E37: 46084 | F37: Danila Hertal Moreira Souza | G37: Em Andamento | H37: Finalizada | J37: 9000076 | L37: NORTE | M37: Corumbá | N37: Diretoria | O37: Corumbá | P37: Origem Externa: SANESUL Nome do Solicitante: RENATO MARCILIO DA SILVA Número Ofício: 6226/2025/PSEC/ALEMS Manifestação: Em 02/03/2026 - realizada reunião presencial na Energisa com os diretores da SANESUL para tratar da qualidade de fornecimento das unidades de Corumbá. Conforme documento anexo, cliente reclama de constantes oscilações no fornecimento de energia elétrica nas unidades de Corumbá. No Município não existem poços profundos, assim toda a produção de agua para o sistema ocorre através de captação superficial direto do rio Paraguai. UCs: 9000076 1717627 30723 1699438 1702111 1698960 1142916 Segue ofício em anexo. | Q37: 46191 | R37: Status atual: Em atuação campo (DEOP/DCMD). Origem Externa: SANESUL Nome do Solicitante: RENATO MARCILIO DA SILVA Número Ofício: 6226/2025/PSEC/ALEMS Manifestação: Em 02/03/2026 - realizada reunião presencial na Energisa com os diretores da SANESUL para tratar da qualidade de fornecimento das unidades de Corumbá. Conforme documento anexo, cliente reclama de constantes oscilações no fornecimento de energia elétrica nas unidades de Corumbá. No Município não existem poços profundos, assim toda a produção de agua para o sistema ocorre através de captação superficial direto do rio Paraguai. UCs: 9000076 1717627 30723 1699438 1702111 1698960 1142916 Segue ofício em anexo. | S37: 46269 | T37: Podas e limpeza de faixas concluidas dia 04/09/26 | U37: 46234 | W37: 46269 | X37: Evair Rogerio da Conceicao | Y37: Gabriella Domingo | AA37: Danila Hertal Moreira Souza | AB37: Sim | AC37: Visita Domo de Ferro | AD37: 46269 | AE37: Gabriella Amorim Domingo | AF37: 46269 | AG37: Gabriella Amorim Domingo | AH37: 100 | AI37: 100 | AJ37: 100 | AN37: =VLOOKUP(M37,[1]municipios!$B:$D,3,0) -> CORUMBA | AO37: =TODAY()-E37 -> 204 | AP37: =IF(AO37<=5,"0–5 dias",IF(AO37<=15,"6–15 dias",IF(AO37<=16,"16–30 dias",IF(AO37<=30,"30–50 dias",">50 dias")))) -> >50 dias | AQ37: =IF(U37="","Dentro",(IF(IF(W37="",TODAY(),W37)<=U37,"Dentro","Fora"))) -> Fora | AR37: =IF(U37="","Não risco",IF((TODAY()-U37)<=7,"Risco","Não risco")) -> Não risco | AS37: =IF(SEARCH("integrar",P37)>0,"Sim","Não") -> #VALUE! | AT37: =IF(S37="",TODAY()-Q37,S37-Q37) -> 78 | AU37: =VLOOKUP(X37,'pontos focais'!C:D,2,0) -> DCMD Manutenção | AV37: =U37-Q37 -> 43
A38: 670 | B38: Visita Domo de Ferro | C38: Qualidade | D38: DEOP | E38: 46084 | F38: Danila Hertal Moreira Souza | G38: Em Andamento | H38: Em Andamento | J38: 9000076 | L38: NORTE | M38: Corumbá | N38: Diretoria | O38: Corumbá | P38: Origem Externa: SANESUL Nome do Solicitante: RENATO MARCILIO DA SILVA Número Ofício: 6226/2025/PSEC/ALEMS Manifestação: Em 02/03/2026 - realizada reunião presencial na Energisa com os diretores da SANESUL para tratar da qualidade de fornecimento das unidades de Corumbá. Conforme documento anexo, cliente reclama de constantes oscilações no fornecimento de energia elétrica nas unidades de Corumbá. No Município não existem poços profundos, assim toda a produção de agua para o sistema ocorre através de captação superficial direto do rio Paraguai. UCs: 9000076 1717627 30723 1699438 1702111 1698960 1142916 Segue ofício em anexo. | Q38: 46233 | R38: Conforme pactuado na reunião de qualidade realizada em 23/07/2026, ficou como saída a instalação de 07 medidores para avaliação dos níveis de tensão das unidades reclamadas e refazer os estudos de religamentos. Conforme alinhado o DESC planilhou as unidades consumidoras por ordem de prioridade para as devidas atuações (planilha em anexo). | S38: 46269 | X38: Luan Henrique Soares Diniz Afonso | Y38: Gabriella Domingo | AA38: Danila Hertal Moreira Souza | AB38: Sim | AC38: Visita Domo de Ferro | AD38: 46269 | AE38: Gabriella Amorim Domingo | AF38: 46269 | AG38: Gabriella Amorim Domingo | AH38: 100 | AI38: 100 | AJ38: 100 | AN38: =VLOOKUP(M38,[1]municipios!$B:$D,3,0) -> CORUMBA | AO38: =TODAY()-E38 -> 204 | AP38: =IF(AO38<=5,"0–5 dias",IF(AO38<=15,"6–15 dias",IF(AO38<=16,"16–30 dias",IF(AO38<=30,"30–50 dias",">50 dias")))) -> >50 dias | AQ38: =IF(U38="","Dentro",(IF(IF(W38="",TODAY(),W38)<=U38,"Dentro","Fora"))) -> Dentro | AR38: =IF(U38="","Não risco",IF((TODAY()-U38)<=7,"Risco","Não risco")) -> Não risco | AS38: =IF(SEARCH("integrar",P38)>0,"Sim","Não") -> #VALUE! | AT38: =IF(S38="",TODAY()-Q38,S38-Q38) -> 36 | AU38: =VLOOKUP(X38,'pontos focais'!C:D,2,0) -> DEOP Qualidade | AV38: =U38-Q38 -> -46233
A39: 670 | B39: Visita Domo de Ferro | C39: Qualidade | D39: DESC | E39: 46084 | F39: Danila Hertal Moreira Souza | G39: Em Andamento | H39: Finalizada | J39: 9000076 | L39: NORTE | M39: Corumbá | N39: Diretoria | O39: Corumbá | P39: Origem Externa: SANESUL Nome do Solicitante: RENATO MARCILIO DA SILVA Número Ofício: 6226/2025/PSEC/ALEMS Manifestação: Em 02/03/2026 - realizada reunião presencial na Energisa com os diretores da SANESUL para tratar da qualidade de fornecimento das unidades de Corumbá. Conforme documento anexo, cliente reclama de constantes oscilações no fornecimento de energia elétrica nas unidades de Corumbá. No Município não existem poços profundos, assim toda a produção de agua para o sistema ocorre através de captação superficial direto do rio Paraguai. UCs: 9000076 1717627 30723 1699438 1702111 1698960 1142916 Segue ofício em anexo. | Q39: 46241 | R39: Notificar cliente sobre o andamento das ações e necessidade de apresentação de estudo de proteção, avaliar possível problemas internos | S39: 46255 | T39: NOTIFICAÇÃO ENVIADA | V39: 46252 | W39: 46255 | X39: Julio Cesar dos Santos Antonelo | Y39: Julio Antonelo | AA39: Danila Hertal Moreira Souza | AB39: Sim | AC39: Visita Domo de Ferro | AD39: 46259 | AE39: Moacir Costa Neto | AF39: 46255 | AG39: Julio Cesar dos Santos Antonelo | AH39: 100 | AI39: 100 | AJ39: 100 | AN39: =VLOOKUP(M39,[1]municipios!$B:$D,3,0) -> CORUMBA | AO39: =TODAY()-E39 -> 204 | AP39: =IF(AO39<=5,"0–5 dias",IF(AO39<=15,"6–15 dias",IF(AO39<=16,"16–30 dias",IF(AO39<=30,"30–50 dias",">50 dias")))) -> >50 dias | AQ39: =IF(U39="","Dentro",(IF(IF(W39="",TODAY(),W39)<=U39,"Dentro","Fora"))) -> Dentro | AR39: =IF(U39="","Não risco",IF((TODAY()-U39)<=7,"Risco","Não risco")) -> Não risco | AS39: =IF(SEARCH("integrar",P39)>0,"Sim","Não") -> #VALUE! | AT39: =IF(S39="",TODAY()-Q39,S39-Q39) -> 14 | AU39: =VLOOKUP(X39,'pontos focais'!C:D,2,0) -> DESC Agentes de Relacionamento | AV39: =U39-Q39 -> -46241
A40: 670 | B40: Visita Domo de Ferro | C40: Vazio | D40: DESC | E40: 46084 | F40: Danila Hertal Moreira Souza | G40: Em Andamento | H40: Em Andamento | I40: Sanesul | J40: 9000076 | L40: NORTE | M40: Corumbá | N40: Diretoria | O40: Corumbá | P40: Origem Externa: SANESUL Nome do Solicitante: RENATO MARCILIO DA SILVA Número Ofício: 6226/2025/PSEC/ALEMS Manifestação: Em 02/03/2026 - realizada reunião presencial na Energisa com os diretores da SANESUL para tratar da qualidade de fornecimento das unidades de Corumbá. Conforme documento anexo, cliente reclama de constantes oscilações no fornecimento de energia elétrica nas unidades de Corumbá. No Município não existem poços profundos, assim toda a produção de agua para o sistema ocorre através de captação superficial direto do rio Paraguai. UCs: 9000076 1717627 30723 1699438 1702111 1698960 1142916 Segue ofício em anexo. | Q40: 46274 | R40: Após a conclusão das ações por parte DEOP/DCMD, elaborar parecer e retornar ao cliente com as devolutivas. | X40: Julio Cesar dos Santos Antonelo | AA40: Danila Hertal Moreira Souza | AB40: Sim | AC40: Visita Domo de Ferro | AD40: 46274 | AE40: Rafael Penteado Rodrigues Martins | AF40: 46274 | AG40: Rafael Penteado Rodrigues Martins | AH40: 100 | AI40: 100 | AJ40: 50 | AM40: CGCP | AN40: =VLOOKUP(M40,[1]municipios!$B:$D,3,0) -> CORUMBA | AO40: =TODAY()-E40 -> 204 | AP40: =IF(AO40<=5,"0–5 dias",IF(AO40<=15,"6–15 dias",IF(AO40<=16,"16–30 dias",IF(AO40<=30,"30–50 dias",">50 dias")))) -> >50 dias | AQ40: =IF(U40="","Dentro",(IF(IF(W40="",TODAY(),W40)<=U40,"Dentro","Fora"))) -> Dentro | AR40: =IF(U40="","Não risco",IF((TODAY()-U40)<=7,"Risco","Não risco")) -> Não risco | AS40: =IF(SEARCH("integrar",P40)>0,"Sim","Não") -> #VALUE! | AT40: =IF(S40="",TODAY()-Q40,S40-Q40) -> 14 | AU40: =VLOOKUP(X40,'pontos focais'!C:D,2,0) -> DESC Agentes de Relacionamento | AV40: =U40-Q40 -> -46274
A41: 824 | B41: Visita Domo de Ferro | C41: Qualidade | D41: DEOP | E41: 46184 | F41: Monike Chaves | G41: Em Andamento | H41: Não Iniciada | L41: SUL | M41: ELDORADO | N41: Prefeitura | O41: Eldorado | P41: ATA DE REUNIÃO – ASSENTAMENTO FLORESTA BRANCA Data: 11 de junho de 2026 Local: Município de Eldorado/MS Participantes: Representantes da Prefeitura Municipal, Energisa MS, Vereadora Mara, moradores e produtores rurais do Assentamento Floresta Branca. Aos onze dias do mês de junho de dois mil e vinte e seis, realizou-se reunião entre representantes da Prefeitura Municipal de Eldorado, da Energisa MS e moradores do Assentamento Floresta Branca, com o objetivo de discutir os problemas relacionados ao fornecimento de energia elétrica na comunidade. A Prefeita Municipal abriu a reunião agradecendo a presença de todos e destacou a importância da participação da Vereadora Mara como representante da comunidade, enfatizando a necessidade de união entre população, poder público e concessionária para a busca de soluções efetivas. Durante a reunião, os moradores relataram diversos problemas relacionados ao fornecimento de energia elétrica, entre eles: * Quedas frequentes de energia, principalmente durante chuvas e ventos; * Oscilações constantes de tensão; * Rompimento de cabos da rede elétrica; * Queima de eletrodomésticos, motores, bombas d’água, ordenhadeiras, resfriadores de leite e outros equipamentos; * Demora no atendimento das ocorrências registradas junto à concessionária; * Problemas em transformadores considerados insuficientes para atender à demanda atual das propriedades; * Dificuldades para obtenção de ressarcimento por danos elétricos. A Vereadora Mara destacou que as reclamações são recorrentes e afetam grande parte das famílias do assentamento, mencionando casos específicos de prejuízos financeiros causados pela queima de equipamentos e pela interrupção das atividades produtivas. Representando a Energisa, o Supervisor de Construção e Manutenção, Sr. André, esclareceu os procedimentos adotados pela empresa, destacando a necessidade de registro das ocorrências por meio dos canais oficiais de atendimento e a importância da atualização cadastral das unidades consumidoras, especialmente quanto à declaração de carga instalada nas propriedades. Ficaram definidos os seguintes encaminhamentos: 1. A Energisa realizará uma inspeção geral na rede elétrica do Assentamento Floresta Branca; 2. Será efetuado levantamento das necessidades de poda de vegetação próxima à rede elétrica; 3. Serão analisados os casos de transformadores com possível necessidade de adequação ou aumento de capacidade; 4. A concessionária avaliará os protocolos de ressarcimento e as solicitações já registradas pelos moradores; 5. Será criado um grupo de comunicação entre representantes da comunidade e a Energisa para acompanhamento das demandas e divulgação das ações executadas; 6. A Energisa comprometeu-se a apresentar retorno à comunidade após a realização das inspeções e análises técnicas. Ao final da reunião, a Prefeita informou que o município está providenciando melhorias nas estradas do assentamento, mediante utilização de material fresado asfáltico recentemente disponibilizado para manutenção dos trechos mais críticos. Nada mais havendo a tratar, a reunião foi encerrada, ficando registrados os compromissos assumidos pelas partes para acompanhamento e solução das demandas apresentadas. Eldorado/MS, 11 de junho de 2026. | Q41: 46211 | R41: Ficaram definidos os seguintes encaminhamentos: 1. A Energisa realizará uma inspeção geral na rede elétrica do Assentamento Floresta Branca; 2. Será efetuado levantamento das necessidades de poda de vegetação próxima à rede elétrica; 3. Serão analisados os casos de transformadores com possível necessidade de adequação ou aumento de capacidade; 4. A concessionária avaliará os protocolos de ressarcimento e as solicitações já registradas pelos moradores; 5. Será criado um grupo de comunicação entre representantes da comunidade e a Energisa para acompanhamento das demandas e divulgação das ações executadas; 6. A Energisa comprometeu-se a apresentar retorno à comunidade após a realização das inspeções e análises técnicas. LUAN, QUAL PREVISÃO DAS CONCLUSÕES DAS AÇÕES? | S41: 46252 | X41: Luan Henrique Soares Diniz Afonso | Y41: Bruna Santos | Z41: Prefeita Fabiana Vereadora Mara Assentados Andre Guilherme Paulo Giovani | AA41: Monike Chaves | AB41: Sim | AC41: Agente de Relacionamento | AD41: 46268 | AE41: Moacir Costa Neto | AF41: 46252 | AG41: Bruna Fabiana Braguin dos Santos | AH41: 100 | AI41: 100 | AJ41: 75 | AN41: =VLOOKUP(M41,[1]municipios!$B:$D,3,0) -> NAVIRAI | AO41: =TODAY()-E41 -> 104 | AP41: =IF(AO41<=5,"0–5 dias",IF(AO41<=15,"6–15 dias",IF(AO41<=16,"16–30 dias",IF(AO41<=30,"30–50 dias",">50 dias")))) -> >50 dias | AQ41: =IF(U41="","Dentro",(IF(IF(W41="",TODAY(),W41)<=U41,"Dentro","Fora"))) -> Dentro | AR41: =IF(U41="","Não risco",IF((TODAY()-U41)<=7,"Risco","Não risco")) -> Não risco | AS41: =IF(SEARCH("integrar",P41)>0,"Sim","Não") -> #VALUE! | AT41: =IF(S41="",TODAY()-Q41,S41-Q41) -> 41 | AU41: =VLOOKUP(X41,'pontos focais'!C:D,2,0) -> DEOP Qualidade | AV41: =U41-Q41 -> -46211
A42: 825 | B42: Visita Domo de Ferro | C42: Ordem de Serviço | D42: DCMD | E42: 46206 | F42: Monike Chaves | G42: Finalizada | H42: Finalizada | L42: SUL | M42: Tacuru | N42: Prefeitura | O42: Tacuru | P42: OS 877 - ORÇAMENTO OS 548014238 - KATILENE OS 548017784 - VILINA OS 548023636 - MARILENE SOLICITAÇÃO APOS REUNIÃO | Q42: 46212 | R42: OS 877 - ORÇAMENTO OS 548014238 - KATILENE OS 548017784 - VILINA OS 548023636 - MARILENE SOLICITAÇÃO APOS REUNIÃO. Por favor agilizar atendimento das ordens de serviço supracitadas. | S42: 46252 | T42: OS'S FINALIZADAS | V42: 46238 | W42: 46238 | X42: Bruna Victoria Rodrigues Ricardes | Y42: Bruna Santos | Z42: Rui Pires AGEHAB | AB42: Sim | AC42: Visita Domo de Ferro | AD42: 46268 | AE42: Moacir Costa Neto | AF42: 46252 | AG42: Bruna Fabiana Braguin dos Santos | AH42: 100 | AI42: 100 | AJ42: 75 | AN42: =VLOOKUP(M42,[1]municipios!$B:$D,3,0) -> NAVIRAI | AO42: =TODAY()-E42 -> 82 | AP42: =IF(AO42<=5,"0–5 dias",IF(AO42<=15,"6–15 dias",IF(AO42<=16,"16–30 dias",IF(AO42<=30,"30–50 dias",">50 dias")))) -> >50 dias | AQ42: =IF(U42="","Dentro",(IF(IF(W42="",TODAY(),W42)<=U42,"Dentro","Fora"))) -> Dentro | AR42: =IF(U42="","Não risco",IF((TODAY()-U42)<=7,"Risco","Não risco")) -> Não risco | AS42: =IF(SEARCH("integrar",P42)>0,"Sim","Não") -> #VALUE! | AT42: =IF(S42="",TODAY()-Q42,S42-Q42) -> 40 | AU42: =VLOOKUP(X42,'pontos focais'!C:D,2,0) -> DCMD Orçamento e Projetos | AV42: =U42-Q42 -> -46212
A43: 831 | B43: Visita Domo de Ferro | C43: Obra | D43: DCMD | E43: 46211 | F43: Monike Chaves | G43: Finalizada | H43: Finalizada | K43: 0502600521 | L43: SUL | M43: Tacuru | N43: Prefeitura | O43: Tacuru | P43: Prefeito de Tacuru informou que o posto de saúde será construído com recursos federal e tem prazos. Agradeço analise a OS 545194335. | Q43: 46246 | R43: Por favor verificar possibilidade de agilizar atendimento da Obra 0502600521. | S43: 46258 | U43: 46253 | W43: 46252 | X43: Amanda Aparecida Teixeira dos Santos | Y43: Rafaela Almeida | Z43: Prefeito Rogerio. | AA43: Jonas Ortiz Rudis | AB43: Sim | AC43: Visita Domo de Ferro | AD43: 46268 | AE43: Moacir Costa Neto | AF43: 46258 | AG43: Rafaela Mattos de Almeida | AH43: 100 | AI43: 100 | AJ43: 100 | AN43: =VLOOKUP(M43,[1]municipios!$B:$D,3,0) -> NAVIRAI | AO43: =TODAY()-E43 -> 77 | AP43: =IF(AO43<=5,"0–5 dias",IF(AO43<=15,"6–15 dias",IF(AO43<=16,"16–30 dias",IF(AO43<=30,"30–50 dias",">50 dias")))) -> >50 dias | AQ43: =IF(U43="","Dentro",(IF(IF(W43="",TODAY(),W43)<=U43,"Dentro","Fora"))) -> Dentro | AR43: =IF(U43="","Não risco",IF((TODAY()-U43)<=7,"Risco","Não risco")) -> Não risco | AS43: =IF(SEARCH("integrar",P43)>0,"Sim","Não") -> #VALUE! | AT43: =IF(S43="",TODAY()-Q43,S43-Q43) -> 12 | AU43: =VLOOKUP(X43,'pontos focais'!C:D,2,0) -> DCMD Programação de Obra | AV43: =U43-Q43 -> 7
A44: 847 | B44: Visita Domo de Ferro | C44: Obra | D44: DCMD | E44: 46213 | F44: Monike Chaves | G44: Finalizada | H44: Finalizada | K44: 0402500933 | L44: SUL | M44: Ponta Porã | N44: Prefeitura | O44: Ponta Porã | P44: A solicitação refere-se a um poste localizado dentro do terreno da cliente, o que tem gerado diversos transtornos, pois ela precisa realizar manobras e desvios sempre que entra ou sai com seu veículo. Além disso, a cliente compareceu à agência bastante insatisfeita, relatando que um vizinho, cuja solicitação de obra foi registrada posteriormente, já está sendo atendido por uma intervenção na mesma rede, o que tem aumentado sua percepção de demora no atendimento do próprio pedido. Central do Cliente (12/08/2026): Em análise foi identificado que a obra 040-25-00933 encontra-se concluída fisicamente (04/08/2026). | Q44: 46213 | R44: A solicitação refere-se a um poste localizado dentro do terreno da cliente, o que tem gerado diversos transtornos, pois ela precisa realizar manobras e desvios sempre que entra ou sai com seu veículo. Além disso, a cliente compareceu à agência bastante insatisfeita, relatando que um vizinho, cuja solicitação de obra foi registrada posteriormente, já está sendo atendido por uma intervenção na mesma rede, o que tem aumentado sua percepção de demora no atendimento do próprio pedido. Obra: 0402500933 | S44: 46238 | T44: obra concluída 31/07 | U44: 46234 | V44: 46234 | W44: 46234 | X44: Felipe Souza do Nascimento | Y44: Amanda Santos | Z44: Cliente esteve na prefeitura e na agencia de atendimento informando que irá acionar a TV, pois o prazo de relocação do poste de dentro do seu terreno está vencido, e diarimente ela tem que deixar seu carro fora de casa. | AB44: Sim | AC44: Visita Domo de Ferro | AD44: 46268 | AE44: Moacir Costa Neto | AF44: 46238 | AG44: Amanda Aparecida Teixeira dos Santos | AH44: 100 | AI44: 100 | AJ44: 100 | AN44: =VLOOKUP(M44,[1]municipios!$B:$D,3,0) -> PONTA PORA | AO44: =TODAY()-E44 -> 75 | AP44: =IF(AO44<=5,"0–5 dias",IF(AO44<=15,"6–15 dias",IF(AO44<=16,"16–30 dias",IF(AO44<=30,"30–50 dias",">50 dias")))) -> >50 dias | AQ44: =IF(U44="","Dentro",(IF(IF(W44="",TODAY(),W44)<=U44,"Dentro","Fora"))) -> Dentro | AR44: =IF(U44="","Não risco",IF((TODAY()-U44)<=7,"Risco","Não risco")) -> Não risco | AS44: =IF(SEARCH("integrar",P44)>0,"Sim","Não") -> #VALUE! | AT44: =IF(S44="",TODAY()-Q44,S44-Q44) -> 25 | AU44: =VLOOKUP(X44,'pontos focais'!C:D,2,0) -> DCMD Programação de Obra | AV44: =U44-Q44 -> 21
A45: 861 | B45: Visita Domo de Ferro | C45: Obra | D45: DCMD | E45: 46217 | F45: Monike Chaves | G45: Finalizada | H45: Finalizada | L45: SUL | M45: Dourados | N45: Prefeitura | O45: Dourados | P45: Rua Araxá OS 549831406 Rua Delci leite Doffinger OS 549837530 Gentielza analisar a liberação desse orçamento antes do prazo de 30 dias, foi um erro interno que não gerou todas as ligações do ofício. | Q45: 46217 | R45: * Rua Araxá - OS 549831406 *Rua Delci leite Doffinger - OS 549837530 Gentileza analisar a liberação desses orçamentos antes do prazo de 30 dias, foi um erro interno que não gerou todas as ligações do ofício. | S45: 46254 | U45: 46288 | V45: 46227 | W45: 46244 | X45: Bruna Victoria Rodrigues Ricardes | Y45: Rafaela Almeida | Z45: Neilton - Engenheiro responsavel | AB45: Sim | AC45: Agente de Relacionamento | AD45: 46268 | AE45: Moacir Costa Neto | AF45: 46254 | AG45: Rafaela Mattos de Almeida | AH45: 100 | AI45: 100 | AJ45: 100 | AN45: =VLOOKUP(M45,[1]municipios!$B:$D,3,0) -> DOURADOS | AO45: =TODAY()-E45 -> 71 | AP45: =IF(AO45<=5,"0–5 dias",IF(AO45<=15,"6–15 dias",IF(AO45<=16,"16–30 dias",IF(AO45<=30,"30–50 dias",">50 dias")))) -> >50 dias | AQ45: =IF(U45="","Dentro",(IF(IF(W45="",TODAY(),W45)<=U45,"Dentro","Fora"))) -> Dentro | AR45: =IF(U45="","Não risco",IF((TODAY()-U45)<=7,"Risco","Não risco")) -> Risco | AS45: =IF(SEARCH("integrar",P45)>0,"Sim","Não") -> #VALUE! | AT45: =IF(S45="",TODAY()-Q45,S45-Q45) -> 37 | AU45: =VLOOKUP(X45,'pontos focais'!C:D,2,0) -> DCMD Orçamento e Projetos | AV45: =U45-Q45 -> 71
A46: 869 | B46: Visita Domo de Ferro | C46: Obra | D46: DCMD | E46: 46217 | F46: Availdo Taveira de Oliveira | G46: Finalizada | H46: Finalizada | K46: 0152600219 | L46: NORTE | M46: Jardim | N46: Prefeitura | O46: Jardim | P46: Visita Domo de Ferro. Por favor agilizar atendimento da Obra 0152600219. Expectativa do Cliente 31/07/2026. Solicitado apoio pelo vice-prefeito do municipio. Sem anexos. Central do Cliente (12/08/2026): Em análise foi identificado que a construção física da Obra 0152600219 está concluída | Q46: 46218 | R46: Visita Domo de Ferro. Por favor agilizar atendimento da Obra 0152600219. Expectativa do Cliente 31/07/2026. Solicitado apoio pelo vice-prefeito do município. Sem anexos. Availdo já alinhou o atendimento com o Supervisor Paulo Vitor e Coordenador Eduardo Batalha. | S46: 46225 | T46: OBRA CONCLUIDA 17/07 | U46: 46234 | W46: 46220 | X46: Felipe Souza do Nascimento | Y46: Amanda Santos | Z46: Agente de Relacionamento Availdo | AA46: Availdo Taveira de Oliveira | AB46: Sim | AC46: Visita Domo de Ferro | AD46: 46268 | AE46: Moacir Costa Neto | AF46: 46225 | AG46: Amanda Aparecida Teixeira dos Santos | AH46: 100 | AI46: 100 | AJ46: 100 | AN46: =VLOOKUP(M46,[1]municipios!$B:$D,3,0) -> JARDIM | AO46: =TODAY()-E46 -> 71 | AP46: =IF(AO46<=5,"0–5 dias",IF(AO46<=15,"6–15 dias",IF(AO46<=16,"16–30 dias",IF(AO46<=30,"30–50 dias",">50 dias")))) -> >50 dias | AQ46: =IF(U46="","Dentro",(IF(IF(W46="",TODAY(),W46)<=U46,"Dentro","Fora"))) -> Dentro | AR46: =IF(U46="","Não risco",IF((TODAY()-U46)<=7,"Risco","Não risco")) -> Não risco | AS46: =IF(SEARCH("integrar",P46)>0,"Sim","Não") -> #VALUE! | AT46: =IF(S46="",TODAY()-Q46,S46-Q46) -> 7 | AU46: =VLOOKUP(X46,'pontos focais'!C:D,2,0) -> DCMD Programação de Obra | AV46: =U46-Q46 -> 16
A47: 875 | B47: Visita Domo de Ferro | C47: Obra | D47: DCMD | E47: 46219 | F47: Monike Chaves | G47: Finalizada | H47: Finalizada | L47: SUL | M47: Ponta Porã | N47: Prefeitura | O47: Ponta Porã | P47: Gentielza priorizar tratativa de obra do loteamento de Ponta Porã, está parado a verba na caixa economica e tem prazos. OS 551631953. Documentos anexo a OS. | Q47: 46219 | R47: Gentileza priorizar tratativa de obra do loteamento de Ponta Porã, está parado a verba na caixa econômica e tem prazos. OS 551631953 Orçamento de Conexão.. Documentos anexo a OS. | S47: 46252 | T47: TRATA-SE DE LOTEAMENTO, DEVE TER PE PARA SEGUIMENTO | U47: 46234 | W47: 46252 | X47: Bruna Victoria Rodrigues Ricardes | Y47: Bruna Santos | Z47: secretario de obras Joelson | AB47: Sim | AC47: Visita Domo de Ferro | AD47: 46268 | AE47: Moacir Costa Neto | AF47: 46252 | AG47: Bruna Fabiana Braguin dos Santos | AH47: 100 | AI47: 100 | AJ47: 100 | AN47: =VLOOKUP(M47,[1]municipios!$B:$D,3,0) -> PONTA PORA | AO47: =TODAY()-E47 -> 69 | AP47: =IF(AO47<=5,"0–5 dias",IF(AO47<=15,"6–15 dias",IF(AO47<=16,"16–30 dias",IF(AO47<=30,"30–50 dias",">50 dias")))) -> >50 dias | AQ47: =IF(U47="","Dentro",(IF(IF(W47="",TODAY(),W47)<=U47,"Dentro","Fora"))) -> Fora | AR47: =IF(U47="","Não risco",IF((TODAY()-U47)<=7,"Risco","Não risco")) -> Não risco | AS47: =IF(SEARCH("integrar",P47)>0,"Sim","Não") -> #VALUE! | AT47: =IF(S47="",TODAY()-Q47,S47-Q47) -> 33 | AU47: =VLOOKUP(X47,'pontos focais'!C:D,2,0) -> DCMD Orçamento e Projetos | AV47: =U47-Q47 -> 15
A48: 893 | B48: Visita Domo de Ferro | C48: Atendimento Comercial | D48: DESC | E48: 46225 | F48: Dian Cleiton de Brito | G48: Em Andamento | H48: Não Iniciada | I48: Reinaldo Jobes Gonçalves | K48: 0602600372 | L48: CENTRO | M48: Inocência | N48: Prefeitura | O48: Inocência | P48: Obra para atender a usina de asfalto responsavel pelas obras no município. "Usina de Asfalto para Pavimentação da MS316, que está necessitando dessa área, já irão iniciar a cobertura com a Capa de Asfalto." Expectativa:. 20/08/26. | Q48: 46283 | R48: Por favor entrar em contato com o cliente para repactuação da expectativa. | X48: Marcelly Arce Avalo Franca | Z48: Antonio Ãngelo - Prefeito | AA48: Dian Cleiton de Brito | AB48: Sim | AC48: Visita Domo de Ferro | AD48: 46283 | AE48: Wander Idalino Machado | AF48: 46283 | AG48: Wander Idalino Machado | AH48: 100 | AI48: 100 | AJ48: 50 | AK48: Relacionamento com cliente | AM48: CGCP | AN48: =VLOOKUP(M48,[1]municipios!$B:$D,3,0) -> PARANAIBA | AO48: =TODAY()-E48 -> 63 | AP48: =IF(AO48<=5,"0–5 dias",IF(AO48<=15,"6–15 dias",IF(AO48<=16,"16–30 dias",IF(AO48<=30,"30–50 dias",">50 dias")))) -> >50 dias | AQ48: =IF(U48="","Dentro",(IF(IF(W48="",TODAY(),W48)<=U48,"Dentro","Fora"))) -> Dentro | AR48: =IF(U48="","Não risco",IF((TODAY()-U48)<=7,"Risco","Não risco")) -> Não risco | AS48: =IF(SEARCH("integrar",P48)>0,"Sim","Não") -> #VALUE! | AT48: =IF(S48="",TODAY()-Q48,S48-Q48) -> 5 | AU48: =VLOOKUP(X48,'pontos focais'!C:D,2,0) -> DESC Agentes de Relacionamento | AV48: =U48-Q48 -> -46283
A49: 893 | B49: Visita Domo de Ferro | C49: Obra | D49: DCMD | E49: 46225 | F49: Dian Cleiton de Brito | G49: Em Andamento | H49: Não Iniciada | I49: Reinaldo Jobes Gonçalves | K49: 0602600372 | L49: CENTRO | M49: Inocência | N49: Prefeitura | O49: Inocência | P49: Obra para atender a usina de asfalto responsavel pelas obras no município. "Usina de Asfalto para Pavimentação da MS316, que está necessitando dessa área, já irão iniciar a cobertura com a Capa de Asfalto." Expectativa:. 20/08/26. | Q49: 46283 | R49: Obra 0602600372 - Por favor incluir na programação. | X49: Amanda Aparecida Teixeira dos Santos | Z49: Antonio Ãngelo - Prefeito | AA49: Dian Cleiton de Brito | AB49: Sim | AC49: Visita Domo de Ferro | AD49: 46283 | AE49: Wander Idalino Machado | AF49: 46283 | AG49: Wander Idalino Machado | AH49: 100 | AI49: 100 | AJ49: 50 | AK49: Programação de Obras e Gestão de Materiais | AM49: DCMD - PROGRAMAÇÃO DE OBRA | AN49: =VLOOKUP(M49,[1]municipios!$B:$D,3,0) -> PARANAIBA | AO49: =TODAY()-E49 -> 63 | AP49: =IF(AO49<=5,"0–5 dias",IF(AO49<=15,"6–15 dias",IF(AO49<=16,"16–30 dias",IF(AO49<=30,"30–50 dias",">50 dias")))) -> >50 dias | AQ49: =IF(U49="","Dentro",(IF(IF(W49="",TODAY(),W49)<=U49,"Dentro","Fora"))) -> Dentro | AR49: =IF(U49="","Não risco",IF((TODAY()-U49)<=7,"Risco","Não risco")) -> Não risco | AS49: =IF(SEARCH("integrar",P49)>0,"Sim","Não") -> #VALUE! | AT49: =IF(S49="",TODAY()-Q49,S49-Q49) -> 5 | AU49: =VLOOKUP(X49,'pontos focais'!C:D,2,0) -> DCMD Programação de Obra | AV49: =U49-Q49 -> -46283
A50: 898 | B50: Visita Domo de Ferro | C50: Informação | D50: DESC | E50: 46225 | F50: Monike Chaves | G50: Finalizada | H50: Finalizada | K50: 0302500580 - 0302600271 - 0302600248 | L50: SUL | M50: Angélica | N50: Prefeitura | O50: Angélica | P50: ATA DE REUNIÃO Data: 23/07 2026 Local: Prefeitura Municipal de Angélica – MS Participantes: Representantes da Prefeitura Municipal de Angélica, Energisa MS, Secretários Municipais. Pauta * Fortalecimento da parceria entre Prefeitura e Energisa. * Manejo da arborização urbana e convênio de poda. * Programação de desligamentos e intervenções na rede elétrica. * Demandas relacionadas à qualidade do fornecimento de energia. * Sobrecarga da rede elétrica e aumento de carga. * Acompanhamento de solicitações técnicas em unidades públicas. Desenvolvimento da reunião A reunião teve como objetivo alinhar o relacionamento entre a Prefeitura de Angélica e a Energisa, fortalecendo a comunicação entre as equipes técnicas e operacionais para agilizar o atendimento das demandas do município. Inicialmente, foi apresentada a estrutura operacional da Energisa responsável pela região sul do Estado, destacando o atendimento realizado pelas equipes locais, pelo supervisor regional e pelo técnico responsável pela área, bem como os canais de atendimento disponíveis para o município. O prefeito ressaltou que um dos principais desafios enfrentados atualmente é a arborização urbana. Foi informado que diversas árvores foram plantadas em gestões anteriores sem planejamento adequado, estando hoje em conflito com a rede elétrica, o que ocasiona interrupções no fornecimento de energia, riscos operacionais e aumento dos custos de manutenção. Também foi relatada a dificuldade em programar desligamentos da rede para execução das podas, reforçando a necessidade de maior integração entre Prefeitura e Energisa para planejamento conjunto das intervenções. A Energisa esclareceu que, atualmente, os desligamentos programados são bastante restritos em razão das exigências regulatórias da ANEEL, motivo pelo qual a concessionária prioriza, sempre que possível, a utilização de equipes de Linha Viva para realização dos serviços com a rede energizada. Como alternativa, foi sugerido que a Prefeitura encaminhe, com antecedência, sua programação semanal ou pontual de podas por meio de ofício direcionado ao canal de atendimento do Poder Público. Dessa forma, a concessionária poderá avaliar cada situação e compatibilizar o cronograma das equipes. Durante a reunião foi destacado que o município possui interesse em manter uma parceria permanente com a Energisa para que as equipes possam atuar de forma coordenada, evitando riscos, reduzindo impactos à população e garantindo maior eficiência nas ações. Na sequência, foi discutido o Convênio de Poda encaminhado anteriormente pela Energisa ao município. Ficou registrado que o documento foi enviado à Secretaria Municipal de Meio Ambiente e será verificada sua tramitação para assinatura. Foi reforçado que o convênio prevê: * atuação da Energisa nas podas emergenciais e nas intervenções em vegetação que oferece risco à rede elétrica; * apoio da Prefeitura na retirada e destinação dos resíduos vegetais; * maior agilidade nas autorizações necessárias; * segurança jurídica para execução dos serviços; * possibilidade de atendimento de árvores em situação crítica mediante solicitação formal do município. O prefeito destacou que o convênio auxiliará o município perante os órgãos de fiscalização e controle, além de facilitar o planejamento das futuras intervenções. Também foi apresentada pela Energisa a possibilidade de utilização do viveiro de mudas da concessionária para doação de espécies adequadas ao plantio urbano, incentivando a substituição gradual das árvores incompatíveis com a rede elétrica por espécies apropriadas. Na sequência, foram discutidas ocorrências relacionadas ao fornecimento de energia elétrica. Foi citado como exemplo positivo um problema recorrente em determinado setor da cidade que foi solucionado após a retirada de uma árvore em conflito com a rede elétrica, eliminando as interrupções registradas anteriormente. O prefeito também relatou ocorrências de oscilações de tensão em alguns bairros e destacou a necessidade de análise técnica sempre que identificadas situações semelhantes. A Energisa explicou que diversos casos decorrem do aumento de carga das unidades consumidoras, quando os clientes ampliam suas instalações elétricas sem comunicar previamente a distribuidora. Nesses casos, é necessária a solicitação formal para análise e eventual redimensionamento da carga. Outro tema abordado foi o crescimento da geração distribuída por meio de sistemas fotovoltaicos. A Energisa explicou que o aumento expressivo das instalações de energia solar tem provocado novos desafios operacionais em todo o Estado, exigindo elevados investimentos em ampliação e modernização do sistema elétrico. Informou ainda que o plano de investimentos da concessionária contempla aproximadamente R$ 1 bilhão em obras para reforço da rede elétrica. Em relação às unidades públicas, foi discutida a situação da Escola Municipal Napoleão. A Prefeitura informou que a unidade apresenta dificuldades para utilização dos aparelhos de ar-condicionado, principalmente após a instalação de um empreendimento comercial nas proximidades. Foi esclarecido que a escola possui três unidades consumidoras (três medidores), distribuídas entre os blocos da edificação, e que já havia sido encaminhada solicitação anterior para análise do transformador. A Energisa informou que realizará: * verificação da carga cadastrada da unidade; * análise dos ofícios anteriormente protocolados; * aferição dos níveis de tensão; * avaliação da necessidade de medições em campo; * estudo sobre eventual redimensionamento da instalação. Também foi solicitado que sejam encaminhados novamente os números dos protocolos anteriores e fotografias dos medidores para facilitar a análise. Durante a reunião surgiu ainda a possibilidade de ampliar a avaliação para todo o complexo escolar, incluindo a creche localizada na mesma quadra, totalizando quatro unidades consumidoras. Ao final, os participantes reforçaram a importância da manutenção da comunicação direta entre Prefeitura e Energisa para solução rápida das demandas técnicas, planejamento das podas, melhorias na qualidade do fornecimento de energia e fortalecimento da parceria institucional. Encaminhamentos 1. Verificar internamente a situação do Convênio de Poda encaminhado pela Energisa e providenciar sua formalização. 2. A Prefeitura encaminhará programação de podas por meio de ofício ao canal do Poder Público da Energisa. 3. A Energisa realizará análise técnica da Escola Municipal Napoleão, incluindo medição de tensão e avaliação da carga instalada. 4. A Prefeitura enviará novamente os protocolos anteriores e fotografias dos medidores da unidade escolar. 5. Avaliar tecnicamente todo o complexo escolar, incluindo a creche localizada na mesma quadra. 6. Manter comunicação direta entre as equipes técnicas para programação de intervenções na rede elétrica e manejo da arborização urbana. 7. Fortalecer a parceria para substituição gradual de espécies arbóreas inadequadas por espécies compatíveis com a rede elétrica. E por ultimo ateção na obra 0302600271 - 0302600248, mudança de postes para atender demanda com urgencia 0, recurso parado. 0302500580 e poste com risco de barida pois está no meio da rua. | Q50: 46226 | R50: Agente Monike, informo que as obras mencionadas já estão cadastradas no APP da Central. Obra 0302600271 - suspensa em 15/07/2026 necessário aprovação de projeto de travessia de rodovia (AGESUL) - cadastrada através do ID 891. Obra 0302600248 - orçamento aprovado pelo cliente na data de 15/07/2026. cadastrada através do ID 818. Obra 0302500580 - cadastrada através do ID 898, ação já direcionada a área responsável para as devidas tratativas. | S50: 46253 | W50: 46253 | X50: Monike Chaves | Y50: Bruna Santos | Z50: Prefeito Edinho Diretora de Planejamento e Obras Natyla Secretario de obras Renato Diego Coodenador Energisa Monike Agente | AA50: Diego Souza Silva | AB50: Sim | AC50: Visita Domo de Ferro | AD50: 46268 | AE50: Moacir Costa Neto | AF50: 46253 | AG50: Bruna Fabiana Braguin dos Santos | AH50: 100 | AI50: 100 | AJ50: 100 | AN50: =VLOOKUP(M50,[1]municipios!$B:$D,3,0) -> NOVA ANDRADINA | AO50: =TODAY()-E50 -> 63 | AP50: =IF(AO50<=5,"0–5 dias",IF(AO50<=15,"6–15 dias",IF(AO50<=16,"16–30 dias",IF(AO50<=30,"30–50 dias",">50 dias")))) -> >50 dias | AQ50: =IF(U50="","Dentro",(IF(IF(W50="",TODAY(),W50)<=U50,"Dentro","Fora"))) -> Dentro | AR50: =IF(U50="","Não risco",IF((TODAY()-U50)<=7,"Risco","Não risco")) -> Não risco | AS50: =IF(SEARCH("integrar",P50)>0,"Sim","Não") -> #VALUE! | AT50: =IF(S50="",TODAY()-Q50,S50-Q50) -> 27 | AU50: =VLOOKUP(X50,'pontos focais'!C:D,2,0) -> DESC Agentes de Relacionamento | AV50: =U50-Q50 -> -46226
A51: 898 | B51: Visita Domo de Ferro | C51: Obra | D51: DCMD | E51: 46225 | F51: Monike Chaves | G51: Finalizada | H51: Finalizada | K51: 0302500580 | L51: SUL | M51: Angélica | N51: Prefeitura | O51: Angélica | P51: ATA DE REUNIÃO Data: 23/07 2026 Local: Prefeitura Municipal de Angélica – MS Participantes: Representantes da Prefeitura Municipal de Angélica, Energisa MS, Secretários Municipais. Pauta * Fortalecimento da parceria entre Prefeitura e Energisa. * Manejo da arborização urbana e convênio de poda. * Programação de desligamentos e intervenções na rede elétrica. * Demandas relacionadas à qualidade do fornecimento de energia. * Sobrecarga da rede elétrica e aumento de carga. * Acompanhamento de solicitações técnicas em unidades públicas. Desenvolvimento da reunião A reunião teve como objetivo alinhar o relacionamento entre a Prefeitura de Angélica e a Energisa, fortalecendo a comunicação entre as equipes técnicas e operacionais para agilizar o atendimento das demandas do município. Inicialmente, foi apresentada a estrutura operacional da Energisa responsável pela região sul do Estado, destacando o atendimento realizado pelas equipes locais, pelo supervisor regional e pelo técnico responsável pela área, bem como os canais de atendimento disponíveis para o município. O prefeito ressaltou que um dos principais desafios enfrentados atualmente é a arborização urbana. Foi informado que diversas árvores foram plantadas em gestões anteriores sem planejamento adequado, estando hoje em conflito com a rede elétrica, o que ocasiona interrupções no fornecimento de energia, riscos operacionais e aumento dos custos de manutenção. Também foi relatada a dificuldade em programar desligamentos da rede para execução das podas, reforçando a necessidade de maior integração entre Prefeitura e Energisa para planejamento conjunto das intervenções. A Energisa esclareceu que, atualmente, os desligamentos programados são bastante restritos em razão das exigências regulatórias da ANEEL, motivo pelo qual a concessionária prioriza, sempre que possível, a utilização de equipes de Linha Viva para realização dos serviços com a rede energizada. Como alternativa, foi sugerido que a Prefeitura encaminhe, com antecedência, sua programação semanal ou pontual de podas por meio de ofício direcionado ao canal de atendimento do Poder Público. Dessa forma, a concessionária poderá avaliar cada situação e compatibilizar o cronograma das equipes. Durante a reunião foi destacado que o município possui interesse em manter uma parceria permanente com a Energisa para que as equipes possam atuar de forma coordenada, evitando riscos, reduzindo impactos à população e garantindo maior eficiência nas ações. Na sequência, foi discutido o Convênio de Poda encaminhado anteriormente pela Energisa ao município. Ficou registrado que o documento foi enviado à Secretaria Municipal de Meio Ambiente e será verificada sua tramitação para assinatura. Foi reforçado que o convênio prevê: * atuação da Energisa nas podas emergenciais e nas intervenções em vegetação que oferece risco à rede elétrica; * apoio da Prefeitura na retirada e destinação dos resíduos vegetais; * maior agilidade nas autorizações necessárias; * segurança jurídica para execução dos serviços; * possibilidade de atendimento de árvores em situação crítica mediante solicitação formal do município. O prefeito destacou que o convênio auxiliará o município perante os órgãos de fiscalização e controle, além de facilitar o planejamento das futuras intervenções. Também foi apresentada pela Energisa a possibilidade de utilização do viveiro de mudas da concessionária para doação de espécies adequadas ao plantio urbano, incentivando a substituição gradual das árvores incompatíveis com a rede elétrica por espécies apropriadas. Na sequência, foram discutidas ocorrências relacionadas ao fornecimento de energia elétrica. Foi citado como exemplo positivo um problema recorrente em determinado setor da cidade que foi solucionado após a retirada de uma árvore em conflito com a rede elétrica, eliminando as interrupções registradas anteriormente. O prefeito também relatou ocorrências de oscilações de tensão em alguns bairros e destacou a necessidade de análise técnica sempre que identificadas situações semelhantes. A Energisa explicou que diversos casos decorrem do aumento de carga das unidades consumidoras, quando os clientes ampliam suas instalações elétricas sem comunicar previamente a distribuidora. Nesses casos, é necessária a solicitação formal para análise e eventual redimensionamento da carga. Outro tema abordado foi o crescimento da geração distribuída por meio de sistemas fotovoltaicos. A Energisa explicou que o aumento expressivo das instalações de energia solar tem provocado novos desafios operacionais em todo o Estado, exigindo elevados investimentos em ampliação e modernização do sistema elétrico. Informou ainda que o plano de investimentos da concessionária contempla aproximadamente R$ 1 bilhão em obras para reforço da rede elétrica. Em relação às unidades públicas, foi discutida a situação da Escola Municipal Napoleão. A Prefeitura informou que a unidade apresenta dificuldades para utilização dos aparelhos de ar-condicionado, principalmente após a instalação de um empreendimento comercial nas proximidades. Foi esclarecido que a escola possui três unidades consumidoras (três medidores), distribuídas entre os blocos da edificação, e que já havia sido encaminhada solicitação anterior para análise do transformador. A Energisa informou que realizará: * verificação da carga cadastrada da unidade; * análise dos ofícios anteriormente protocolados; * aferição dos níveis de tensão; * avaliação da necessidade de medições em campo; * estudo sobre eventual redimensionamento da instalação. Também foi solicitado que sejam encaminhados novamente os números dos protocolos anteriores e fotografias dos medidores para facilitar a análise. Durante a reunião surgiu ainda a possibilidade de ampliar a avaliação para todo o complexo escolar, incluindo a creche localizada na mesma quadra, totalizando quatro unidades consumidoras. Ao final, os participantes reforçaram a importância da manutenção da comunicação direta entre Prefeitura e Energisa para solução rápida das demandas técnicas, planejamento das podas, melhorias na qualidade do fornecimento de energia e fortalecimento da parceria institucional. Encaminhamentos 1. Verificar internamente a situação do Convênio de Poda encaminhado pela Energisa e providenciar sua formalização. 2. A Prefeitura encaminhará programação de podas por meio de ofício ao canal do Poder Público da Energisa. 3. A Energisa realizará análise técnica da Escola Municipal Napoleão, incluindo medição de tensão e avaliação da carga instalada. 4. A Prefeitura enviará novamente os protocolos anteriores e fotografias dos medidores da unidade escolar. 5. Avaliar tecnicamente todo o complexo escolar, incluindo a creche localizada na mesma quadra. 6. Manter comunicação direta entre as equipes técnicas para programação de intervenções na rede elétrica e manejo da arborização urbana. 7. Fortalecer a parceria para substituição gradual de espécies arbóreas inadequadas por espécies compatíveis com a rede elétrica. E por ultimo ateção na obra 0302600271 - 0302600248, mudança de postes para atender demanda com urgencia 0, recurso parado. 0302500580 e poste com risco de barida pois está no meio da rua. | Q51: 46226 | R51: Por favor verificar possibilidade de agilizar atendimento da Obra 0302500580 - Deslocamento de Poste. | S51: 46269 | T51: "No dia 31/08, não foi possível realizar a execução, pois não conseguimos contato com o COI. O local estava sem sinal de rádio e de celular, impossibilitando a comunicação necessária para continuidade da atividade. A obra foi reprogramada para o dia 29/09." respondido no ID 938 | U51: 46356 | X51: Amanda Aparecida Teixeira dos Santos | Y51: Amanda Santos | Z51: Prefeito Edinho Diretora de Planejamento e Obras Natyla Secretario de obras Renato Diego Coodenador Energisa Monike Agente | AA51: Diego Souza Silva | AB51: Sim | AC51: Visita Domo de Ferro | AD51: 46269 | AE51: Amanda Aparecida Teixeira dos Santos | AF51: 46269 | AG51: Amanda Aparecida Teixeira dos Santos | AH51: 100 | AI51: 100 | AJ51: 100 | AN51: =VLOOKUP(M51,[1]municipios!$B:$D,3,0) -> NOVA ANDRADINA | AO51: =TODAY()-E51 -> 63 | AP51: =IF(AO51<=5,"0–5 dias",IF(AO51<=15,"6–15 dias",IF(AO51<=16,"16–30 dias",IF(AO51<=30,"30–50 dias",">50 dias")))) -> >50 dias | AQ51: =IF(U51="","Dentro",(IF(IF(W51="",TODAY(),W51)<=U51,"Dentro","Fora"))) -> Dentro | AR51: =IF(U51="","Não risco",IF((TODAY()-U51)<=7,"Risco","Não risco")) -> Risco | AS51: =IF(SEARCH("integrar",P51)>0,"Sim","Não") -> #VALUE! | AT51: =IF(S51="",TODAY()-Q51,S51-Q51) -> 43 | AU51: =VLOOKUP(X51,'pontos focais'!C:D,2,0) -> DCMD Programação de Obra | AV51: =U51-Q51 -> 130
A52: 906 | B52: Visita Domo de Ferro | C52: Obra | D52: DCMD | E52: 46227 | F52: Monike Chaves | G52: Finalizada | H52: Finalizada | K52: 0202601007 | L52: SUL | M52: Fátima do Sul | N52: Mídia | O52: Fátima do Sul | P52: Solicito por favor inserir este caso para acompanhamento na central, esse cliente teve sua jornada de ligação nova iniciada em 28/04, porém teve sua ordem de serviço transitando entre a baixa de campo e a baixa de projeto sem avanço das etapas necessárias para início da obra, apenas em 10/06 (43 dias após o pedido) seu processo seguiu o trâmite correto, sendo gerado obra para atendimento. Gentileza verificar a possibilidade de executarmos em caráter emergencial. CLIENTE ATENDIDO MEDIDOR INSTALADO N6283376261 | Q52: 46230 | R52: 0202601007 | S52: 46255 | U52: 46265 | V52: 46239 | W52: 46244 | X52: Amanda Aparecida Teixeira dos Santos | Y52: Rafaela Almeida | Z52: Diego Souza Silva | AA52: Diego Souza Silva | AB52: Sim | AC52: Visita Domo de Ferro | AD52: 46268 | AE52: Moacir Costa Neto | AF52: 46255 | AG52: Rafaela Mattos de Almeida | AH52: 50 | AI52: 50 | AJ52: 50 | AN52: =VLOOKUP(M52,[1]municipios!$B:$D,3,0) -> RIO BRILHANTE | AO52: =TODAY()-E52 -> 61 | AP52: =IF(AO52<=5,"0–5 dias",IF(AO52<=15,"6–15 dias",IF(AO52<=16,"16–30 dias",IF(AO52<=30,"30–50 dias",">50 dias")))) -> >50 dias | AQ52: =IF(U52="","Dentro",(IF(IF(W52="",TODAY(),W52)<=U52,"Dentro","Fora"))) -> Dentro | AR52: =IF(U52="","Não risco",IF((TODAY()-U52)<=7,"Risco","Não risco")) -> Não risco | AS52: =IF(SEARCH("integrar",P52)>0,"Sim","Não") -> #VALUE! | AT52: =IF(S52="",TODAY()-Q52,S52-Q52) -> 25 | AU52: =VLOOKUP(X52,'pontos focais'!C:D,2,0) -> DCMD Programação de Obra | AV52: =U52-Q52 -> 35
A53: 933 | B53: Visita Domo de Ferro | C53: Informação | D53: DESC | E53: 46234 | F53: Giovani Moura Sousa | G53: Finalizada | H53: Não Iniciada | I53: Assentamento Laga Grande | L53: SUL | M53: Dourados | N53: Câmara | O53: Dourados | P53: Solicitado a troca do transformador de 25 kv para um de 45 kv. Transformador localizado às proximidades das UC's abaixo: 10/912450-4 10/904447-0 1.223.596.051-09 | Q53: 46246 | R53: Por gentileza elaborar resposta e direcionar à Câmara Municipal de Dourados - Ofício 019/2026, pois a solicitação precisa ser protocolada individualmente pelos interessados. | X53: CRISLAINE ARRUDA DA SILVA | Z53: Vereador Rogério | AA53: Giovani Moura Sousa | AB53: Sim | AC53: Visita Domo de Ferro | AD53: 46268 | AE53: Moacir Costa Neto | AF53: 46246 | AG53: Wander Idalino Machado | AH53: 25 | AI53: 25 | AJ53: 12.5 | AN53: =VLOOKUP(M53,[1]municipios!$B:$D,3,0) -> DOURADOS | AO53: =TODAY()-E53 -> 54 | AP53: =IF(AO53<=5,"0–5 dias",IF(AO53<=15,"6–15 dias",IF(AO53<=16,"16–30 dias",IF(AO53<=30,"30–50 dias",">50 dias")))) -> >50 dias | AQ53: =IF(U53="","Dentro",(IF(IF(W53="",TODAY(),W53)<=U53,"Dentro","Fora"))) -> Dentro | AR53: =IF(U53="","Não risco",IF((TODAY()-U53)<=7,"Risco","Não risco")) -> Não risco | AS53: =IF(SEARCH("integrar",P53)>0,"Sim","Não") -> #VALUE! | AT53: =IF(S53="",TODAY()-Q53,S53-Q53) -> 42 | AU53: =VLOOKUP(X53,'pontos focais'!C:D,2,0) -> DESC Ofícios | AV53: =U53-Q53 -> -46246
A54: 933 | B54: Visita Domo de Ferro | C54: Obra | D54: DCMD | E54: 46234 | F54: Giovani Moura Sousa | G54: Finalizada | H54: Finalizada | L54: SUL | M54: Dourados | N54: Câmara | O54: Dourados | P54: Solicitado a troca do transformador de 25 kv para um de 45 kv. Transformador localizado às proximidades das UC's abaixo: 10/912450-4 10/904447-0 1.223.596.051-09 | Q54: 46237 | R54: Solicitado a troca do transformador de 25 kv para um de 45 kv. Transformador localizado às proximidades das UC's abaixo: 10/912450-4 10/904447-0 1.223.596.051-09 | S54: 46255 | U54: 46265 | W54: 46239 | X54: Bruno Camargo de Souza | Y54: Rafaela Almeida | Z54: Vereador Rogério | AA54: Giovani Moura Sousa | AB54: Sim | AC54: Visita Domo de Ferro | AD54: 46268 | AE54: Moacir Costa Neto | AF54: 46255 | AG54: Rafaela Mattos de Almeida | AH54: 25 | AI54: 25 | AJ54: 25 | AN54: =VLOOKUP(M54,[1]municipios!$B:$D,3,0) -> DOURADOS | AO54: =TODAY()-E54 -> 54 | AP54: =IF(AO54<=5,"0–5 dias",IF(AO54<=15,"6–15 dias",IF(AO54<=16,"16–30 dias",IF(AO54<=30,"30–50 dias",">50 dias")))) -> >50 dias | AQ54: =IF(U54="","Dentro",(IF(IF(W54="",TODAY(),W54)<=U54,"Dentro","Fora"))) -> Dentro | AR54: =IF(U54="","Não risco",IF((TODAY()-U54)<=7,"Risco","Não risco")) -> Não risco | AS54: =IF(SEARCH("integrar",P54)>0,"Sim","Não") -> #VALUE! | AT54: =IF(S54="",TODAY()-Q54,S54-Q54) -> 18 | AU54: =VLOOKUP(X54,'pontos focais'!C:D,2,0) -> DCMD Orçamento e Projetos | AV54: =U54-Q54 -> 28
A55: 938 | B55: Visita Domo de Ferro | C55: Obra | D55: DCMD | E55: 46227 | F55: Monike Chaves | G55: Em Andamento | H55: Em Andamento | K55: 0302500580 | L55: SUL | M55: Angélica | N55: Prefeitura | O55: Angélica | P55: Prefeitura solicitou agilidade na realocação de 2 postes em Ipezal. Visita realizada pelo Projeto Integrar - Registro ID 123 | Q55: 46233 | R55: Prefeitura solicitou agilidade na realocação de 2 postes em Ipezal. Visita realizada pelo Projeto Integrar - Registro ID 123 | S55: 46269 | T55: No dia 31/08, não foi possível realizar a execução, pois não conseguimos contato com o COI. O local estava sem sinal de rádio e de celular, impossibilitando a comunicação necessária para continuidade da atividade. A obra foi reprogramada para o dia 29/09. | U55: 46295 | V55: 46294 | X55: Amanda Aparecida Teixeira dos Santos | Y55: Amanda Santos | AA55: Diego Souza Silva | AB55: Sim | AC55: Visita Domo de Ferro | AD55: 46269 | AE55: Amanda Aparecida Teixeira dos Santos | AF55: 46269 | AG55: Amanda Aparecida Teixeira dos Santos | AH55: 100 | AI55: 100 | AJ55: 100 | AN55: =VLOOKUP(M55,[1]municipios!$B:$D,3,0) -> NOVA ANDRADINA | AO55: =TODAY()-E55 -> 61 | AP55: =IF(AO55<=5,"0–5 dias",IF(AO55<=15,"6–15 dias",IF(AO55<=16,"16–30 dias",IF(AO55<=30,"30–50 dias",">50 dias")))) -> >50 dias | AQ55: =IF(U55="","Dentro",(IF(IF(W55="",TODAY(),W55)<=U55,"Dentro","Fora"))) -> Dentro | AR55: =IF(U55="","Não risco",IF((TODAY()-U55)<=7,"Risco","Não risco")) -> Risco | AS55: =IF(SEARCH("integrar",P55)>0,"Sim","Não") -> Sim | AT55: =IF(S55="",TODAY()-Q55,S55-Q55) -> 36 | AU55: =VLOOKUP(X55,'pontos focais'!C:D,2,0) -> DCMD Programação de Obra | AV55: =U55-Q55 -> 62
A56: 942 | B56: Visita Domo de Ferro | C56: Poda | D56: DCMD | E56: 46136 | F56: Availdo Taveira de Oliveira | G56: Em Andamento | H56: Não Iniciada | L56: CENTRO | M56: Corguinho | N56: Prefeitura | O56: Corguinho | P56: Visita realizada pelo Projeto Integrar - Registro ID 74 | Q56: 46234 | R56: Podar Árvore em frente a Dona Cândida na comunidade baianopolis, Visita realizada pelo Projeto Integrar - Registro ID 74 | S56: 46253 | X56: Evair Rogerio da Conceicao | Y56: Bruna Santos | Z56: Fabricio Silva | AA56: Fabricio Cerchiari da Silva | AB56: Sim | AC56: Visita Domo de Ferro | AD56: 46268 | AE56: Moacir Costa Neto | AF56: 46253 | AG56: Bruna Fabiana Braguin dos Santos | AH56: 100 | AI56: 100 | AJ56: 100 | AN56: =VLOOKUP(M56,[1]municipios!$B:$D,3,0) -> CAMPO GRANDE INTERIOR | AO56: =TODAY()-E56 -> 152 | AP56: =IF(AO56<=5,"0–5 dias",IF(AO56<=15,"6–15 dias",IF(AO56<=16,"16–30 dias",IF(AO56<=30,"30–50 dias",">50 dias")))) -> >50 dias | AQ56: =IF(U56="","Dentro",(IF(IF(W56="",TODAY(),W56)<=U56,"Dentro","Fora"))) -> Dentro | AR56: =IF(U56="","Não risco",IF((TODAY()-U56)<=7,"Risco","Não risco")) -> Não risco | AS56: =IF(SEARCH("integrar",P56)>0,"Sim","Não") -> Sim | AT56: =IF(S56="",TODAY()-Q56,S56-Q56) -> 19 | AU56: =VLOOKUP(X56,'pontos focais'!C:D,2,0) -> DCMD Manutenção | AV56: =U56-Q56 -> -46234
A57: 943 | B57: Visita Domo de Ferro | C57: Atendimento Comercial | D57: DESC | E57: 46117 | F57: Monike Chaves | G57: Finalizada | H57: Finalizada | L57: SUL | M57: Batayporã | N57: Prefeitura | O57: Batayporã | P57: Visita realizada pelo Projeto Integrar - Registro ID 44 1- Prefeito citou que a cidade está com obras de loteamentos particulares, ainda em fase de canteiro. Acompanhar essas solicitações pela central do cliente, coletando expectativa futura de prazo com a Prefeitura. 2- Sobre a carreta "Nossa Energia" da Eficiência Energética. Prefeito demonstrou interesse, solicitei para que ela sugerisse uma data para a realização de uma ação na cidade. (26, 27 e 28 de Junho é a Festa do Sereno, maior evento da cidade). 3- Sobre a poda na cidade e o possível apoio na recolha de galhos, o Prefeito citou que Julho é o melhor mês. Pedu para evitar podar em Junho em razão da festa do sereno, e que as equipes da Prefeitura estarão todas ocupadas. 4- Citaram alguns problemas de interrupção na UC da MS Pantanal (Tratamento de água e esgoto). Talvez seja sobrecarga e necessidade de revisão da declaração. A unidade fica próxima do cemitério. Realizar diagnóstico. | Q57: 46237 | R57: FAVOR REALIZAR AS ANALISES DAS DEMANDAS DO PROJETO INTEGRAR OS QUATROS PONTOS E NOS RESPALDAR AS ATUALIZAÇÕES . | S57: 46247 | T57: GESTORA MONIKE REALIZOU TODAS AS TRATATIVAS | U57: 46248 | W57: 46247 | X57: Monike Chaves | Y57: Bruna Santos | Z57: GERMINO ROZ - PREFEITO DIAN DIEGO SOUZA | AA57: Diego Souza Silva | AB57: Sim | AC57: Visita Domo de Ferro | AD57: 46268 | AE57: Moacir Costa Neto | AF57: 46247 | AG57: Bruna Fabiana Braguin dos Santos | AH57: 100 | AI57: 100 | AJ57: 75 | AN57: =VLOOKUP(M57,[1]municipios!$B:$D,3,0) -> NOVA ANDRADINA | AO57: =TODAY()-E57 -> 171 | AP57: =IF(AO57<=5,"0–5 dias",IF(AO57<=15,"6–15 dias",IF(AO57<=16,"16–30 dias",IF(AO57<=30,"30–50 dias",">50 dias")))) -> >50 dias | AQ57: =IF(U57="","Dentro",(IF(IF(W57="",TODAY(),W57)<=U57,"Dentro","Fora"))) -> Dentro | AR57: =IF(U57="","Não risco",IF((TODAY()-U57)<=7,"Risco","Não risco")) -> Não risco | AS57: =IF(SEARCH("integrar",P57)>0,"Sim","Não") -> Sim | AT57: =IF(S57="",TODAY()-Q57,S57-Q57) -> 10 | AU57: =VLOOKUP(X57,'pontos focais'!C:D,2,0) -> DESC Agentes de Relacionamento | AV57: =U57-Q57 -> 11
A58: 944 | B58: Visita Domo de Ferro | C58: Atendimento Comercial | D58: DESC | E58: 46140 | F58: Availdo Taveira de Oliveira | G58: Finalizada | H58: Finalizada | L58: NORTE | M58: Corumbá | N58: Prefeitura | O58: Corumbá | P58: Visita realizada pelo Projeto Integrar - Registro ID 52 1- Execução de 4 obras em atraso a pedido da prefeitura de Ladario. 2- Apoio na poda de 5 Sete Copas na cidade de Ládario. 3- Solicitação de totem para atendimento na prefeitura de Ládario. | Q58: 46237 | R58: FAVOR ANALISAR AS DEMANDAS DO PROJETO INTEGRAR E NOS DAR RESPALDOS E ATUALIZAÇÕES E ENCAMINHAR SE NECESSARIO COM AÇÕES PARA OS DEPARTAMENTOS RESPONSAVEIS. | S58: 46273 | U58: 46248 | W58: 46262 | X58: Availdo Taveira de Oliveira | Y58: Aline Mesquita | Z58: HELDER BARBOSA | AA58: Helder Barbosa Diniz | AB58: Sim | AC58: Visita Domo de Ferro | AD58: 46273 | AE58: Aline da Silva Mesquita | AF58: 46273 | AG58: Aline da Silva Mesquita | AH58: 100 | AI58: 100 | AJ58: 100 | AN58: =VLOOKUP(M58,[1]municipios!$B:$D,3,0) -> CORUMBA | AO58: =TODAY()-E58 -> 148 | AP58: =IF(AO58<=5,"0–5 dias",IF(AO58<=15,"6–15 dias",IF(AO58<=16,"16–30 dias",IF(AO58<=30,"30–50 dias",">50 dias")))) -> >50 dias | AQ58: =IF(U58="","Dentro",(IF(IF(W58="",TODAY(),W58)<=U58,"Dentro","Fora"))) -> Fora | AR58: =IF(U58="","Não risco",IF((TODAY()-U58)<=7,"Risco","Não risco")) -> Não risco | AS58: =IF(SEARCH("integrar",P58)>0,"Sim","Não") -> Sim | AT58: =IF(S58="",TODAY()-Q58,S58-Q58) -> 36 | AU58: =VLOOKUP(X58,'pontos focais'!C:D,2,0) -> DESC Agentes de Relacionamento | AV58: =U58-Q58 -> 11
A59: 945 | B59: Visita Domo de Ferro | C59: Atendimento Comercial | D59: DESC | E59: 46141 | F59: Availdo Taveira de Oliveira | G59: Finalizada | H59: Devolvido | L59: NORTE | M59: Dois Irmãos do Buriti | N59: Prefeitura | O59: Dois Irmãos do Buriti | P59: Visita realizada pelo Projeto Integrar - Registro ID 50 1- Validar e responder ao prefeito como e em qual rede será conectada as GDs do Polo industrial. 2- Industria no Polo Industrial que querem migrar da Coeso para EMS - Frigorifico, Peixe, mandioca e Laranja; | Q59: 46237 | R59: FAVOR ANALISAR AS DEMANDAS DO PROJETO INTEGRAR E NOS DAR RESPALDOS E ATUALIZAÇÕES E ENCAMINHAR SE NECESSARIO COM AÇÕES PARA OS DEPARTAMENTOS RESPONSAVEIS. | S59: 46237 | T59: Segue resumo em foto anexo. As demandas estão registradas no APP. | U59: 46248 | W59: 46237 | X59: Availdo Taveira de Oliveira | Y59: Anderson Smaniotto | AA59: Anderson Brum Smaniotto | AB59: Sim | AC59: Visita Domo de Ferro | AD59: 46268 | AE59: Moacir Costa Neto | AF59: 46237 | AG59: Anderson Brum Smaniotto | AH59: 100 | AI59: 100 | AJ59: 75 | AN59: =VLOOKUP(M59,[1]municipios!$B:$D,3,0) -> AQUIDAUANA | AO59: =TODAY()-E59 -> 147 | AP59: =IF(AO59<=5,"0–5 dias",IF(AO59<=15,"6–15 dias",IF(AO59<=16,"16–30 dias",IF(AO59<=30,"30–50 dias",">50 dias")))) -> >50 dias | AQ59: =IF(U59="","Dentro",(IF(IF(W59="",TODAY(),W59)<=U59,"Dentro","Fora"))) -> Dentro | AR59: =IF(U59="","Não risco",IF((TODAY()-U59)<=7,"Risco","Não risco")) -> Não risco | AS59: =IF(SEARCH("integrar",P59)>0,"Sim","Não") -> Sim | AT59: =IF(S59="",TODAY()-Q59,S59-Q59) -> 0 | AU59: =VLOOKUP(X59,'pontos focais'!C:D,2,0) -> DESC Agentes de Relacionamento | AV59: =U59-Q59 -> 11
A60: 945 | B60: Visita Domo de Ferro | C60: Informação | D60: DESC | E60: 46141 | F60: Availdo Taveira de Oliveira | G60: Finalizada | H60: Finalizada | L60: NORTE | M60: Dois Irmãos do Buriti | N60: Prefeitura | O60: Dois Irmãos do Buriti | P60: Visita realizada pelo Projeto Integrar - Registro ID 50 1- Validar e responder ao prefeito como e em qual rede será conectada as GDs do Polo industrial. 2- Industria no Polo Industrial que querem migrar da Coeso para EMS - Frigorifico, Peixe, mandioca e Laranja; | Q60: 46245 | R60: Ação gerada e direcionada ao DESC (Availdo) para as devidas tratativas. Por favor, disponibilizar as informações a seguir para que possamos gerar as ações e direcionar aos responsáveis para as devidas tratativas. Projeto Integrar - ID 50. 1. Validar e responder ao prefeito como e em qual rede será conectada as GDs do Polo Industrial, para direcionamento gentileza informar o nº da(s) unidade(s) conssumidora(s) ou o nº do(s) projeto(s) elétrico(s). 2. Indústria no Polo Industrial que querem migrar da Coeso para a EMS - (Frigorífico, Peixe, Mandioca e Laranja), para os devidos direcionamentos informar o nº da(s) unidade(s) consumidora(s). | S60: 46247 | T60: SEM INFORMAÇÕES SUFICIENTES PARA ANALISE | W60: 46247 | X60: Availdo Taveira de Oliveira | Y60: Bruna Santos | AA60: Anderson Brum Smaniotto | AB60: Sim | AC60: Visita Domo de Ferro | AD60: 46268 | AE60: Moacir Costa Neto | AF60: 46247 | AG60: Bruna Fabiana Braguin dos Santos | AH60: 100 | AI60: 100 | AJ60: 75 | AN60: =VLOOKUP(M60,[1]municipios!$B:$D,3,0) -> AQUIDAUANA | AO60: =TODAY()-E60 -> 147 | AP60: =IF(AO60<=5,"0–5 dias",IF(AO60<=15,"6–15 dias",IF(AO60<=16,"16–30 dias",IF(AO60<=30,"30–50 dias",">50 dias")))) -> >50 dias | AQ60: =IF(U60="","Dentro",(IF(IF(W60="",TODAY(),W60)<=U60,"Dentro","Fora"))) -> Dentro | AR60: =IF(U60="","Não risco",IF((TODAY()-U60)<=7,"Risco","Não risco")) -> Não risco | AS60: =IF(SEARCH("integrar",P60)>0,"Sim","Não") -> Sim | AT60: =IF(S60="",TODAY()-Q60,S60-Q60) -> 2 | AU60: =VLOOKUP(X60,'pontos focais'!C:D,2,0) -> DESC Agentes de Relacionamento | AV60: =U60-Q60 -> -46245
A61: 946 | B61: Visita Domo de Ferro | C61: Atendimento Comercial | D61: DESC | E61: 46182 | F61: Availdo Taveira de Oliveira | G61: Finalizada | H61: Finalizada | L61: CENTRO | M61: Paranaíba | N61: Prefeitura | O61: Paranaíba | P61: Visita realizada pelo Projeto Integrar - Registro ID 87 1- Questionou que quando de uma obra estão trocando os postes e levando os braços da luminária. 2- Solicitou para ver a possibilidade de ligar os padrões que foram desmembrados das lojas anexa ao terminal rodoviário, foi orientado a solicitar uma OS de padronização. | Q61: 46237 | R61: FAVOR ANALISAR AS DEMANDAS DO PROJETO INTEGRAR E NOS DAR RESPALDOS E ATUALIZAÇÕES E ENCAMINHAR SE NECESSARIO COM AÇÕES PARA OS DEPARTAMENTOS RESPONSAVEIS. | S61: 46253 | U61: 46248 | W61: 46253 | X61: Availdo Taveira de Oliveira | Y61: Bruna Santos | AB61: Sim | AC61: Visita Domo de Ferro | AD61: 46268 | AE61: Moacir Costa Neto | AF61: 46253 | AG61: Bruna Fabiana Braguin dos Santos | AH61: 100 | AI61: 100 | AJ61: 100 | AN61: =VLOOKUP(M61,[1]municipios!$B:$D,3,0) -> PARANAIBA | AO61: =TODAY()-E61 -> 106 | AP61: =IF(AO61<=5,"0–5 dias",IF(AO61<=15,"6–15 dias",IF(AO61<=16,"16–30 dias",IF(AO61<=30,"30–50 dias",">50 dias")))) -> >50 dias | AQ61: =IF(U61="","Dentro",(IF(IF(W61="",TODAY(),W61)<=U61,"Dentro","Fora"))) -> Fora | AR61: =IF(U61="","Não risco",IF((TODAY()-U61)<=7,"Risco","Não risco")) -> Não risco | AS61: =IF(SEARCH("integrar",P61)>0,"Sim","Não") -> Sim | AT61: =IF(S61="",TODAY()-Q61,S61-Q61) -> 16 | AU61: =VLOOKUP(X61,'pontos focais'!C:D,2,0) -> DESC Agentes de Relacionamento | AV61: =U61-Q61 -> 11
A62: 947 | B62: Visita Domo de Ferro | C62: Atendimento Comercial | D62: DESC | E62: 46126 | F62: Monike Chaves | G62: Finalizada | H62: Finalizada | M62: Dourados | N62: Prefeitura | P62: Visita realizada pelo Projeto Integrar - Registro ID 45 1- Prefeito citou que estão com projetos em andamento de loteamentos sociais pela cidade, e que provavelmente irá solicitar uma carta de viabilidade em breve. Um com 72 lotes e outro com 20 lotes. Inserir para acompanhamento na central do cliente. 2- Prefeito citou região da AGROFAP, que o local estava com faltas de energia constantes, porém já foi resolvido após a retirada de um trecho de bambus pela Energisa. Informou sobre o Ass. Bela Manhã, que está com faltas constantes de energia. Inspecionar. 3- "Realocação de rede na entrada da cidade para a construção de um portal na entrada da cidade. Ação interna: Inserir essa obra na Central do Cliente. 0302600023 - Liberada em 27/02/2026" | Q62: 46237 | R62: FAVOR ANALISAR AS DEMANDAS DO PROJETO INTEGRAR E NOS DAR RESPALDOS E ATUALIZAÇÕES E ENCAMINHAR SE NECESSARIO COM AÇÕES PARA OS DEPARTAMENTOS RESPONSAVEIS. | S62: 46247 | T62: EM CONTATO COM A GESTORA MONIKE TODAS AS DEMANDAS FORAM TRATADAS | U62: 46248 | W62: 46247 | X62: Availdo Taveira de Oliveira | Y62: Bruna Santos | AA62: Diego Souza Silva | AB62: Sim | AC62: Visita Domo de Ferro | AD62: 46268 | AE62: Moacir Costa Neto | AF62: 46247 | AG62: Bruna Fabiana Braguin dos Santos | AH62: 100 | AI62: 100 | AJ62: 75 | AN62: =VLOOKUP(M62,[1]municipios!$B:$D,3,0) -> DOURADOS | AO62: =TODAY()-E62 -> 162 | AP62: =IF(AO62<=5,"0–5 dias",IF(AO62<=15,"6–15 dias",IF(AO62<=16,"16–30 dias",IF(AO62<=30,"30–50 dias",">50 dias")))) -> >50 dias | AQ62: =IF(U62="","Dentro",(IF(IF(W62="",TODAY(),W62)<=U62,"Dentro","Fora"))) -> Dentro | AR62: =IF(U62="","Não risco",IF((TODAY()-U62)<=7,"Risco","Não risco")) -> Não risco | AS62: =IF(SEARCH("integrar",P62)>0,"Sim","Não") -> Sim | AT62: =IF(S62="",TODAY()-Q62,S62-Q62) -> 10 | AU62: =VLOOKUP(X62,'pontos focais'!C:D,2,0) -> DESC Agentes de Relacionamento | AV62: =U62-Q62 -> 11
A63: 948 | B63: Visita Domo de Ferro | C63: Atendimento Comercial | D63: DESC | E63: 46136 | F63: Availdo Taveira de Oliveira | G63: Finalizada | H63: Finalizada | L63: CENTRO | M63: Terenos | N63: Prefeitura | O63: Terenos | P63: Visita realizada pelo Projeto Integrar - Registro ID 73 Individualizar a medição da praça de eventos . Central do Cliente (12/08/2026): Projeto Integrar. Informação, não foram anexados documentos e/ou informado nº de unidade consumidora, OS ou demais dados do(s) cliente(s) para abertura de ações. | Q63: 46237 | R63: FAVOR ANALISAR AS DEMANDAS DO PROJETO INTEGRAR E NOS DAR RESPALDOS E ATUALIZAÇÕES E ENCAMINHAR SE NECESSARIO COM AÇÕES PARA OS DEPARTAMENTOS RESPONSAVEIS. | S63: 46246 | T63: Projeto Integrar. Informação, não foram anexados documentos e/ou informado nº de unidade consumidora, OS ou demais dados do(s) cliente(s) para abertura de ações. | U63: 46248 | W63: 46246 | X63: Availdo Taveira de Oliveira | Y63: Wander Machado | AA63: Fabricio Cerchiari da Silva | AB63: Sim | AC63: Visita Domo de Ferro | AD63: 46268 | AE63: Moacir Costa Neto | AF63: 46246 | AG63: Wander Idalino Machado | AH63: 100 | AI63: 100 | AJ63: 75 | AN63: =VLOOKUP(M63,[1]municipios!$B:$D,3,0) -> CAMPO GRANDE INTERIOR | AO63: =TODAY()-E63 -> 152 | AP63: =IF(AO63<=5,"0–5 dias",IF(AO63<=15,"6–15 dias",IF(AO63<=16,"16–30 dias",IF(AO63<=30,"30–50 dias",">50 dias")))) -> >50 dias | AQ63: =IF(U63="","Dentro",(IF(IF(W63="",TODAY(),W63)<=U63,"Dentro","Fora"))) -> Dentro | AR63: =IF(U63="","Não risco",IF((TODAY()-U63)<=7,"Risco","Não risco")) -> Não risco | AS63: =IF(SEARCH("integrar",P63)>0,"Sim","Não") -> Sim | AT63: =IF(S63="",TODAY()-Q63,S63-Q63) -> 9 | AU63: =VLOOKUP(X63,'pontos focais'!C:D,2,0) -> DESC Agentes de Relacionamento | AV63: =U63-Q63 -> 11
A64: 960 | B64: Visita Domo de Ferro | C64: Informação | D64: Central do Cliente | E64: 46238 | F64: Giovani Moura Sousa | G64: Finalizada | H64: Finalizada | L64: CENTRO | M64: Campo Grande | N64: Câmara | O64: Campo Grande | P64: Solicitado manutenção do veto à emenda do Vereador Roilço sobre fios de internet. Informação. | Q64: 46239 | R64: Informação. Solicitado manutenção do veto à emenda do Vereador Roilço sobre fios de internet. | S64: 46245 | U64: 46239 | W64: 46239 | X64: Wander Idalino Machado | Y64: Wander Machado | Z64: Vereador Rrafael Tavares | AA64: Giovani Moura Sousa | AB64: Sim | AC64: Visita Domo de Ferro | AD64: 46268 | AE64: Moacir Costa Neto | AF64: 46245 | AG64: Wander Idalino Machado | AH64: 25 | AI64: 25 | AJ64: 25 | AN64: =VLOOKUP(M64,[1]municipios!$B:$D,3,0) -> CAMPO GRANDE | AO64: =TODAY()-E64 -> 50 | AP64: =IF(AO64<=5,"0–5 dias",IF(AO64<=15,"6–15 dias",IF(AO64<=16,"16–30 dias",IF(AO64<=30,"30–50 dias",">50 dias")))) -> >50 dias | AQ64: =IF(U64="","Dentro",(IF(IF(W64="",TODAY(),W64)<=U64,"Dentro","Fora"))) -> Dentro | AR64: =IF(U64="","Não risco",IF((TODAY()-U64)<=7,"Risco","Não risco")) -> Não risco | AS64: =IF(SEARCH("integrar",P64)>0,"Sim","Não") -> #VALUE! | AT64: =IF(S64="",TODAY()-Q64,S64-Q64) -> 6 | AU64: =VLOOKUP(X64,'pontos focais'!C:D,2,0) -> Central do Cliente | AV64: =U64-Q64 -> 0
A65: 961 | B65: Visita Domo de Ferro | C65: Informação | D65: Central do Cliente | E65: 46238 | F65: Giovani Moura Sousa | G65: Finalizada | H65: Finalizada | L65: CENTRO | M65: Campo Grande | N65: Câmara | O65: Campo Grande | P65: Solicitado a manutenção do veto à emenda do Vereador Ronilço quanto aos fios de internet. Informação. | Q65: 46239 | R65: Informação. Solicitado a manutenção do veto à emenda do Vereador Ronilço quanto aos fios de internet. | S65: 46239 | T65: Solicitado a manutenção do veto à emenda do Vereador Ronilço quanto aos fios de internet. | W65: 46239 | X65: Wander Idalino Machado | Y65: Wander Machado | Z65: Vereador André salineiro | AB65: Sim | AC65: Visita Domo de Ferro | AD65: 46268 | AE65: Moacir Costa Neto | AF65: 46239 | AG65: Wander Idalino Machado | AH65: 25 | AI65: 25 | AJ65: 25 | AN65: =VLOOKUP(M65,[1]municipios!$B:$D,3,0) -> CAMPO GRANDE | AO65: =TODAY()-E65 -> 50 | AP65: =IF(AO65<=5,"0–5 dias",IF(AO65<=15,"6–15 dias",IF(AO65<=16,"16–30 dias",IF(AO65<=30,"30–50 dias",">50 dias")))) -> >50 dias | AQ65: =IF(U65="","Dentro",(IF(IF(W65="",TODAY(),W65)<=U65,"Dentro","Fora"))) -> Dentro | AR65: =IF(U65="","Não risco",IF((TODAY()-U65)<=7,"Risco","Não risco")) -> Não risco | AS65: =IF(SEARCH("integrar",P65)>0,"Sim","Não") -> #VALUE! | AT65: =IF(S65="",TODAY()-Q65,S65-Q65) -> 0 | AU65: =VLOOKUP(X65,'pontos focais'!C:D,2,0) -> Central do Cliente | AV65: =U65-Q65 -> -46239
A66: 962 | B66: Visita Domo de Ferro | C66: Informação | D66: Central do Cliente | E66: 46238 | F66: Giovani Moura Sousa | G66: Finalizada | H66: Finalizada | L66: CENTRO | M66: Campo Grande | N66: Câmara | O66: Campo Grande | P66: Slicitado a manutenção do veto contra a emenda do Vereador Ronilço quanto aos fios de internet. Informação. | Q66: 46239 | R66: Informação. Solicitado a manutenção do veto contra a emenda do Vereador Ronilço quanto aos fios de internet. | S66: 46245 | U66: 46239 | W66: 46239 | X66: Wander Idalino Machado | Y66: Wander Machado | Z66: Vreador Juari | AA66: Giovani Moura Sousa | AB66: Sim | AC66: Visita Domo de Ferro | AD66: 46268 | AE66: Moacir Costa Neto | AF66: 46245 | AG66: Wander Idalino Machado | AH66: 25 | AI66: 25 | AJ66: 25 | AN66: =VLOOKUP(M66,[1]municipios!$B:$D,3,0) -> CAMPO GRANDE | AO66: =TODAY()-E66 -> 50 | AP66: =IF(AO66<=5,"0–5 dias",IF(AO66<=15,"6–15 dias",IF(AO66<=16,"16–30 dias",IF(AO66<=30,"30–50 dias",">50 dias")))) -> >50 dias | AQ66: =IF(U66="","Dentro",(IF(IF(W66="",TODAY(),W66)<=U66,"Dentro","Fora"))) -> Dentro | AR66: =IF(U66="","Não risco",IF((TODAY()-U66)<=7,"Risco","Não risco")) -> Não risco | AS66: =IF(SEARCH("integrar",P66)>0,"Sim","Não") -> #VALUE! | AT66: =IF(S66="",TODAY()-Q66,S66-Q66) -> 6 | AU66: =VLOOKUP(X66,'pontos focais'!C:D,2,0) -> Central do Cliente | AV66: =U66-Q66 -> 0
A67: 962 | B67: Visita Domo de Ferro | C67: Informação | D67: Vazio | E67: 46238 | F67: Giovani Moura Sousa | G67: Finalizada | H67: Finalizada | L67: CENTRO | M67: Campo Grande | N67: Câmara | O67: Campo Grande | P67: Slicitado a manutenção do veto contra a emenda do Vereador Ronilço quanto aos fios de internet. Informação. | Q67: 46239 | R67: Informação. Solicitado a manutenção do veto contra a emenda do Vereador Ronilço quanto aos fios de internet. | S67: 46245 | U67: 46239 | W67: 46239 | X67: Wander Idalino Machado | Y67: Wander Machado | Z67: Vreador Juari | AA67: Giovani Moura Sousa | AB67: Sim | AC67: Visita Domo de Ferro | AD67: 46268 | AE67: Moacir Costa Neto | AF67: 46245 | AG67: Wander Idalino Machado | AH67: 25 | AI67: 25 | AJ67: 25 | AN67: =VLOOKUP(M67,[1]municipios!$B:$D,3,0) -> CAMPO GRANDE | AO67: =TODAY()-E67 -> 50 | AP67: =IF(AO67<=5,"0–5 dias",IF(AO67<=15,"6–15 dias",IF(AO67<=16,"16–30 dias",IF(AO67<=30,"30–50 dias",">50 dias")))) -> >50 dias | AQ67: =IF(U67="","Dentro",(IF(IF(W67="",TODAY(),W67)<=U67,"Dentro","Fora"))) -> Dentro | AR67: =IF(U67="","Não risco",IF((TODAY()-U67)<=7,"Risco","Não risco")) -> Não risco | AS67: =IF(SEARCH("integrar",P67)>0,"Sim","Não") -> #VALUE! | AT67: =IF(S67="",TODAY()-Q67,S67-Q67) -> 6 | AU67: =VLOOKUP(X67,'pontos focais'!C:D,2,0) -> Central do Cliente | AV67: =U67-Q67 -> 0
A68: 962 | B68: Visita Domo de Ferro | C68: Vazio | D68: Vazio | E68: 46238 | F68: Giovani Moura Sousa | G68: Finalizada | H68: Finalizada | L68: CENTRO | M68: Campo Grande | N68: Câmara | O68: Campo Grande | P68: Slicitado a manutenção do veto contra a emenda do Vereador Ronilço quanto aos fios de internet. Informação. | Q68: 46239 | R68: Informação. Solicitado a manutenção do veto contra a emenda do Vereador Ronilço quanto aos fios de internet. | S68: 46245 | T68: Informação. Solicitado a manutenção do veto contra a emenda do Vereador Ronilço quanto aos fios de internet. | X68: Wander Idalino Machado | Y68: Wander Machado | Z68: Vreador Juari | AA68: Giovani Moura Sousa | AB68: Sim | AC68: Visita Domo de Ferro | AD68: 46268 | AE68: Moacir Costa Neto | AF68: 46245 | AG68: Wander Idalino Machado | AH68: 25 | AI68: 25 | AJ68: 25 | AN68: =VLOOKUP(M68,[1]municipios!$B:$D,3,0) -> CAMPO GRANDE | AO68: =TODAY()-E68 -> 50 | AP68: =IF(AO68<=5,"0–5 dias",IF(AO68<=15,"6–15 dias",IF(AO68<=16,"16–30 dias",IF(AO68<=30,"30–50 dias",">50 dias")))) -> >50 dias | AQ68: =IF(U68="","Dentro",(IF(IF(W68="",TODAY(),W68)<=U68,"Dentro","Fora"))) -> Dentro | AR68: =IF(U68="","Não risco",IF((TODAY()-U68)<=7,"Risco","Não risco")) -> Não risco | AS68: =IF(SEARCH("integrar",P68)>0,"Sim","Não") -> #VALUE! | AT68: =IF(S68="",TODAY()-Q68,S68-Q68) -> 6 | AU68: =VLOOKUP(X68,'pontos focais'!C:D,2,0) -> Central do Cliente | AV68: =U68-Q68 -> -46239
A69: 963 | B69: Visita Domo de Ferro | C69: Informação | D69: Central do Cliente | E69: 46238 | F69: Giovani Moura Sousa | G69: Finalizada | H69: Finalizada | L69: CENTRO | M69: Campo Grande | N69: Câmara | O69: Campo Grande | P69: Solicitada a manutenção do veto contra emenda do Vereador Ronilço quanto aos fios de internet. Informação. | Q69: 46239 | R69: Informação. Solicitada a manutenção do veto contra emenda do Vereador Ronilço quanto aos fios de internet. | S69: 46239 | W69: 46239 | X69: Wander Idalino Machado | Y69: Wander Machado | Z69: Vereador Otávio Trad | AA69: Giovani Moura Sousa | AB69: Sim | AC69: Visita Domo de Ferro | AD69: 46268 | AE69: Moacir Costa Neto | AF69: 46239 | AG69: Wander Idalino Machado | AH69: 25 | AI69: 25 | AJ69: 25 | AN69: =VLOOKUP(M69,[1]municipios!$B:$D,3,0) -> CAMPO GRANDE | AO69: =TODAY()-E69 -> 50 | AP69: =IF(AO69<=5,"0–5 dias",IF(AO69<=15,"6–15 dias",IF(AO69<=16,"16–30 dias",IF(AO69<=30,"30–50 dias",">50 dias")))) -> >50 dias | AQ69: =IF(U69="","Dentro",(IF(IF(W69="",TODAY(),W69)<=U69,"Dentro","Fora"))) -> Dentro | AR69: =IF(U69="","Não risco",IF((TODAY()-U69)<=7,"Risco","Não risco")) -> Não risco | AS69: =IF(SEARCH("integrar",P69)>0,"Sim","Não") -> #VALUE! | AT69: =IF(S69="",TODAY()-Q69,S69-Q69) -> 0 | AU69: =VLOOKUP(X69,'pontos focais'!C:D,2,0) -> Central do Cliente | AV69: =U69-Q69 -> -46239
A70: 964 | B70: Visita Domo de Ferro | C70: Informação | D70: Central do Cliente | E70: 46238 | F70: Giovani Moura Sousa | G70: Finalizada | H70: Finalizada | L70: CENTRO | M70: Campo Grande | N70: Câmara | O70: Campo Grande | P70: Solicitado manutenção do vento contra a emenda do Vereador Ronilço quanto aos fios de internet. Informação. | Q70: 46239 | R70: Informação. Solicitado manutenção do vento contra a emenda do Vereador Ronilço quanto aos fios de internet | S70: 46265 | U70: 46295 | W70: 46239 | X70: Wander Idalino Machado | Y70: Rafaela Almeida | Z70: Vereador Wilson Lands | AA70: Giovani Moura Sousa | AB70: Sim | AC70: Visita Domo de Ferro | AD70: 46268 | AE70: Moacir Costa Neto | AF70: 46265 | AG70: Rafaela Mattos de Almeida | AH70: 25 | AI70: 25 | AJ70: 25 | AN70: =VLOOKUP(M70,[1]municipios!$B:$D,3,0) -> CAMPO GRANDE | AO70: =TODAY()-E70 -> 50 | AP70: =IF(AO70<=5,"0–5 dias",IF(AO70<=15,"6–15 dias",IF(AO70<=16,"16–30 dias",IF(AO70<=30,"30–50 dias",">50 dias")))) -> >50 dias | AQ70: =IF(U70="","Dentro",(IF(IF(W70="",TODAY(),W70)<=U70,"Dentro","Fora"))) -> Dentro | AR70: =IF(U70="","Não risco",IF((TODAY()-U70)<=7,"Risco","Não risco")) -> Risco | AS70: =IF(SEARCH("integrar",P70)>0,"Sim","Não") -> #VALUE! | AT70: =IF(S70="",TODAY()-Q70,S70-Q70) -> 26 | AU70: =VLOOKUP(X70,'pontos focais'!C:D,2,0) -> Central do Cliente | AV70: =U70-Q70 -> 56
A71: 965 | B71: Visita Domo de Ferro | C71: Informação | D71: Central do Cliente | E71: 46238 | F71: Giovani Moura Sousa | G71: Finalizada | H71: Finalizada | L71: CENTRO | M71: Campo Grande | N71: Câmara | O71: Campo Grande | P71: Solicitada a manutenção do vet contra emenda do Vereador Ronilço quanto aos fios de internet. Informação. | Q71: 46239 | R71: Informação. Solicitada a manutenção do veto contra emenda do Vereador Ronilço quanto aos fios de internet. | S71: 46239 | W71: 46239 | X71: Wander Idalino Machado | Y71: Wander Machado | Z71: Vereador Papy | AA71: Giovani Moura Sousa | AB71: Sim | AC71: Visita Domo de Ferro | AD71: 46268 | AE71: Moacir Costa Neto | AF71: 46239 | AG71: Wander Idalino Machado | AH71: 25 | AI71: 25 | AJ71: 25 | AN71: =VLOOKUP(M71,[1]municipios!$B:$D,3,0) -> CAMPO GRANDE | AO71: =TODAY()-E71 -> 50 | AP71: =IF(AO71<=5,"0–5 dias",IF(AO71<=15,"6–15 dias",IF(AO71<=16,"16–30 dias",IF(AO71<=30,"30–50 dias",">50 dias")))) -> >50 dias | AQ71: =IF(U71="","Dentro",(IF(IF(W71="",TODAY(),W71)<=U71,"Dentro","Fora"))) -> Dentro | AR71: =IF(U71="","Não risco",IF((TODAY()-U71)<=7,"Risco","Não risco")) -> Não risco | AS71: =IF(SEARCH("integrar",P71)>0,"Sim","Não") -> #VALUE! | AT71: =IF(S71="",TODAY()-Q71,S71-Q71) -> 0 | AU71: =VLOOKUP(X71,'pontos focais'!C:D,2,0) -> Central do Cliente | AV71: =U71-Q71 -> -46239
A72: 980 | B72: Visita Domo de Ferro | C72: Obra | D72: DCMD | E72: 46241 | F72: Dian Cleiton de Brito | G72: Em Andamento | H72: Em Andamento | K72: 0102601310 | L72: CENTRO | M72: Sidrolândia | N72: Assembleia Legislativa | O72: Sidrolândia | P72: Solicita agilizar execução do Ponto de entrega Expec 21/08/26 | Q72: 46245 | R72: Solicita agilizar execução do Ponto de entrega Expectativa do cliente 21/08/26 | S72: 46280 | T72: Reprogramada para 27/09 - devido a contingência | U72: 46255 | V72: 46292 | X72: Amanda Aparecida Teixeira dos Santos | Y72: Amanda Santos | Z72: Gerson Claro Paulo Roberto William Maksoud | AA72: Dian Cleiton de Brito | AB72: Sim | AC72: Visita Domo de Ferro | AD72: 46280 | AE72: Amanda Aparecida Teixeira dos Santos | AF72: 46280 | AG72: Amanda Aparecida Teixeira dos Santos | AH72: 100 | AI72: 100 | AJ72: 100 | AN72: =VLOOKUP(M72,[1]municipios!$B:$D,3,0) -> CAMPO GRANDE INTERIOR | AO72: =TODAY()-E72 -> 47 | AP72: =IF(AO72<=5,"0–5 dias",IF(AO72<=15,"6–15 dias",IF(AO72<=16,"16–30 dias",IF(AO72<=30,"30–50 dias",">50 dias")))) -> >50 dias | AQ72: =IF(U72="","Dentro",(IF(IF(W72="",TODAY(),W72)<=U72,"Dentro","Fora"))) -> Fora | AR72: =IF(U72="","Não risco",IF((TODAY()-U72)<=7,"Risco","Não risco")) -> Não risco | AS72: =IF(SEARCH("integrar",P72)>0,"Sim","Não") -> #VALUE! | AT72: =IF(S72="",TODAY()-Q72,S72-Q72) -> 35 | AU72: =VLOOKUP(X72,'pontos focais'!C:D,2,0) -> DCMD Programação de Obra | AV72: =U72-Q72 -> 10
A73: 986 | B73: Visita Domo de Ferro | C73: Obra | D73: DCMD | E73: 46244 | F73: Dian Cleiton de Brito | G73: Finalizada | H73: Finalizada | K73: 0302600292 | L73: SUL | M73: Bataguassu | N73: Assembleia Legislativa | O73: Bataguassu | P73: Ligação nova do Poço no Assentamento Sta Paula. 25/08/26. | Q73: 46245 | R73: Ligação nova do Poço no Assentamento Sta Paula. Expectativa do cliente: 25/08/26. Solicita agilização no atendimento da Obra 0302600292. | S73: 46267 | T73: Obra 0302600292 concluída. | U73: 46259 | V73: 46275 | W73: 46267 | X73: Amanda Aparecida Teixeira dos Santos | Y73: Wander Machado | Z73: DEPUTADO CARAVINA | AA73: Dian Cleiton de Brito | AB73: Sim | AC73: Visita Domo de Ferro | AD73: 46268 | AE73: Moacir Costa Neto | AF73: 46267 | AG73: Wander Idalino Machado | AH73: 100 | AI73: 100 | AJ73: 100 | AN73: =VLOOKUP(M73,[1]municipios!$B:$D,3,0) -> NOVA ANDRADINA | AO73: =TODAY()-E73 -> 44 | AP73: =IF(AO73<=5,"0–5 dias",IF(AO73<=15,"6–15 dias",IF(AO73<=16,"16–30 dias",IF(AO73<=30,"30–50 dias",">50 dias")))) -> >50 dias | AQ73: =IF(U73="","Dentro",(IF(IF(W73="",TODAY(),W73)<=U73,"Dentro","Fora"))) -> Fora | AR73: =IF(U73="","Não risco",IF((TODAY()-U73)<=7,"Risco","Não risco")) -> Não risco | AS73: =IF(SEARCH("integrar",P73)>0,"Sim","Não") -> #VALUE! | AT73: =IF(S73="",TODAY()-Q73,S73-Q73) -> 22 | AU73: DESC Agentes de Relacionamento | AV73: =U73-Q73 -> 14
A74: 986 | B74: Visita Domo de Ferro | C74: Ordem de Serviço | D74: DEOP | E74: 46244 | F74: Dian Cleiton de Brito | G74: Finalizada | H74: Finalizada | L74: SUL | M74: Bataguassu | N74: Assembleia Legislativa | O74: Bataguassu | P74: Ligação nova do Poço no Assentamento Sta Paula. 25/08/26. | Q74: 46267 | R74: Por favor, agilizar atendimentos das ordens de serviço 561015595 (Vistoria) e 561015594 (Ligação Nova). Ligação nova do poço no assentamento Santa Paula. | S74: 46276 | T74: Vistoria/Ligação executadas em 02/09/2026, dando origem a unidade consumidora 3893362. | W74: 46276 | X74: Matheus Carneiro de Oliveira | Y74: Wander Machado | Z74: DEPUTADO CARAVINA | AA74: Dian Cleiton de Brito | AB74: Sim | AC74: Visita Domo de Ferro | AD74: 46276 | AE74: Wander Idalino Machado | AF74: 46276 | AG74: Wander Idalino Machado | AH74: 100 | AI74: 100 | AJ74: 100 | AN74: =VLOOKUP(M74,[1]municipios!$B:$D,3,0) -> NOVA ANDRADINA | AO74: =TODAY()-E74 -> 44 | AP74: =IF(AO74<=5,"0–5 dias",IF(AO74<=15,"6–15 dias",IF(AO74<=16,"16–30 dias",IF(AO74<=30,"30–50 dias",">50 dias")))) -> >50 dias | AQ74: =IF(U74="","Dentro",(IF(IF(W74="",TODAY(),W74)<=U74,"Dentro","Fora"))) -> Dentro | AR74: =IF(U74="","Não risco",IF((TODAY()-U74)<=7,"Risco","Não risco")) -> Não risco | AS74: =IF(SEARCH("integrar",P74)>0,"Sim","Não") -> #VALUE! | AT74: =IF(S74="",TODAY()-Q74,S74-Q74) -> 9 | AU74: =VLOOKUP(X74,'pontos focais'!C:D,2,0) -> DEOP COI | AV74: =U74-Q74 -> -46267
A75: 1063 | B75: Visita Domo de Ferro | C75: Atendimento Comercial | D75: DESC | E75: 46258 | F75: Aline da Silva Mesquita | G75: Finalizada | H75: Devolvido | K75: 0702600108 | L75: NORTE | M75: Coxim | N75: Prefeitura | O75: Coxim | P75: Ventura obra do Centro de Convenções 070-26-00108 Porem segue algumas observações; a Obra ainda não esta em execução mesmo ter saído sem custo, provavelmente o que esta pendente é o contrato de demanda com os grandes clientes. o posto de transformação também esta pendente a solicitação de comissionamento. | Q75: 46258 | R75: Verificar com o cliente a aprovação do orçamento, para liberação da programação da obra. | S75: 46275 | V75: 46261 | X75: Marcelly Arce Avalo Franca | Y75: Rafaela Almeida | AA75: Availdo Taveira de Oliveira | AB75: Não | AC75: Prefeitura | AD75: 46275 | AE75: Rafaela Mattos de Almeida | AF75: 46275 | AG75: Rafaela Mattos de Almeida | AH75: 100 | AI75: 100 | AJ75: 100 | AN75: =VLOOKUP(M75,[1]municipios!$B:$D,3,0) -> COXIM | AO75: =TODAY()-E75 -> 30 | AP75: =IF(AO75<=5,"0–5 dias",IF(AO75<=15,"6–15 dias",IF(AO75<=16,"16–30 dias",IF(AO75<=30,"30–50 dias",">50 dias")))) -> 30–50 dias | AQ75: =IF(U75="","Dentro",(IF(IF(W75="",TODAY(),W75)<=U75,"Dentro","Fora"))) -> Dentro | AR75: =IF(U75="","Não risco",IF((TODAY()-U75)<=7,"Risco","Não risco")) -> Não risco | AS75: =IF(SEARCH("integrar",P75)>0,"Sim","Não") -> #VALUE! | AT75: =IF(S75="",TODAY()-Q75,S75-Q75) -> 17 | AU75: =VLOOKUP(X75,'pontos focais'!C:D,2,0) -> DESC Agentes de Relacionamento | AV75: =U75-Q75 -> -46258
A76: 1063 | B76: Visita Domo de Ferro | C76: Vazio | D76: DESC | E76: 46258 | F76: Aline da Silva Mesquita | G76: Finalizada | H76: Em Andamento | K76: 0702600108 | L76: NORTE | M76: Coxim | N76: Prefeitura | O76: Coxim | P76: Ventura obra do Centro de Convenções 070-26-00108 Porem segue algumas observações; a Obra ainda não esta em execução mesmo ter saído sem custo, provavelmente o que esta pendente é o contrato de demanda com os grandes clientes. o posto de transformação também esta pendente a solicitação de comissionamento. | Q76: 46258 | R76: Verificar com o cliente a aprovação do orçamento, para liberação da programação da obra. | S76: 46262 | T76: Em tratativa com o cliente o mesmo foi informado que é necessário enviar formulário preenchido. Aguardando o mesmo enviar o formulário. | V76: 46261 | X76: Marcelly Arce Avalo Franca | Y76: Rafaela Almeida | AA76: Availdo Taveira de Oliveira | AB76: Não | AC76: Visita Domo de Ferro | AD76: 46262 | AE76: Rafaela Mattos de Almeida | AF76: 46262 | AG76: Rafaela Mattos de Almeida | AH76: 100 | AI76: 100 | AJ76: 100 | AN76: =VLOOKUP(M76,[1]municipios!$B:$D,3,0) -> COXIM | AO76: =TODAY()-E76 -> 30 | AP76: =IF(AO76<=5,"0–5 dias",IF(AO76<=15,"6–15 dias",IF(AO76<=16,"16–30 dias",IF(AO76<=30,"30–50 dias",">50 dias")))) -> 30–50 dias | AQ76: =IF(U76="","Dentro",(IF(IF(W76="",TODAY(),W76)<=U76,"Dentro","Fora"))) -> Dentro | AR76: =IF(U76="","Não risco",IF((TODAY()-U76)<=7,"Risco","Não risco")) -> Não risco | AS76: =IF(SEARCH("integrar",P76)>0,"Sim","Não") -> #VALUE! | AT76: =IF(S76="",TODAY()-Q76,S76-Q76) -> 4 | AU76: =VLOOKUP(X76,'pontos focais'!C:D,2,0) -> DESC Agentes de Relacionamento | AV76: =U76-Q76 -> -46258
A77: 1068 | B77: Visita Domo de Ferro | C77: Obra | D77: DCMD | E77: 46255 | F77: Availdo Taveira de Oliveira | G77: Finalizada | H77: Finalizada | K77: 0702600176 | L77: NORTE | M77: Coxim | N77: Prefeitura | O77: Coxim | P77: Prefeito solicita agilidade na execução da obra de relocação da rede. Respondido no ID 1064 duplicado. Finalizando CARD atual. | Q77: 46259 | R77: Obra 0702600176 - Programação de obra (agilidade na execução). | S77: 46269 | T77: RESPONDIDO NO ID 1064 | U77: 46280 | X77: Amanda Aparecida Teixeira dos Santos | Y77: Amanda Santos | AB77: Não | AC77: Visita Domo de Ferro | AD77: 46269 | AE77: Amanda Aparecida Teixeira dos Santos | AF77: 46269 | AG77: Amanda Aparecida Teixeira dos Santos | AH77: 100 | AI77: 100 | AJ77: 100 | AN77: =VLOOKUP(M77,[1]municipios!$B:$D,3,0) -> COXIM | AO77: =TODAY()-E77 -> 33 | AP77: =IF(AO77<=5,"0–5 dias",IF(AO77<=15,"6–15 dias",IF(AO77<=16,"16–30 dias",IF(AO77<=30,"30–50 dias",">50 dias")))) -> >50 dias | AQ77: =IF(U77="","Dentro",(IF(IF(W77="",TODAY(),W77)<=U77,"Dentro","Fora"))) -> Fora | AR77: =IF(U77="","Não risco",IF((TODAY()-U77)<=7,"Risco","Não risco")) -> Não risco | AS77: =IF(SEARCH("integrar",P77)>0,"Sim","Não") -> #VALUE! | AT77: =IF(S77="",TODAY()-Q77,S77-Q77) -> 10 | AU77: =VLOOKUP(X77,'pontos focais'!C:D,2,0) -> DCMD Programação de Obra | AV77: =U77-Q77 -> 21
A78: 147 | B78: Visita Domo de Ferro | C78: Poda | D78: DCMD | E78: 46154 | F78: Giovani Moura Sousa | G78: Finalizada | H78: Finalizada | L78: CENTRO | M78: Sidrolândia | N78: Assembleia Legislativa | O78: Sidrolândia | P78: NÃO CONSTA INFORMAÇÕES BÁSICAS PARA SEGUIR COM A TRATATIVA. | Q78: 46154 | R78: Gentileza verificar como esta a questão de programação de poda no município de Sidrolândia. | S78: 46247 | X78: Evair Rogerio da Conceicao | Y78: Gabriella Domingo | Z78: Deputado Renato Câmara Giovani Energisa | AA78: Giovani Moura Sousa | AB78: Não | AC78: Visita Domo de Ferro | AD78: 46268 | AE78: Moacir Costa Neto | AF78: 46247 | AG78: Gabriella Amorim Domingo | AH78: 100 | AI78: 100 | AJ78: 100 | AN78: =VLOOKUP(M78,[1]municipios!$B:$D,3,0) -> CAMPO GRANDE INTERIOR | AO78: =TODAY()-E78 -> 134 | AP78: =IF(AO78<=5,"0–5 dias",IF(AO78<=15,"6–15 dias",IF(AO78<=16,"16–30 dias",IF(AO78<=30,"30–50 dias",">50 dias")))) -> >50 dias | AQ78: =IF(U78="","Dentro",(IF(IF(W78="",TODAY(),W78)<=U78,"Dentro","Fora"))) -> Dentro | AR78: =IF(U78="","Não risco",IF((TODAY()-U78)<=7,"Risco","Não risco")) -> Não risco | AS78: =IF(SEARCH("integrar",P78)>0,"Sim","Não") -> #VALUE! | AT78: =IF(S78="",TODAY()-Q78,S78-Q78) -> 93 | AU78: =VLOOKUP(X78,'pontos focais'!C:D,2,0) -> DCMD Manutenção | AV78: =U78-Q78 -> -46154
A79: 147 | B79: Visita Domo de Ferro | C79: Qualidade | D79: DESC | E79: 46154 | F79: Giovani Moura Sousa | G79: Finalizada | H79: Finalizada | L79: CENTRO | M79: Sidrolândia | N79: Assembleia Legislativa | O79: Sidrolândia | P79: NÃO CONSTA INFORMAÇÕES BÁSICAS PARA SEGUIR COM A TRATATIVA. | Q79: 46154 | R79: Agente Giovani, quanto a qualidade sobre o reestabelecimento de energia em tempo hábil precisa de mais informações para análise da área. | S79: 46247 | X79: Giovani Moura Sousa | Y79: Gabriella Domingo | Z79: Deputado Renato Câmara Giovani Energisa | AA79: Giovani Moura Sousa | AB79: Não | AC79: Visita Domo de Ferro | AD79: 46268 | AE79: Moacir Costa Neto | AF79: 46247 | AG79: Gabriella Amorim Domingo | AH79: 100 | AI79: 100 | AJ79: 100 | AN79: =VLOOKUP(M79,[1]municipios!$B:$D,3,0) -> CAMPO GRANDE INTERIOR | AO79: =TODAY()-E79 -> 134 | AP79: =IF(AO79<=5,"0–5 dias",IF(AO79<=15,"6–15 dias",IF(AO79<=16,"16–30 dias",IF(AO79<=30,"30–50 dias",">50 dias")))) -> >50 dias | AQ79: =IF(U79="","Dentro",(IF(IF(W79="",TODAY(),W79)<=U79,"Dentro","Fora"))) -> Dentro | AR79: =IF(U79="","Não risco",IF((TODAY()-U79)<=7,"Risco","Não risco")) -> Não risco | AS79: =IF(SEARCH("integrar",P79)>0,"Sim","Não") -> #VALUE! | AT79: =IF(S79="",TODAY()-Q79,S79-Q79) -> 93 | AU79: =VLOOKUP(X79,'pontos focais'!C:D,2,0) -> Institucional | AV79: =U79-Q79 -> -46154
A80: 150 | B80: Visita Domo de Ferro | C80: Qualidade | D80: DESC | E80: 46154 | F80: Giovani Moura Sousa | G80: Finalizada | H80: Finalizada | I80: Câmara Municipal Ponta Porã | L80: SUL | M80: Ponta Porã | N80: Câmara | O80: Ponta Porã | P80: Solicitou atenão da Energisa quanto ao tempo de reestabelecimento da energia. Solicitou medição da energia que chega na torre transmissora da rádio de sua propriedade. | R80: Agente solicitar unidade consumidora ou uma referência para localizar a unidade reclamada. | S80: 46154 | T80: Enviado ao Agente no whats. Agente solicitar unidade consumidora ou uma referência para localizar a unidade reclamada. | X80: Vazio | Y80: Danila Souza | Z80: Vereador Agnaldo Miudinho Giovani energisa | AA80: Fabricio da Silva Almeida | AB80: Não | AC80: Visita Domo de Ferro | AD80: 46268 | AE80: Moacir Costa Neto | AF80: 46154 | AG80: Danila Hertal Moreira Souza | AH80: 25 | AI80: 25 | AJ80: 12.5 | AN80: =VLOOKUP(M80,[1]municipios!$B:$D,3,0) -> PONTA PORA | AO80: =TODAY()-E80 -> 134 | AP80: =IF(AO80<=5,"0–5 dias",IF(AO80<=15,"6–15 dias",IF(AO80<=16,"16–30 dias",IF(AO80<=30,"30–50 dias",">50 dias")))) -> >50 dias | AQ80: =IF(U80="","Dentro",(IF(IF(W80="",TODAY(),W80)<=U80,"Dentro","Fora"))) -> Dentro | AR80: =IF(U80="","Não risco",IF((TODAY()-U80)<=7,"Risco","Não risco")) -> Não risco | AS80: =IF(SEARCH("integrar",P80)>0,"Sim","Não") -> #VALUE! | AT80: =IF(S80="",TODAY()-Q80,S80-Q80) -> 46154 | AU80: =VLOOKUP(X80,'pontos focais'!C:D,2,0) -> Central do Cliente | AV80: =U80-Q80 -> 0
A81: 156 | B81: Visita Domo de Ferro | C81: Qualidade | D81: DEOP | E81: 46231 | F81: Giovani Moura Sousa | G81: Finalizada | H81: Finalizada | L81: SUL | M81: Dourados | N81: Câmara | O81: Dourados | P81: Vereador solicitou revisão no sistema elétrico nos bairros Novo Horizonte e Altos do Indaiá em Dourados. Protocolo 9500628194. | R81: Gentileza verificar os bairros relatados pelo vereador. Na reunião em campo o Agente de relacionamento Giovani coletou o protocolo 9500628194 UC 3742758. | S81: 46252 | T81: DUPLICADO COM ID 550 | W81: 46252 | X81: Gerson Mendes Ortiz | Y81: Bruna Santos | Z81: Vereador Sargento Prates Giovani energisa | AA81: Giovani Moura Sousa | AB81: Não | AC81: Visita Domo de Ferro | AD81: 46268 | AE81: Moacir Costa Neto | AF81: 46252 | AG81: Bruna Fabiana Braguin dos Santos | AH81: 25 | AI81: 25 | AJ81: 25 | AN81: =VLOOKUP(M81,[1]municipios!$B:$D,3,0) -> DOURADOS | AO81: =TODAY()-E81 -> 57 | AP81: =IF(AO81<=5,"0–5 dias",IF(AO81<=15,"6–15 dias",IF(AO81<=16,"16–30 dias",IF(AO81<=30,"30–50 dias",">50 dias")))) -> >50 dias | AQ81: =IF(U81="","Dentro",(IF(IF(W81="",TODAY(),W81)<=U81,"Dentro","Fora"))) -> Dentro | AR81: =IF(U81="","Não risco",IF((TODAY()-U81)<=7,"Risco","Não risco")) -> Não risco | AS81: =IF(SEARCH("integrar",P81)>0,"Sim","Não") -> #VALUE! | AT81: =IF(S81="",TODAY()-Q81,S81-Q81) -> 46252 | AU81: =VLOOKUP(X81,'pontos focais'!C:D,2,0) -> DEOP Qualidade | AV81: =U81-Q81 -> 0
A82: 186 | B82: Visita Domo de Ferro | C82: Atendimento Comercial | D82: DCMD | E82: 46231 | F82: Dian Cleiton de Brito | G82: Finalizada | H82: Finalizada | L82: SUL | M82: Jateí | N82: Prefeitura | O82: Jateí | P82: Agenda para evitar audiência Pública. | Q82: 46155 | R82: Arquivo da visita referentes ao pontos em KML em anexo nesse card. Ponto 1 – Poda MT/BT Ponto 4 – Poda MT Ponto 5 – Poda BT Ponto 6 – Manutenção Fusível Ponto 7 – Poda BT Ponto 12 – Medidor Exposto Ponto 13 – Poda BT Ponto 14 – Poda/Manutenção Ponto 15 – Poda BT Ponto 16 – Poda BT Ponto 17 – Poda BT Ponto 18 – Poda BT Ponto 19 – Poda MT Ponto 20 – Aprumar Poste Ponto 21 – Regularizar Ramal / Implantar Poste. Ponto 22 – Poda BT Ponto 23 – Poda MT Ponto 24 – Poda MT | S82: 46247 | V82: 46262 | X82: Evair Rogerio da Conceicao | Y82: Gabriella Domingo | Z82: Prefeita- Cileide Presidente da Câmara - Robinho Representante do Comercio SANESUL Representante assentamento rural | AA82: Dian Cleiton de Brito | AB82: Não | AC82: Visita Domo de Ferro | AD82: 46268 | AE82: Moacir Costa Neto | AF82: 46247 | AG82: Gabriella Amorim Domingo | AH82: 100 | AI82: 100 | AJ82: 100 | AN82: =VLOOKUP(M82,[1]municipios!$B:$D,3,0) -> DOURADOS | AO82: =TODAY()-E82 -> 57 | AP82: =IF(AO82<=5,"0–5 dias",IF(AO82<=15,"6–15 dias",IF(AO82<=16,"16–30 dias",IF(AO82<=30,"30–50 dias",">50 dias")))) -> >50 dias | AQ82: =IF(U82="","Dentro",(IF(IF(W82="",TODAY(),W82)<=U82,"Dentro","Fora"))) -> Dentro | AR82: =IF(U82="","Não risco",IF((TODAY()-U82)<=7,"Risco","Não risco")) -> Não risco | AS82: =IF(SEARCH("integrar",P82)>0,"Sim","Não") -> #VALUE! | AT82: =IF(S82="",TODAY()-Q82,S82-Q82) -> 92 | AU82: =VLOOKUP(X82,'pontos focais'!C:D,2,0) -> DCMD Manutenção | AV82: =U82-Q82 -> -46155
A83: 186 | B83: Visita Domo de Ferro | C83: Atendimento Comercial | D83: DEOP | E83: 46231 | F83: Dian Cleiton de Brito | G83: Finalizada | H83: Finalizada | L83: SUL | M83: Jateí | N83: Prefeitura | O83: Jateí | P83: Agenda para evitar audiência Pública. | R83: Sobrecarga: Alegaram que um dos loteamentos da cidade está com constantes faltas de energia, e que suspeitam de sobrecarga, o bairro se chama PORTAL DO SOL. Explicamos para os presentes que podemos estar tratando de um possível aumento de carga a revelia. Solicitamos para que a câmara nos passe as UC´s para realizarmos uma avaliação completa no local.Citaram que lá existe: Igreja, salão, funilaria, loja de material para construção. As referências elétricas são: TD(748480) // TD(748483) // TD (705324) // TD (705323) // TD (9631) - GDO02 Falta de energia: Gleba Nova Esperança: Alegam constantes interrupções nesta região, alegam que lá existe uma escola com mais de 200 alunos e que vem sofrendo com constantes quedas de energia. As referências elétricas são: TD(35070) // TD (34501) // TD (719015) – NHS 01. Manutenção: Informaram que existe uma demanda para troca de postes de madeira de eucalipto. Informações que iriamos checar o status dessa demanda e dar uma devolutiva. | S83: 46259 | T83: É necessário que o município encaminhe um oficio contendo as unidades consumidoras e a descrição de cada uma, para que possamos realizar o ajuste, o município precisa formalizar o pedido através de oficio. | W83: 46259 | X83: Gerson Mendes Ortiz | Y83: Wander Machado | Z83: Prefeita- Cileide Presidente da Câmara - Robinho Representante do Comercio SANESUL Representante assentamento rural | AA83: Dian Cleiton de Brito | AB83: Não | AC83: Visita Domo de Ferro | AD83: 46268 | AE83: Moacir Costa Neto | AF83: 46259 | AG83: Wander Idalino Machado | AH83: 100 | AI83: 100 | AJ83: 100 | AN83: =VLOOKUP(M83,[1]municipios!$B:$D,3,0) -> DOURADOS | AO83: =TODAY()-E83 -> 57 | AP83: =IF(AO83<=5,"0–5 dias",IF(AO83<=15,"6–15 dias",IF(AO83<=16,"16–30 dias",IF(AO83<=30,"30–50 dias",">50 dias")))) -> >50 dias | AQ83: =IF(U83="","Dentro",(IF(IF(W83="",TODAY(),W83)<=U83,"Dentro","Fora"))) -> Dentro | AR83: =IF(U83="","Não risco",IF((TODAY()-U83)<=7,"Risco","Não risco")) -> Não risco | AS83: =IF(SEARCH("integrar",P83)>0,"Sim","Não") -> #VALUE! | AT83: =IF(S83="",TODAY()-Q83,S83-Q83) -> 46259 | AU83: =VLOOKUP(X83,'pontos focais'!C:D,2,0) -> DEOP Qualidade | AV83: =U83-Q83 -> 0
A84: 186 | B84: Visita Domo de Ferro | C84: Atendimento Comercial | D84: DESC | E84: 46231 | F84: Dian Cleiton de Brito | G84: Finalizada | H84: Finalizada | L84: SUL | M84: Jateí | N84: Prefeitura | O84: Jateí | P84: Agenda para evitar audiência Pública. | Q84: 46155 | R84: Ajuste no Faturamento: A Prefeita solicita a alteração dos nomes das unidades consumidoras da Prefeitura, de forma a facilitar a gestão do município na hora de pagar as despesas, uma vez que atualmente a descrição das unidades da Prefeitura não discriminam qual é o local (Posto de Saúde, Creche, Escola, Prefeitura). | S84: 46259 | T84: É necessário que o município encaminhe um oficio contendo as unidades consumidoras e a descrição de cada uma, para que possamos realizar o ajuste, o município precisa formalizar o pedido através de oficio. | W84: 46259 | X84: Monike Chaves | Y84: Wander Machado | Z84: Prefeita- Cileide Presidente da Câmara - Robinho Representante do Comercio SANESUL Representante assentamento rural | AA84: Dian Cleiton de Brito | AB84: Não | AC84: Visita Domo de Ferro | AD84: 46268 | AE84: Moacir Costa Neto | AF84: 46259 | AG84: Wander Idalino Machado | AH84: 100 | AI84: 100 | AJ84: 100 | AN84: =VLOOKUP(M84,[1]municipios!$B:$D,3,0) -> DOURADOS | AO84: =TODAY()-E84 -> 57 | AP84: =IF(AO84<=5,"0–5 dias",IF(AO84<=15,"6–15 dias",IF(AO84<=16,"16–30 dias",IF(AO84<=30,"30–50 dias",">50 dias")))) -> >50 dias | AQ84: =IF(U84="","Dentro",(IF(IF(W84="",TODAY(),W84)<=U84,"Dentro","Fora"))) -> Dentro | AR84: =IF(U84="","Não risco",IF((TODAY()-U84)<=7,"Risco","Não risco")) -> Não risco | AS84: =IF(SEARCH("integrar",P84)>0,"Sim","Não") -> #VALUE! | AT84: =IF(S84="",TODAY()-Q84,S84-Q84) -> 104 | AU84: DESC Agentes de Relacionamento | AV84: =U84-Q84 -> -46155
A85: 248 | B85: Visita Domo de Ferro | C85: Obra | D85: DESC | E85: 46154 | F85: Dian Cleiton de Brito | G85: Finalizada | H85: Finalizada | L85: SUL | M85: Fátima do Sul | N85: Prefeitura | O85: Fátima do Sul | P85: SOLICITA AGILIZAR ANALISE DE PROJETO DE GD QUE TEM RECURSOS APROVADOS PELA ITAIPU. PROJETO APROVADO DIA 27/05. | Q85: 46195 | R85: Dian, gentileza confirmar com a prefeitura se receberam o orçamento. E garantir estão ciente que devem solicitar o orçamento do ponto de entrega para conexão do empreendimento, pois até o momento não tem essa solicitação registrada. | S85: 46247 | X85: Dian Cleiton de Brito | Y85: Gabriella Domingo | Z85: Marcio Jose Gomes Danilo Katsomori Dirceu Deguti Viera Filho Bruno de Araujo Benites Rosa da EFENG | AA85: Dian Cleiton de Brito | AB85: Não | AC85: Visita Domo de Ferro | AD85: 46268 | AE85: Moacir Costa Neto | AF85: 46247 | AG85: Gabriella Amorim Domingo | AH85: 100 | AI85: 100 | AJ85: 100 | AN85: =VLOOKUP(M85,[1]municipios!$B:$D,3,0) -> RIO BRILHANTE | AO85: =TODAY()-E85 -> 134 | AP85: =IF(AO85<=5,"0–5 dias",IF(AO85<=15,"6–15 dias",IF(AO85<=16,"16–30 dias",IF(AO85<=30,"30–50 dias",">50 dias")))) -> >50 dias | AQ85: =IF(U85="","Dentro",(IF(IF(W85="",TODAY(),W85)<=U85,"Dentro","Fora"))) -> Dentro | AR85: =IF(U85="","Não risco",IF((TODAY()-U85)<=7,"Risco","Não risco")) -> Não risco | AS85: =IF(SEARCH("integrar",P85)>0,"Sim","Não") -> #VALUE! | AT85: =IF(S85="",TODAY()-Q85,S85-Q85) -> 52 | AU85: =VLOOKUP(X85,'pontos focais'!C:D,2,0) -> Institucional | AV85: =U85-Q85 -> -46195
A86: 248 | B86: Visita Domo de Ferro | C86: Projeto Elétrico | D86: DCMD | E86: 46154 | F86: Dian Cleiton de Brito | G86: Finalizada | H86: Finalizada | L86: SUL | M86: Fátima do Sul | N86: Prefeitura | O86: Fátima do Sul | P86: SOLICITA AGILIZAR ANALISE DE PROJETO DE GD QUE TEM RECURSOS APROVADOS PELA ITAIPU. PROJETO APROVADO DIA 27/05. | Q86: 46155 | R86: Solicitado para agilizar análise do PE 1962226. OS nº 530498622. | S86: 46197 | U86: 46234 | W86: 46195 | X86: Bruna Victoria Rodrigues Ricardes | Y86: Rafaela Almeida | Z86: Marcio Jose Gomes Danilo Katsomori Dirceu Deguti Viera Filho Bruno de Araujo Benites Rosa da EFENG | AA86: Dian Cleiton de Brito | AB86: Não | AC86: Visita Domo de Ferro | AD86: 46268 | AE86: Moacir Costa Neto | AF86: 46197 | AG86: Rafaela Mattos de Almeida | AH86: 100 | AI86: 100 | AJ86: 100 | AN86: =VLOOKUP(M86,[1]municipios!$B:$D,3,0) -> RIO BRILHANTE | AO86: =TODAY()-E86 -> 134 | AP86: =IF(AO86<=5,"0–5 dias",IF(AO86<=15,"6–15 dias",IF(AO86<=16,"16–30 dias",IF(AO86<=30,"30–50 dias",">50 dias")))) -> >50 dias | AQ86: =IF(U86="","Dentro",(IF(IF(W86="",TODAY(),W86)<=U86,"Dentro","Fora"))) -> Dentro | AR86: =IF(U86="","Não risco",IF((TODAY()-U86)<=7,"Risco","Não risco")) -> Não risco | AS86: =IF(SEARCH("integrar",P86)>0,"Sim","Não") -> #VALUE! | AT86: =IF(S86="",TODAY()-Q86,S86-Q86) -> 42 | AU86: =VLOOKUP(X86,'pontos focais'!C:D,2,0) -> DCMD Orçamento e Projetos | AV86: =U86-Q86 -> 79
A87: 269 | B87: Visita Domo de Ferro | C87: Informação | D87: DESC | E87: 46052 | F87: Monike Chaves | G87: Finalizada | H87: Finalizada | I87: Prefeitura de Rio Negro | L87: NORTE | M87: Rio Negro | N87: Prefeitura | O87: Rio Negro | P87: Agenda de Campo - Projeto Integrar | Q87: 46155 | R87: Sinalizado alguns empreendimentos novos no município que será lançado como: Loteamento Valdemar Pedro e a Pavimentação da estrada da Ponte Nova. | X87: Monike Chaves | AA87: Luis Filipe Swenson Pereira Amado, Anderson Brum Smaniotto | AB87: Não | AC87: Visita Domo de Ferro | AD87: 46268 | AE87: Moacir Costa Neto | AF87: 46155 | AG87: Danila Hertal Moreira Souza | AH87: 100 | AI87: 100 | AJ87: 50 | AN87: =VLOOKUP(M87,[1]municipios!$B:$D,3,0) -> COXIM | AO87: =TODAY()-E87 -> 236 | AP87: =IF(AO87<=5,"0–5 dias",IF(AO87<=15,"6–15 dias",IF(AO87<=16,"16–30 dias",IF(AO87<=30,"30–50 dias",">50 dias")))) -> >50 dias | AQ87: =IF(U87="","Dentro",(IF(IF(W87="",TODAY(),W87)<=U87,"Dentro","Fora"))) -> Dentro | AR87: =IF(U87="","Não risco",IF((TODAY()-U87)<=7,"Risco","Não risco")) -> Não risco | AS87: =IF(SEARCH("integrar",P87)>0,"Sim","Não") -> Sim | AT87: =IF(S87="",TODAY()-Q87,S87-Q87) -> 133 | AU87: =VLOOKUP(X87,'pontos focais'!C:D,2,0) -> DESC Agentes de Relacionamento | AV87: =U87-Q87 -> -46155
A88: 269 | B88: Visita Domo de Ferro | C88: Qualidade | D88: DEOP | E88: 46052 | F88: Monike Chaves | G88: Finalizada | H88: Finalizada | L88: NORTE | M88: Rio Negro | N88: Prefeitura | O88: Rio Negro | P88: Agenda de Campo - Projeto Integrar | Q88: 46155 | R88: Ativar o RD recém instalado: RD58497164. | S88: 46247 | T88: RD58497164 - com supervisão, imagem anexo. | W88: 46247 | X88: Gerson Mendes Ortiz | Y88: Bruna Santos | AA88: Luis Filipe Swenson Pereira Amado, Anderson Brum Smaniotto | AB88: Não | AC88: Visita Domo de Ferro | AD88: 46268 | AE88: Moacir Costa Neto | AF88: 46247 | AG88: Bruna Fabiana Braguin dos Santos | AH88: 100 | AI88: 100 | AJ88: 100 | AN88: =VLOOKUP(M88,[1]municipios!$B:$D,3,0) -> COXIM | AO88: =TODAY()-E88 -> 236 | AP88: =IF(AO88<=5,"0–5 dias",IF(AO88<=15,"6–15 dias",IF(AO88<=16,"16–30 dias",IF(AO88<=30,"30–50 dias",">50 dias")))) -> >50 dias | AQ88: =IF(U88="","Dentro",(IF(IF(W88="",TODAY(),W88)<=U88,"Dentro","Fora"))) -> Dentro | AR88: =IF(U88="","Não risco",IF((TODAY()-U88)<=7,"Risco","Não risco")) -> Não risco | AS88: =IF(SEARCH("integrar",P88)>0,"Sim","Não") -> Sim | AT88: =IF(S88="",TODAY()-Q88,S88-Q88) -> 92 | AU88: =VLOOKUP(X88,'pontos focais'!C:D,2,0) -> DEOP Qualidade | AV88: =U88-Q88 -> -46155
A89: 270 | B89: Visita Domo de Ferro | C89: Atendimento Comercial | D89: DEOP | E89: 46160 | F89: Monike Chaves | G89: Finalizada | H89: Finalizada | L89: SUL | M89: Vicentina | N89: Prefeitura | O89: Vicentina | P89: Agenda de Campo - Projeto Integrar | Q89: 46160 | R89: Prefeito pediu uma atenção especial para um assentamento que fica no município de Caarapó, porém pela proximidade com Vicentina os moradores vão até o município para solicitar melhorias, são produtores de leite. ASSENTAMENTO NOSSA SRA. DO CARMO - 41 Assentados. Manutenção de rede. Verificar reincidência de abertura e inserir num acompanhamento específico. Referências elétricas: FU(963) FU(38390) - VIC02 | S89: 46247 | T89: AÇÃO FINALIZADA EM CAMPO, EM CONTATO COM O PREFEITO, HOUVE UMA MELHORA SIGNIFICATIVA APÓS AS MANUTENÇÕES | W89: 46247 | X89: Luan Henrique Soares Diniz Afonso | Y89: Bruna Santos | Z89: Reunião realizada com a prefeitura: Prefeito Cleber, Bruna e Leticia. | AA89: Diego Souza Silva | AB89: Não | AC89: Visita Domo de Ferro | AD89: 46268 | AE89: Moacir Costa Neto | AF89: 46247 | AG89: Bruna Fabiana Braguin dos Santos | AH89: 100 | AI89: 100 | AJ89: 100 | AN89: =VLOOKUP(M89,[1]municipios!$B:$D,3,0) -> NOVA ANDRADINA | AO89: =TODAY()-E89 -> 128 | AP89: =IF(AO89<=5,"0–5 dias",IF(AO89<=15,"6–15 dias",IF(AO89<=16,"16–30 dias",IF(AO89<=30,"30–50 dias",">50 dias")))) -> >50 dias | AQ89: =IF(U89="","Dentro",(IF(IF(W89="",TODAY(),W89)<=U89,"Dentro","Fora"))) -> Dentro | AR89: =IF(U89="","Não risco",IF((TODAY()-U89)<=7,"Risco","Não risco")) -> Não risco | AS89: =IF(SEARCH("integrar",P89)>0,"Sim","Não") -> Sim | AT89: =IF(S89="",TODAY()-Q89,S89-Q89) -> 87 | AU89: =VLOOKUP(X89,'pontos focais'!C:D,2,0) -> DEOP Qualidade | AV89: =U89-Q89 -> -46160
A90: 270 | B90: Visita Domo de Ferro | C90: Atendimento Comercial | D90: DESC | E90: 46160 | F90: Monike Chaves | G90: Finalizada | H90: Finalizada | L90: SUL | M90: Vicentina | N90: Prefeitura | O90: Vicentina | P90: Agenda de Campo - Projeto Integrar | Q90: 46160 | R90: Checar se estão cadastrados como bacia leiteira | S90: 46197 | U90: 46191 | X90: Monike Chaves | Y90: Rafaela Almeida | Z90: Reunião realizada com a prefeitura: Prefeito Cleber, Bruna e Leticia. | AA90: Diego Souza Silva | AB90: Não | AC90: Visita Domo de Ferro | AD90: 46268 | AE90: Moacir Costa Neto | AF90: 46197 | AG90: Rafaela Mattos de Almeida | AH90: 100 | AI90: 100 | AJ90: 100 | AN90: =VLOOKUP(M90,[1]municipios!$B:$D,3,0) -> NOVA ANDRADINA | AO90: =TODAY()-E90 -> 128 | AP90: =IF(AO90<=5,"0–5 dias",IF(AO90<=15,"6–15 dias",IF(AO90<=16,"16–30 dias",IF(AO90<=30,"30–50 dias",">50 dias")))) -> >50 dias | AQ90: =IF(U90="","Dentro",(IF(IF(W90="",TODAY(),W90)<=U90,"Dentro","Fora"))) -> Fora | AR90: =IF(U90="","Não risco",IF((TODAY()-U90)<=7,"Risco","Não risco")) -> Não risco | AS90: =IF(SEARCH("integrar",P90)>0,"Sim","Não") -> Sim | AT90: =IF(S90="",TODAY()-Q90,S90-Q90) -> 37 | AU90: =VLOOKUP(X90,'pontos focais'!C:D,2,0) -> DESC Agentes de Relacionamento | AV90: =U90-Q90 -> 31
A91: 272 | B91: Visita Domo de Ferro | C91: Atendimento Comercial | D91: Central do Cliente | E91: 46155 | F91: Danila Hertal Moreira Souza | G91: Finalizada | H91: Finalizada | L91: SUL | M91: Dourados | N91: Prefeitura | O91: Dourados | P91: Origem: Thiago Balbio/Pres. Paulo. Solicitação de prioridade da obra 0202600473- Afastamento de Rede OS 509306177. Expectativa do cliente: o quanto antes essas, lançado no priorizador 31/05. | Q91: 46155 | S91: 46245 | X91: Vazio | Y91: Aline Mesquita | Z91: Prefeito Marçal Filho | AA91: Danila Hertal Moreira Souza | AB91: Não | AC91: Visita Domo de Ferro | AD91: 46268 | AE91: Moacir Costa Neto | AF91: 46245 | AG91: Aline da Silva Mesquita | AH91: 100 | AI91: 100 | AJ91: 100 | AN91: =VLOOKUP(M91,[1]municipios!$B:$D,3,0) -> DOURADOS | AO91: =TODAY()-E91 -> 133 | AP91: =IF(AO91<=5,"0–5 dias",IF(AO91<=15,"6–15 dias",IF(AO91<=16,"16–30 dias",IF(AO91<=30,"30–50 dias",">50 dias")))) -> >50 dias | AQ91: =IF(U91="","Dentro",(IF(IF(W91="",TODAY(),W91)<=U91,"Dentro","Fora"))) -> Dentro | AR91: =IF(U91="","Não risco",IF((TODAY()-U91)<=7,"Risco","Não risco")) -> Não risco | AS91: =IF(SEARCH("integrar",P91)>0,"Sim","Não") -> #VALUE! | AT91: =IF(S91="",TODAY()-Q91,S91-Q91) -> 90 | AU91: =VLOOKUP(X91,'pontos focais'!C:D,2,0) -> Central do Cliente | AV91: =U91-Q91 -> -46155
A92: 272 | B92: Visita Domo de Ferro | C92: Obra | D92: DCMD | E92: 46155 | F92: Danila Hertal Moreira Souza | G92: Finalizada | H92: Finalizada | I92: Prefeitura de Dourados | K92: 0202600473 | L92: SUL | M92: Dourados | N92: Prefeitura | O92: Dourados | P92: Origem: Thiago Balbio/Pres. Paulo. Solicitação de prioridade da obra 0202600473- Afastamento de Rede OS 509306177. Expectativa do cliente: o quanto antes essas, lançado no priorizador 31/05. | Q92: 46155 | R92: Origem: Thiago Balbio/Pres. Paulo. Solicitação de prioridade da obra 0202600473- Afastamento de Rede OS 509306177. Expectativa do cliente: o quanto antes essas, lançado no priorizador 31/05. | S92: 46184 | T92: CONCLUIDA | U92: 46173 | X92: Felipe Souza do Nascimento | Y92: Felipe Nascimento | Z92: Prefeito Marçal Filho | AA92: Danila Hertal Moreira Souza | AB92: Não | AC92: Visita Domo de Ferro | AD92: 46268 | AE92: Moacir Costa Neto | AF92: 46184 | AG92: Felipe Souza do Nascimento | AH92: 100 | AI92: 100 | AJ92: 50 | AN92: =VLOOKUP(M92,[1]municipios!$B:$D,3,0) -> DOURADOS | AO92: =TODAY()-E92 -> 133 | AP92: =IF(AO92<=5,"0–5 dias",IF(AO92<=15,"6–15 dias",IF(AO92<=16,"16–30 dias",IF(AO92<=30,"30–50 dias",">50 dias")))) -> >50 dias | AQ92: =IF(U92="","Dentro",(IF(IF(W92="",TODAY(),W92)<=U92,"Dentro","Fora"))) -> Fora | AR92: =IF(U92="","Não risco",IF((TODAY()-U92)<=7,"Risco","Não risco")) -> Não risco | AS92: =IF(SEARCH("integrar",P92)>0,"Sim","Não") -> #VALUE! | AT92: =IF(S92="",TODAY()-Q92,S92-Q92) -> 29 | AU92: =VLOOKUP(X92,'pontos focais'!C:D,2,0) -> DCMD Programação de Obra | AV92: =U92-Q92 -> 18
A93: 283 | B93: Visita Domo de Ferro | C93: Manutenção | D93: DCMD | E93: 46156 | F93: Giovani Moura Sousa | G93: Finalizada | H93: Finalizada | L93: CENTRO | M93: Campo Grande | N93: Câmara | O93: Campo Grande | P93: RECOMPOSIÇÃO DE ENERGIA EM RUA LATERAL DO CONDOMÍNIO RIVIERA LIGAÇÃO DE ILUMINAÇÃO PÚBLICA | Q93: 46162 | R93: Conforme conversado pelo ligação com o César irá uma equipe no local hoje 20/05 para realizar o levantamento do que precisa para realizar a adequação da rede no máximo até sexta 22/05. | S93: 46255 | T93: EM CONTATO COM O CESAR DO DCMD, INFORMOU QUE FOI REGULARIZADO | X93: Evair Rogerio da Conceicao | Y93: Bruna Santos | Z93: Vereador André Salineiro Giovani Moura Energisa | AA93: Giovani Moura Sousa | AB93: Não | AC93: Visita Domo de Ferro | AD93: 46255 | AE93: Bruna Fabiana Braguin dos Santos | AF93: 46255 | AG93: Bruna Fabiana Braguin dos Santos | AH93: 25 | AI93: 25 | AJ93: 25 | AN93: =VLOOKUP(M93,[1]municipios!$B:$D,3,0) -> CAMPO GRANDE | AO93: =TODAY()-E93 -> 132 | AP93: =IF(AO93<=5,"0–5 dias",IF(AO93<=15,"6–15 dias",IF(AO93<=16,"16–30 dias",IF(AO93<=30,"30–50 dias",">50 dias")))) -> >50 dias | AQ93: =IF(U93="","Dentro",(IF(IF(W93="",TODAY(),W93)<=U93,"Dentro","Fora"))) -> Dentro | AR93: =IF(U93="","Não risco",IF((TODAY()-U93)<=7,"Risco","Não risco")) -> Não risco | AS93: =IF(SEARCH("integrar",P93)>0,"Sim","Não") -> #VALUE! | AT93: =IF(S93="",TODAY()-Q93,S93-Q93) -> 93 | AU93: =VLOOKUP(X93,'pontos focais'!C:D,2,0) -> DCMD Manutenção | AV93: =U93-Q93 -> -46162
A94: 290 | B94: Visita Domo de Ferro | C94: Atendimento Comercial | D94: DEOP | E94: 46054 | F94: Monike Chaves | G94: Finalizada | H94: Finalizada | L94: SUL | M94: Jateí | N94: Prefeitura | O94: Jateí | P94: Agenda de Campo - Projeto Integrar | Q94: 46160 | R94: 1 - Falta de energia: Gleba Nova Esperança: Alegam constantes interrupções nesta região, alegam que lá existe uma escola com mais de 200 alunos e que vem sofrendo com constantes quedas de energia. Informaram que existe uma demanda para troca de postes de madeira de eucalipto. Informações que iriamos checar o status dessa demanda e dar uma devolutiva. SENDO TRATADO NO CARD 186. 2 - Nível de tensão: Recebemos muitas reclamações dos vereadores de oscilações de energia ao longo do período diurno. PENDENTE 3 - | S94: 46247 | T94: TODAS AS AÇÕES CONCLUÍDAS | W94: 46247 | X94: Luan Henrique Soares Diniz Afonso | Y94: Bruna Santos | Z94: Prefeitura e Câmara: Prefeita Cileide, Vice Prefeito Francisco, Vereadora Antônia, Vereador Edson e Outros 4 vereadores | AA94: Diego Souza Silva, Emerson Seixas Costa, Thiago de Alvarenga Balbio | AB94: Não | AC94: Solicitações GA | AD94: 46268 | AE94: Moacir Costa Neto | AF94: 46247 | AG94: Bruna Fabiana Braguin dos Santos | AH94: 100 | AI94: 100 | AJ94: 100 | AN94: =VLOOKUP(M94,[1]municipios!$B:$D,3,0) -> DOURADOS | AO94: =TODAY()-E94 -> 234 | AP94: =IF(AO94<=5,"0–5 dias",IF(AO94<=15,"6–15 dias",IF(AO94<=16,"16–30 dias",IF(AO94<=30,"30–50 dias",">50 dias")))) -> >50 dias | AQ94: =IF(U94="","Dentro",(IF(IF(W94="",TODAY(),W94)<=U94,"Dentro","Fora"))) -> Dentro | AR94: =IF(U94="","Não risco",IF((TODAY()-U94)<=7,"Risco","Não risco")) -> Não risco | AS94: =IF(SEARCH("integrar",P94)>0,"Sim","Não") -> Sim | AT94: =IF(S94="",TODAY()-Q94,S94-Q94) -> 87 | AU94: =VLOOKUP(X94,'pontos focais'!C:D,2,0) -> DEOP Qualidade | AV94: =U94-Q94 -> -46160
A95: 290 | B95: Visita Domo de Ferro | C95: Atendimento Comercial | D95: DESC | E95: 46054 | F95: Monike Chaves | G95: Finalizada | H95: Finalizada | L95: SUL | M95: Jateí | N95: Prefeitura | O95: Jateí | P95: Agenda de Campo - Projeto Integrar | Q95: 46160 | R95: 1 - Prefeita informou que a maior festa da cidade é a festa da fogueira, e será em 2026 em 29/06. INFORMAÇÃO 2 - Hotel na frente da praça: Prefeita citou que esse hotel é do mesmo dono do restaurante, a solicitação está no nome do solicitante: Edson Alves dos Santos (67 99698-3121). Prefeita pediu para agilizar esse pedido. PENDENTE 3 - A unidade consumidora do restaurante (mesmo dono), alega estar com problemas de tensão, iremos checar para ver se temos histórico deste pedido. Edson Alves dos Santos (67 99698-3121). PENDENTE 4 - A Prefeita solicita a alteração dos nomes das unidades consumidoras da Prefeitura, de forma a facilitar a gestão do município na hora de pagar as despesas, uma vez que atualmente a descrição das unidades da Prefeitura não discriminam qual é o local (Posto de Saúde, Creche, Escola, Prefeitura). SENDO TRATADO NO CARD 186 5 - Atendimento: Reclamaram muito da GISA e do CallBack realizado pela Energisa, citaram muita dificuldade em serem atendidos pelos canais digitais. (PENDENTE) 6 - Prefeita citou sobre a comissão da Assomasul (Associação dos Municípios de Mato Grosso do Sul), onde percebe que estão sendo tratados muitos assuntos que envolvem a Energisa. INFORMAÇÃO 7 - usina solar construída pela Prefeitura. SENDO TRATADO NO CARD 186 8 - A Prefeita trouxe para discussão a COSIP e a taxa de iluminação pública. Ela até citou que desejava utilizar os créditos de sua usina solar para abater a Cosip, mas de qualquer forma caso essa ideia não seja viável, deseja ver uma forma de isentar as famílias de baixa rende de pagar a taxa, e segundo e vereador Edson, já existe uma lei municipal prevendo essa possibilidade. Monike explicou que existe uma Portaria que ampara esse assunto, a se comprometeu a compartilhar com a Prefeitura. SENDO TRATADO NO CARD 186 9 - Sobre a carreta "Nossa Energia" da Eficiência Energética. Prefeita demonstrou interesse, solicitei para que ela sugerisse uma data para a realização de uma ação na cidade. (11 de novembro é o aniversário da cidade). Dia da Mulher: Em razão do município de Jateí. INFORMAÇÃO | S95: 46247 | T95: TODAS AS AÇÕES TRATADAS. | W95: 46247 | X95: Monike Chaves | Y95: Bruna Santos | Z95: Prefeitura e Câmara: Prefeita Cileide, Vice Prefeito Francisco, Vereadora Antônia, Vereador Edson e Outros 4 vereadores | AA95: Diego Souza Silva, Emerson Seixas Costa, Thiago de Alvarenga Balbio | AB95: Não | AC95: Visita Domo de Ferro | AD95: 46268 | AE95: Moacir Costa Neto | AF95: 46247 | AG95: Bruna Fabiana Braguin dos Santos | AH95: 100 | AI95: 100 | AJ95: 100 | AN95: =VLOOKUP(M95,[1]municipios!$B:$D,3,0) -> DOURADOS | AO95: =TODAY()-E95 -> 234 | AP95: =IF(AO95<=5,"0–5 dias",IF(AO95<=15,"6–15 dias",IF(AO95<=16,"16–30 dias",IF(AO95<=30,"30–50 dias",">50 dias")))) -> >50 dias | AQ95: =IF(U95="","Dentro",(IF(IF(W95="",TODAY(),W95)<=U95,"Dentro","Fora"))) -> Dentro | AR95: =IF(U95="","Não risco",IF((TODAY()-U95)<=7,"Risco","Não risco")) -> Não risco | AS95: =IF(SEARCH("integrar",P95)>0,"Sim","Não") -> Sim | AT95: =IF(S95="",TODAY()-Q95,S95-Q95) -> 87 | AU95: =VLOOKUP(X95,'pontos focais'!C:D,2,0) -> DESC Agentes de Relacionamento | AV95: =U95-Q95 -> -46160
A96: 290 | B96: Visita Domo de Ferro | C96: Qualidade | D96: DEOP | E96: 46054 | F96: Monike Chaves | G96: Finalizada | H96: Finalizada | I96: Prefeitura de Jateí | L96: SUL | M96: Jateí | N96: Prefeitura | O96: Jateí | P96: Agenda de Campo - Projeto Integrar | Q96: 46160 | R96: Sobrecarga: Alegaram que um dos loteamentos da cidade está com constantes faltas de energia, e que suspeitam de sobrecarga, o bairro se chama PORTAL DO SOL. Explicamos para os presentes que podemos estar tratando de um possível aumento de carga à revelia. Solicitamos para que a câmara nos informes as unidades consumidores para realizarmos uma avaliação completa no local. Citaram que lá existe: Igreja, salão, funilaria, loja de material para construção. As referências elétricas são: TD(748480) // TD(748483) - GDO02 | X96: Luan Henrique Soares Diniz Afonso | Z96: Prefeitura e Câmara: Prefeita Cileide, Vice Prefeito Francisco, Vereadora Antônia, Vereador Edson e Outros 4 vereadores | AA96: Diego Souza Silva, Emerson Seixas Costa, Thiago de Alvarenga Balbio | AB96: Não | AC96: Visita Domo de Ferro | AD96: 46268 | AE96: Moacir Costa Neto | AF96: 46160 | AG96: Danila Hertal Moreira Souza | AH96: 100 | AI96: 100 | AJ96: 50 | AN96: =VLOOKUP(M96,[1]municipios!$B:$D,3,0) -> DOURADOS | AO96: =TODAY()-E96 -> 234 | AP96: =IF(AO96<=5,"0–5 dias",IF(AO96<=15,"6–15 dias",IF(AO96<=16,"16–30 dias",IF(AO96<=30,"30–50 dias",">50 dias")))) -> >50 dias | AQ96: =IF(U96="","Dentro",(IF(IF(W96="",TODAY(),W96)<=U96,"Dentro","Fora"))) -> Dentro | AR96: =IF(U96="","Não risco",IF((TODAY()-U96)<=7,"Risco","Não risco")) -> Não risco | AS96: =IF(SEARCH("integrar",P96)>0,"Sim","Não") -> Sim | AT96: =IF(S96="",TODAY()-Q96,S96-Q96) -> 128 | AU96: =VLOOKUP(X96,'pontos focais'!C:D,2,0) -> DEOP Qualidade | AV96: =U96-Q96 -> -46160
A97: 291 | B97: Visita Domo de Ferro | C97: Atendimento Comercial | D97: Atendimento | E97: 46054 | F97: Monike Chaves | G97: Finalizada | H97: Finalizada | L97: SUL | M97: Deodápolis | N97: Prefeitura | O97: Deodápolis | P97: Agenda de Campo - Projeto Integrar | Q97: 46160 | R97: Atendimento: O Prefeito alegou dificuldades com o formato atual de atendimento na cidade, que é realizado dentro do Supermercado Macaúba em um Tóten com o auxílio de uma colaboradora do próprio mercado. Ele nos informou que está abrindo uma central de atendimento ao cidadão, e ofereceu um dos postos, inclusive com mão de obra, para a agência a alocação de 1 tóten da Energisa. Essa central de atendimento estará pronta no segundo semestre. | S97: 46246 | W97: 46246 | X97: Wesley Ricardo Santana Cosim | Y97: Bruna Santos | Z97: Prefeitura e Câmara: Prefeito Jean, Assessor Orlindo. | AA97: Diego Souza Silva, Emerson Seixas Costa, Thiago de Alvarenga Balbio | AB97: Não | AC97: Solicitações GA | AD97: 46268 | AE97: Moacir Costa Neto | AF97: 46246 | AG97: Bruna Fabiana Braguin dos Santos | AH97: 100 | AI97: 100 | AJ97: 100 | AN97: =VLOOKUP(M97,[1]municipios!$B:$D,3,0) -> NOVA ANDRADINA | AO97: =TODAY()-E97 -> 234 | AP97: =IF(AO97<=5,"0–5 dias",IF(AO97<=15,"6–15 dias",IF(AO97<=16,"16–30 dias",IF(AO97<=30,"30–50 dias",">50 dias")))) -> >50 dias | AQ97: =IF(U97="","Dentro",(IF(IF(W97="",TODAY(),W97)<=U97,"Dentro","Fora"))) -> Dentro | AR97: =IF(U97="","Não risco",IF((TODAY()-U97)<=7,"Risco","Não risco")) -> Não risco | AS97: =IF(SEARCH("integrar",P97)>0,"Sim","Não") -> Sim | AT97: =IF(S97="",TODAY()-Q97,S97-Q97) -> 86 | AU97: =VLOOKUP(X97,'pontos focais'!C:D,2,0) -> Atendimento | AV97: =U97-Q97 -> -46160
A98: 291 | B98: Visita Domo de Ferro | C98: Atendimento Comercial | D98: DESC | E98: 46054 | F98: Monike Chaves | G98: Finalizada | H98: Finalizada | L98: SUL | M98: Deodápolis | N98: Prefeitura | O98: Deodápolis | P98: Agenda de Campo - Projeto Integrar | Q98: 46160 | R98: 1 - Creche João Pedro Pelegrini - Esta unidade ocupa atualmente 1/2 quarteirão, e segundo o Prefeito irão construir um Posto de Saúde. Eles alegam que atualmente o circuito já está apresentando constantes interrupções, e que na visão deles seria por problemas de sobrecarga. Definimos que a Prefeitura nos enviaria a carga atual da creche, e faremos uma análise com medição e levantamento em campo para identificação do atual problema. Neste levantamento já podemos checar qual será a melhor forma de atender a futura carga do posto de saúde que ficará nesta quadra. PENDENTE 2 - Alegaram que o prédio da Prefeitura também está com problemas de sobrecarga, geralmente percebido quando se liga o ar-condicionado. Com base na descrição do Sr. Orlindo, fica evidente se tratar de problema interno, pois ele cita que o disjuntor deles abre com frequência. Solicitamos para que eles mapeiem a carga declarada da Prefeitura, e enviem para a Energisa avaliar a necessidade de melhoria na rede. Porém ficou esclarecido que não temos problemas em nossa rede. PENDENTE 3 - Débito de IP: O Prefeito e Assessor citaram sobre o "susto" que levaram após a comunicação da Energisa a respeito da cobrança de pontos de iluminação pública que não foram informados pela Prefeitura, e consequentemente não estavam cadastrados em nosso sistema. Eles citaram que não querem passar pelo mesmo problema e pediram nossa ajuda para apontar os locais onde estão fazendo a troca das lâmpadas. Informamos que esse levantamento não é de responsabilidade da Energisa, e que a própria Prefeitura deve realizar o levantamento e encaminhar para atualização da Energisa. Definimos que será agendada uma reunião com o técnico da Prefeitura para ensinarmos para ele como fazer o levantamento. (Diego Galego). PENDENTE 4 - Polo industrial: O Prefeito citou que estão criando um Pólo Industrial na cidade, e já possuem uma ideia do perfil de carga de quem irá se instalar por lá. Informamos da importância da Prefeitura levantar a carga declarada para que a Energisa faça uma avaliação geral de demanda. Além disto, cada solicitante deverá entrar com seu pedido separadamente, gerando um processo de ligação para cada empresa instalada. PENDENTE 5 - Perguntaram da possiblidade de instalarmos mais lâmpadas de LED na cidade. Respondemos que esse processo é feito dentro das chamadas públicas de eficiência energética da ANEEL, e que para a Prefeitura necessita se inscrever na próxima janela que acontecerá no mês de setembro. INFORMAÇÃO 6 - Projeto Pontos Cegos (Iluminação Pública). Solicitaram recálculo dos orçamentos de rede (só não pagaram ano passado pois estavam com poucos recursos em caixa). Pediram priorização das obras. Como elas ainda nem foram pagas, será necessária chegar uma ordem de priorização de desejo para a Prefeitura. (Levantar a relação de obras). PENDENTE 7 - Usina solar - ID 8453625 - Jean Carlos Silva Gomes. Prefeito cita que está tendo problemas para se fazer a injeção de potência e coletar os ganhos de sua GD, que pretende alugar para um Supermercado. § Identificamos que o problema nasceu por uma falta de seu projetista que não informou UC em seu projeto, e da Energisa de não devolver para que o cliente fizesse a correção. PENDENTE | S98: 46247 | X98: Monike Chaves | Y98: Gabriella Domingo | Z98: Prefeitura e Câmara: Prefeito Jean, Assessor Orlindo. | AA98: Diego Souza Silva, Emerson Seixas Costa, Thiago de Alvarenga Balbio | AB98: Não | AC98: Visita Domo de Ferro | AD98: 46268 | AE98: Moacir Costa Neto | AF98: 46247 | AG98: Gabriella Amorim Domingo | AH98: 100 | AI98: 100 | AJ98: 100 | AN98: =VLOOKUP(M98,[1]municipios!$B:$D,3,0) -> NOVA ANDRADINA | AO98: =TODAY()-E98 -> 234 | AP98: =IF(AO98<=5,"0–5 dias",IF(AO98<=15,"6–15 dias",IF(AO98<=16,"16–30 dias",IF(AO98<=30,"30–50 dias",">50 dias")))) -> >50 dias | AQ98: =IF(U98="","Dentro",(IF(IF(W98="",TODAY(),W98)<=U98,"Dentro","Fora"))) -> Dentro | AR98: =IF(U98="","Não risco",IF((TODAY()-U98)<=7,"Risco","Não risco")) -> Não risco | AS98: =IF(SEARCH("integrar",P98)>0,"Sim","Não") -> Sim | AT98: =IF(S98="",TODAY()-Q98,S98-Q98) -> 87 | AU98: =VLOOKUP(X98,'pontos focais'!C:D,2,0) -> DESC Agentes de Relacionamento | AV98: =U98-Q98 -> -46160
A99: 291 | B99: Visita Domo de Ferro | C99: Qualidade | D99: DCMD | E99: 46054 | F99: Monike Chaves | G99: Finalizada | H99: Finalizada | I99: Prefeitura de Deodápolis | L99: SUL | M99: Deodápolis | N99: Prefeitura | O99: Deodápolis | P99: Agenda de Campo - Projeto Integrar | Q99: 46160 | R99: O conjunto DEODÁPOLIS teve uma melhoria de 16% no DEC global cheio percebido pela população. | X99: Diego Souza Silva | Z99: Prefeitura e Câmara: Prefeito Jean, Assessor Orlindo. | AA99: Diego Souza Silva, Emerson Seixas Costa, Thiago de Alvarenga Balbio | AB99: Não | AC99: Visita Domo de Ferro | AD99: 46268 | AE99: Moacir Costa Neto | AF99: 46160 | AG99: Danila Hertal Moreira Souza | AH99: 100 | AI99: 100 | AJ99: 50 | AN99: =VLOOKUP(M99,[1]municipios!$B:$D,3,0) -> NOVA ANDRADINA | AO99: =TODAY()-E99 -> 234 | AP99: =IF(AO99<=5,"0–5 dias",IF(AO99<=15,"6–15 dias",IF(AO99<=16,"16–30 dias",IF(AO99<=30,"30–50 dias",">50 dias")))) -> >50 dias | AQ99: =IF(U99="","Dentro",(IF(IF(W99="",TODAY(),W99)<=U99,"Dentro","Fora"))) -> Dentro | AR99: =IF(U99="","Não risco",IF((TODAY()-U99)<=7,"Risco","Não risco")) -> Não risco | AS99: =IF(SEARCH("integrar",P99)>0,"Sim","Não") -> Sim | AT99: =IF(S99="",TODAY()-Q99,S99-Q99) -> 128 | AU99: DESC Agentes de Relacionamento | AV99: =U99-Q99 -> -46160
A100: 292 | B100: Visita Domo de Ferro | C100: Informação | D100: Central do Cliente | E100: 46063 | F100: Availdo Taveira de Oliveira | G100: Finalizada | H100: Finalizada | L100: CENTRO | M100: Jaraguari | N100: Prefeitura | O100: Jaraguari | P100: Agenda de Campo - Projeto Integrar. Card finalizado agenda em campo - Projeto Integrar - sem documentos em anexo e ou ações para direcionamentos. | Q100: 46238 | R100: Agenda de Campo - Projeto Integrar. Informação. Sem documentos em anexo e ou ações para direcionamentos. | S100: 46238 | W100: 46238 | X100: Wander Idalino Machado | Y100: Wander Machado | Z100: Sem informações | AA100: Alex Almeida Leite | AB100: Não | AC100: Visita Domo de Ferro | AD100: 46268 | AE100: Moacir Costa Neto | AF100: 46238 | AG100: Wander Idalino Machado | AH100: 100 | AI100: 100 | AJ100: 100 | AN100: =VLOOKUP(M100,[1]municipios!$B:$D,3,0) -> CAMPO GRANDE INTERIOR | AO100: =TODAY()-E100 -> 225 | AP100: =IF(AO100<=5,"0–5 dias",IF(AO100<=15,"6–15 dias",IF(AO100<=16,"16–30 dias",IF(AO100<=30,"30–50 dias",">50 dias")))) -> >50 dias | AQ100: =IF(U100="","Dentro",(IF(IF(W100="",TODAY(),W100)<=U100,"Dentro","Fora"))) -> Dentro | AR100: =IF(U100="","Não risco",IF((TODAY()-U100)<=7,"Risco","Não risco")) -> Não risco | AS100: =IF(SEARCH("integrar",P100)>0,"Sim","Não") -> Sim | AT100: =IF(S100="",TODAY()-Q100,S100-Q100) -> 0 | AU100: =VLOOKUP(X100,'pontos focais'!C:D,2,0) -> Central do Cliente | AV100: =U100-Q100 -> -46238
...

Sheet RESUMO
B3: Rótulos de Coluna | H3: Em andamento | I3: Concluídas | J3: Backlog (Não iniciada) | K3: Dentro da Expectativa
B4: Em Andamento | C4: Finalizada | D4: Não Iniciada | E4: Total Geral | H4: =B5 -> 30 | I4: =C5 -> 154 | J4: =D5 -> 26 | K4: =B13 -> 173
A5: Contagem de Status_Acao | B5: 30 | C5: 154 | D5: 26 | E5: 210 | H5: =H4/$E$5 -> 0.14285714 | I5: =I4/$E$5 -> 0.73333333 | J5: =J4/$E$5 -> 0.12380952 | K5: =K4/D13 -> 0.82380952
K7: =GETPIVOTDATA("Status_Acao",$A$8,"Expectativa","Fora")/GETPIVOTDATA("Status_Acao",$A$8) -> 0.17619048
A8: Contagem de Status_Acao | B8: Rótulos de Coluna | H8: Demandas em dentro da expectativa | I8: Demandas em fora da expectativa | J8: Demandas em risco de prazo | K8: =D10+D12 -> 56
A9: Rótulos de Linha | B9: Dentro | C9: Fora | D9: Total Geral | H9: =B12+B10 -> 44 | I9: =C12+C10 -> 12 | J9: =B21 -> 5
A10: Em Andamento | B10: 20 | C10: 10 | D10: 30 | H10: =H9/$K$8 -> 0.78571429 | I10: =I9/$K$8 -> 0.21428571 | J10: =J9/$K$8 -> 0.089285714
A11: Finalizada | B11: 129 | C11: 25 | D11: 154
A12: Não Iniciada | B12: 24 | C12: 2 | D12: 26
A13: Total Geral | B13: 173 | C13: 37 | D13: 210 | H13: Status_Acao | I13: (Vários itens)
H15: Rótulos de Linha | I15: Contagem de Status_Acao
A16: Status_Acao | B16: (Vários itens) | H16: AQUIDAUANA | I16: 1
A17: Expectativa | B17: Dentro | H17: COSTA RICA | I17: 1
H18: COXIM | I18: 3
A19: Rótulos de Linha | B19: Contagem de Risco | H19: CORUMBA | I19: 3
A20: Não risco | B20: 39 | H20: NAVIRAI | I20: 3
A21: Risco | B21: 5 | H21: CAMPO GRANDE | I21: 3
A22: Total Geral | B22: 44 | H22: JARDIM | I22: 4
H23: RIO BRILHANTE | I23: 4
E24: Tipologia | H24: NOVA ANDRADINA | I24: 4
H25: DOURADOS | I25: 6
A26: Status_Acao | B26: (Vários itens) | H26: PARANAIBA | I26: 6
H27: PONTA PORA | I27: 8
A28: Rótulos de Linha | B28: Contagem de Tipologia | H28: CAMPO GRANDE INTERIOR | I28: 10
A29: Informação | B29: 2 | H29: Total Geral | I29: 56
A30: Vazio | B30: 3
A31: Poda | B31: 4
A32: Atendimento Comercial | B32: 5
A33: Manutenção | B33: 9
A34: Qualidade | B34: 13
A35: Obra | B35: 20
A36: Total Geral | B36: 56 | E36: 65
E37: 69 | F37: =E37-E36 -> 4
E38: =4/E37 -> 0.057971014 | F38: =F37/E37 -> 0.057971014
A41: Status_Acao | B41: (Vários itens)
A43: Rótulos de Linha | B43: Contagem de Area
A44: Vazio | B44: 0.017857143
A45: DESC | B45: 0.16071429
A46: DEOP | B46: 0.19642857
A47: DCMD | B47: 0.625
A48: Total Geral | B48: 1
A53: Status_Acao | B53: (Vários itens)
A55: Rótulos de Linha | B55: Contagem de Area
A56: Central do Cliente | B56: 1
A57: DECP - Ligação GA | B57: 1
A58: DCMD Orçamento e Projetos | B58: 1
A59: DESC Ofícios | B59: 2
A60: DESC Agentes de Relacionamento | B60: 7 | H60: AGING | K60: Risco | L60: Risco
A61: DEOP Qualidade | B61: 10 | H61: Status_Acao | I61: (Vários itens) | K61: Status_Acao | L61: (Vários itens)
A62: DCMD Manutenção | B62: 16
A63: DCMD Programação de Obra | B63: 18 | H63: Rótulos de Linha | I63: Contagem de Area | K63: Rótulos de Linha | L63: Contagem de Area
A64: Total Geral | B64: 56 | H64: 0–5 dias | I64: 0.035714286 | K64: DCMD Orçamento e Projetos | L64: 1
H65: >50 dias | I65: 0.76785714 | K65: DCMD Programação de Obra | L65: 7
H66: 30–50 dias | I66: 0.16071429 | K66: DECP - Ligação GA | L66: 1
H67: 6–15 dias | I67: 0.035714286 | K67: Total Geral | L67: 9
H68: Total Geral | I68: 1
I72: % da carteira
H73: > 50 dias | I73: 0.72
H74: 30-50 dias | I74: 0.08
H75: 16–30 dias | I75: 0.02
H76: 6–15 dias | I76: 0.09 | M76: Expectativa | N76: (Tudo)
A77: Expectativa | B77: (Tudo) | D77: Expectativa | E77: (Tudo) | H77: 0–5 dias | I77: 0.09 | M77: Status_Acao | N77: (Vários itens)
A78: Status_Acao | B78: (Vários itens) | D78: Status_Acao | E78: (Vários itens) | I78: =SUM(I73:I77) -> 1
M79: Rótulos de Linha | N79: Contagem de Area
A80: Rótulos de Linha | B80: Contagem de Area | D80: Rótulos de Linha | E80: Contagem de Area | M80: Mundo Novo | N80: 1
A81: Prefeitura | B81: 113 | D81: Projeto Elétrico | E81: 1 | M81: Rio Brilhante | N81: 1
A82: Câmara | B82: 50 | D82: Ordem de Serviço | E82: 2 | M82: Jardim | N82: 1
A83: Diretoria | B83: 26 | D83: Vazio | E83: 4 | M83: Ivinhema | N83: 1
A84: ALEMS | B84: 18 | D84: Poda | E84: 11 | M84: Rochedo | N84: 1
A85: Governo do Estado | B85: 2 | D85: Manutenção | E85: 15 | M85: Corguinho | N85: 1
A86: Mídia | B86: 1 | D86: Qualidade | E86: 32 | M86: Aral Moreira | N86: 1
A87: Total Geral | B87: 210 | D87: Informação | E87: 40 | M87: ELDORADO | N87: 1
D88: Atendimento Comercial | E88: 52 | M88: Nioaque | N88: 1
D89: Obra | E89: 53 | M89: Aquidauana | N89: 1
B90: Integrar | D90: Total Geral | E90: 210 | M90: Caarapó | N90: 1
N91: 1
A92: Status_Acao | B92: (Vários itens) | M92: Bandeirantes | N92: 1
A93: Integrar | B93: Sim | D93: Status_Acao | E93: (Vários itens) | M93: Costa Rica | N93: 1
M94: Laguna Carapã | N94: 1
A95: Rótulos de Linha | B95: Contagem de Area | D95: Rótulos de Linha | E95: Contagem de Area | M95: Paranaíba | N95: 2
A96: Atendimento Comercial | B96: 13 | D96: Atendimento Comercial | E96: 5 | M96: Miranda | N96: 2
A97: Informação | B97: 8 | D97: Informação | E97: 2 | M97: Vicentina | N97: 2
A98: Obra | B98: 1 | D98: Manutenção | E98: 7 | M98: Alcinópolis | N98: 2
A99: Poda | B99: 1 | D99: Obra | E99: 20 | M99: Glória de Dourados | N99: 2
A100: Qualidade | B100: 3 | D100: Poda | E100: 3 | M100: Anastácio | N100: 2
A101: Vazio | B101: 1 | D101: Qualidade | E101: 10 | M101: Paraíso das Águas | N101: 2
A102: Total Geral | B102: 27 | D102: Vazio | E102: 3 | M102: Rio Negro | N102: 2
D103: Total Geral | E103: 50 | M103: Antônio João | N103: 2
M104: Bela Vista | N104: 2
D105: Expectativa | E105: (Vários itens) | M105: Jaraguari | N105: 3
A106: Expectativa | B106: Fora | D106: Risco | E106: Risco | H106: Área | I106: Fora da Expectativa | J106: Riscos | K106: Total | M106: Tacuru | N106: 3
A107: Status_Acao | B107: (Vários itens) | D107: Status_Acao | E107: (Vários itens) | H107: DCMD Manutenção | I107: 1 | J107: 0 | K107: =SUM(I107:J107) -> 1 | M107: Terenos | N107: 3
H108: DCMD Orçamento e Projetos | I108: 1 | J108: 0 | K108: =SUM(I108:J108) -> 1 | M108: Angélica | N108: 3
A109: Área | B109: Qtd | D109: Área | E109: Contagem de Area | H109: DCMD Programação de Obra | I109: 1 | J109: 4 | K109: =SUM(I109:J109) -> 5 | M109: Deodápolis | N109: 3
A110: DCMD Manutenção | B110: 1 | D110: DCMD Orçamento e Projetos | E110: 1 | H110: DEOP Qualidade | I110: 1 | J110: 0 | K110: =SUM(I110:J110) -> 1 | M110: Nova Alvorada do Sul | N110: 3
A111: DCMD Programação de Obra | B111: 9 | D111: DCMD Programação de Obra | E111: 4 | H111: Total Geral | I111: =SUM(I107:I110) -> 4 | J111: =SUM(J107:J110) -> 4 | K111: =SUM(K107:K110) -> 8 | M111: Coronel Sapucaia | N111: 3
A112: DESC Agentes de Relacionamento | B112: 1 | D112: Total Geral | E112: 5 | M112: Fátima do Sul | N112: 3
A113: DECP - Ligação GA | B113: 1 | M113: Aparecida do Taboado | N113: 3
A114: Total Geral | B114: 12 | M114: Dois Irmãos do Buriti | N114: 4
M115: Coxim | N115: 4
...

Sheet Analitico
A1: ID | B1: Tipologia | C1: Data_Manifestacao | D1: Status_Acao | E1: Cliente | F1: UC | G1: Obra_Const_Man | H1: Regional | I1: Localidade | J1: Poder | K1: Prefeitura | L1: Manifestação | M1: Resposta_Area | N1: Resp_Tratativa | O1: Participantes_Municipio | P1: Peso_Geral | Q1: Processo | R1: Previsao | S1: Sub_Areas | T1: Supervisão | U1: SLA | V1: Area 2
A2: 298 | B2: Atendimento Comercial | C2: 45982 | D2: Não Iniciada | E2: Prefeitura de Inocência | H2: CENTRO | I2: Inocência | J2: Prefeitura | K2: Inocência | L2: Reunião Institucional | N2: Luan Henrique Soares Diniz Afonso | P2: 50 | T2: PARANAIBA | U2: 126 | V2: DEOP Qualidade
A3: 449 | B3: Qualidade | C3: 45992 | D3: Em Andamento | H3: CENTRO | I3: Inocência | J3: Câmara | K3: Inocência | L3: Origem Externa: Câmara Municipal de Inocência Nome do Solicitante: Valmes José de Carvalho Número Ofício: 279/2025/GAB/CMI Os: 479315607 Manifestação: Ofício encaminha solicitação de estudo visando solucionar as constantes quedas de energia na Rua Francklin Gomes da Silva, Jardim Bocaina, no município de Incoência. Domo de ferro: Foi realizado visita in loco pelo Dian, conversado com o Vice Prefeito Henrique e foi levantado as seguintes informações relacionadas a qualidade: Religamentos no município todo dia das 18 às 20hrs, Fábrica de gelo com oscilação e queima de equipamentos, trecho TD 734803 e Quedas de energia na R: Pernambuco em frente ao Mercado M & M, casa da vereadora Joceana. Status atual: Em atuação campo (DEOP/DCMD) | N3: Evair Rogerio da Conceicao | P3: 25 | T3: PARANAIBA | U3: 74 | V3: DCMD Manutenção
A4: 457 | B4: Manutenção | C4: 46000 | D4: Em Andamento | F4: 2496509 | H4: CENTRO | I4: Inocência | J4: Câmara | K4: Inocência | L4: Origem Externa: Visita in loco Nome do Solicitante: Vereador Shell Número Ofício: N/A OS: N/A Manifestação: Foi realizado a visita in loco pelo Dian e foi recebido a demanda de manutenção na UC 2496509, trata-se de um produtor de leite. UC 2496509 - Fazenda Santa Maria (Inocência) | N4: Evair Rogerio da Conceicao | P4: 25 | T4: PARANAIBA | U4: 74 | V4: DCMD Manutenção
A5: 456 | B5: Poda | C5: 46000 | D5: Em Andamento | H5: CENTRO | I5: Sidrolândia | J5: Prefeitura | K5: Sidrolândia | L5: Origem Externa: Visita in loco Nome do Solicitante: Secretário de Obras Sr. Cleyton Número Ofício: N/A OS: N/A Manifestação: Foi realizado a visita in loco no município pelo Giovani e foi coletada a demanda de poda no Assentamento Eldorado II. Município Sidrolândia | N5: Evair Rogerio da Conceicao | P5: 100 | T5: CAMPO GRANDE INTERIOR | U5: 74 | V5: DCMD Manutenção
A6: 455 | B6: Manutenção | C6: 46000 | D6: Em Andamento | H6: NORTE | I6: BONITO | J6: Prefeitura | K6: Bonito | L6: Origem Externa: Visita in loco Nome do Solicitante: Prefeitura Número Ofício: N/A OS: N/A Manifestação: Em visita realizada no município pelo Dian foram coletadas algumas demandas, segue as demandas solicitadas: Limpeza de faixa mecanizada - LM entre ID 9070606 e ID 9070607 (CRÍTICO), Lançado 450 MTS LIMPEZA de faixa LM entre ID 8615174 e ID 9046178 (URGENTE), Lançado 220 MTS limpeza de faixa LM entre ID 135469229 e ID 9046694 (URGENTE) e Lançado 300 MTS limpeza de faixa LM entre ID 9553699 e ID 9563035 (URGENTE) | N6: Evair Rogerio da Conceicao | P6: 100 | T6: JARDIM | U6: 74 | V6: DCMD Manutenção
A7: 448 | B7: Poda | C7: 46000 | D7: Em Andamento | H7: SUL | I7: Nova Alvorada do Sul | J7: Prefeitura | K7: Nova Alvorada do Sul | L7: Origem Externa: Visita in loco Nome do Solicitante: Prefeito Sr. José Paulo, Vereadores Junior Beraldi, Rodrigo Cowboi, Rozidalia Reis, Nelson Fernandes secretário de Obras, Valdemar Rocha Vice-Prefeito, Leandro Barbosa Presidente do sindicato Rural, Sandra Pereira da associação comercial, Giliani Rodrigues, Emanuel e Sintia representantes da Indústria Atvos. Número Ofício: N/A OS: N/A Manifestação: Foi realizado a visita in loco pelo Giovani e foi recebido a demanda de podas de árvores no trecho da BR 163 localizada entre Nova Alvorada do Sul e a Ponte seca. | M7: QUAL STATUS DAS AÇÕES DE CAMPO? | N7: Evair Rogerio da Conceicao | P7: 100 | T7: RIO BRILHANTE | U7: 74 | V7: DCMD Manutenção
A8: 458 | B8: Manutenção | C8: 46001 | D8: Em Andamento | H8: CENTRO | I8: Ribas do Rio Pardo | J8: Prefeitura | K8: Ribas do Rio Pardo | L8: Origem Externa: Visita in loco Nome do Solicitante: Prefeito Roberson e a Vereadora e Presidente da Câmara Sra. Tânia Número Ofício: N/A OS: N/A Manifestação: Foi realizado a visita in loco pelo Giovani e foi recebido a demanda de poda na faixa de servidão no Ass. Nossa Senhora das Graças no município de Ribas do Rio Pardo. | N8: Evair Rogerio da Conceicao | P8: 100 | T8: CAMPO GRANDE INTERIOR | U8: 74 | V8: DCMD Manutenção
A9: 459 | B9: Qualidade | C9: 46001 | D9: Não Iniciada | E9: Prefeitura Municipal Bonito | H9: NORTE | I9: BONITO | J9: Prefeitura | K9: Bonito | L9: Origem Externa: Visita in loco Nome do Solicitante: Prefeitura municipal Número Ofício: N/A OS: N/A Manifestação: Foi realizado a visita in loco pelo Dian e foi recebido a demanda de qualidade no fornecimento - Gruta do Lago Azul, Pousada Boyra, Bon Bom no município de Bonito. | N9: Luan Henrique Soares Diniz Afonso | P9: 50 | Q9: Qualidade do produto | S9: DEOP - QUALIDADE | T9: JARDIM | U9: 34 | V9: DEOP Qualidade
A10: 332 | B10: Qualidade | C10: 46080 | D10: Não Iniciada | E10: Prefeitura de Batayorã | F10: 197686 | H10: SUL | I10: Batayporã | J10: Prefeitura | K10: Batayporã | L10: Prefeito Germino, informou que esteve com Presidente Paulo, para falar sobre qualidade de serviços prestados e na demora do restabelecimento principalmente em áreas rurais. Ele não concordou com o orçamento enviado para relocação do poste, que estavam colcoando cabo protegido e a rede era cabo nu, que não arcaria com custo uma vez a energisa, tomando a iniciativa de melhorar o cabeamento, orçamento foi corrigido e enviado o nova ele. | N10: Evair Rogerio da Conceicao | O10: Prefeito Vice Prefeito Energisa Secretário de Obras | P10: 50 | T10: NOVA ANDRADINA | U10: 49 | V10: DCMD Manutenção
A11: 332 | B11: Manutenção | C11: 46080 | D11: Não Iniciada | E11: Prefeitura de Batayorã | F11: 197686 | H11: SUL | I11: Batayporã | J11: Prefeitura | K11: Batayporã | L11: Prefeito Germino, informou que esteve com Presidente Paulo, para falar sobre qualidade de serviços prestados e na demora do restabelecimento principalmente em áreas rurais. Ele não concordou com o orçamento enviado para relocação do poste, que estavam colcoando cabo protegido e a rede era cabo nu, que não arcaria com custo uma vez a energisa, tomando a iniciativa de melhorar o cabeamento, orçamento foi corrigido e enviado o nova ele. | N11: Evair Rogerio da Conceicao | O11: Prefeito Vice Prefeito Energisa Secretário de Obras | P11: 50 | Q11: Manutenção e Poda | S11: DCMD - PODA E MANUTENÇÃO | T11: NOVA ANDRADINA | U11: 13 | V11: DCMD Manutenção
A12: 1022 | B12: Qualidade | C12: 46083 | D12: Não Iniciada | F12: 30723 | H12: NORTE | I12: Corumbá | J12: Diretoria | K12: Corumbá | L12: Em 02/03/2026 - realizada reunião presencial na Energisa com os diretores da SANESUL para tratar da qualidade de fornecimento das unidades de Corumbá. Conforme documento anexo, cliente reclama de constantes oscilações no fornecimento de energia elétrica nas unidades de Corumbá. | N12: Luan Henrique Soares Diniz Afonso | O12: RENATO MARCILIO DA SILVA | P12: 100 | T12: CORUMBA | U12: 43 | V12: DEOP Qualidade
A13: 670 | B13: Qualidade | C13: 46084 | D13: Em Andamento | F13: 9000076 | H13: NORTE | I13: Corumbá | J13: Diretoria | K13: Corumbá | L13: Origem Externa: SANESUL Nome do Solicitante: RENATO MARCILIO DA SILVA Número Ofício: 6226/2025/PSEC/ALEMS Manifestação: Em 02/03/2026 - realizada reunião presencial na Energisa com os diretores da SANESUL para tratar da qualidade de fornecimento das unidades de Corumbá. Conforme documento anexo, cliente reclama de constantes oscilações no fornecimento de energia elétrica nas unidades de Corumbá. No Município não existem poços profundos, assim toda a produção de agua para o sistema ocorre através de captação superficial direto do rio Paraguai. UCs: 9000076 1717627 30723 1699438 1702111 1698960 1142916 Segue ofício em anexo. | N13: Luan Henrique Soares Diniz Afonso | P13: 100 | T13: CORUMBA | U13: 36 | V13: DEOP Qualidade
A14: 670 | B14: Vazio | C14: 46084 | D14: Em Andamento | E14: Sanesul | F14: 9000076 | H14: NORTE | I14: Corumbá | J14: Diretoria | K14: Corumbá | L14: Origem Externa: SANESUL Nome do Solicitante: RENATO MARCILIO DA SILVA Número Ofício: 6226/2025/PSEC/ALEMS Manifestação: Em 02/03/2026 - realizada reunião presencial na Energisa com os diretores da SANESUL para tratar da qualidade de fornecimento das unidades de Corumbá. Conforme documento anexo, cliente reclama de constantes oscilações no fornecimento de energia elétrica nas unidades de Corumbá. No Município não existem poços profundos, assim toda a produção de agua para o sistema ocorre através de captação superficial direto do rio Paraguai. UCs: 9000076 1717627 30723 1699438 1702111 1698960 1142916 Segue ofício em anexo. | N14: Julio Cesar dos Santos Antonelo | P14: 50 | S14: CGCP | T14: CORUMBA | U14: 12 | V14: DESC Agentes de Relacionamento
A15: 708 | B15: Poda | C15: 46085 | D15: Em Andamento | H15: CENTRO | I15: Jaraguari | J15: Assembleia Legislativa | K15: Jaraguari | L15: Audiência Pública - Zeca do PT (Jaraguari e Sonora). Reclamação de qualidade de fornecimento sobre frequência de falta de energia. Origem: Audiência Pública Dep. Estadual Zeca do PT 3701152 -Jaraguari 917743 - Sonora | N15: Evair Rogerio da Conceicao | O15: Audiência Pública - Zeca do PT (Jaraguari e Sonora) | P15: 100 | T15: CAMPO GRANDE INTERIOR | U15: 60 | V15: DCMD Manutenção
A16: 675 | B16: Manutenção | C16: 46092 | D16: Em Andamento | F16: 158916 | H16: SUL | I16: Amambai | J16: Diretoria | K16: Amambai | L16: Solicitação feita pelo Diretor Matos - Reclamação de constante queda, acionado o time de manutenção. UC 158916 - Fazenda Arrozal (Amambai) | N16: Evair Rogerio da Conceicao | P16: 100 | T16: PONTA PORA | U16: 61 | V16: DCMD Manutenção
A17: 707 | B17: Qualidade | C17: 46125 | D17: Não Iniciada | E17: Itahum Export Comercio de Cereais Ltda | F17: 3456606 | H17: SUL | I17: Ponta Porã | J17: Diretoria | K17: Ponta Porã | L17: Nome do Solicitante: Gabriel da Silva Mendonça Cliente Miguela Luiza Rufino dos Santos Barcelos Manna publicou uma reclamação publica, reclama de constantes quedas de energia na UC 10/3456606-7 no endereço: Rua Heitor Laburu nº 200 bairro: Jardim Itatiaia região urbana. Segue anexo. Diagnóstico Qualidade. | N17: Luan Henrique Soares Diniz Afonso | P17: 50 | Q17: Qualidade do produto | S17: DEOP - QUALIDADE | T17: PONTA PORA | U17: 34 | V17: DEOP Qualidade
A18: 56 | B18: Atendimento Comercial | C18: 46135 | D18: Em Andamento | E18: Vandereli Oliveira Domingos | F18: 2476949 | H18: SUL | I18: Amambai | J18: Câmara | K18: Amambai | L18: Vereadores pedem apoio com a obra para atendimento ao aumento de carga da UC 2486949, horta hidropônica de grande porte da região. apresentado o Ofício 094/2026 | N18: Jessika da Silva Arruda de Paula | O18: Vereador Darci Jose da Silva Vereador Jota Roberto Vereador Suzana Ulisses Joao Pedro (Projetista) Vandereli Oliveira Domingos (Cliente | P18: 12.5 | T18: PONTA PORA | U18: 31 | V18: DESC Ofícios
A19: 942 | B19: Poda | C19: 46136 | D19: Não Iniciada | H19: CENTRO | I19: Corguinho | J19: Prefeitura | K19: Corguinho | L19: Visita realizada pelo Projeto Integrar - Registro ID 74 | N19: Evair Rogerio da Conceicao | O19: Fabricio Silva | P19: 100 | T19: CAMPO GRANDE INTERIOR | U19: 19 | V19: DCMD Manutenção
A20: 723 | B20: Manutenção | C20: 46146 | D20: Em Andamento | F20: 1937031 | H20: SUL | I20: Maracaju | J20: Câmara | K20: Maracaju | L20: Queda frequente de energia - rede desta unidade é de Itahum do outro lado do rio, o que foi cogitado nas reuniões foi futuramente uma rede nova que seja do sentido Maracaju aonde fic localizada a propriedade - ASSUNTO SERÁ PROSSEGUIDO COM DIAN DEVIDO JÁ TER CONHECIMENTO DO ASSUNTO. | N20: Evair Rogerio da Conceição | P20: 25 | T20: RIO BRILHANTE | U20: 70 | V20: DCMD Manutenção
A21: 550 | B21: Qualidade | C21: 46154 | D21: Não Iniciada | F21: 3742758 | H21: SUL | I21: Dourados | J21: Câmara | K21: Dourados | L21: Origem: Agente de relacionamento Giovani Moura Vereador solicitou revisão no sistema elétrico nos bairros Novo Horizonte e Altos do Indaiá em Dourados. Protocolo 9500628194. UC 3742758. Em atuação Campo (DEOP/DCMD). | N21: Luan Henrique Soares Diniz Afonso | O21: Vereador. | P21: 25 | T21: DOURADOS | U21: 69 | V21: DESC Agentes de Relacionamento
